Workbook

Sheet 00_Методика
A1: Методика оценки объема рынка через количество потенциальных клиентов
A3: Назначение Excel-шаблона
A4: Цель | B4: Рассчитать оценочный объем рынка электронного бизнеса через количество потенциальных клиентов, коэффициенты сужения, средний чек, частоту покупки и достижимую долю рынка.
A5: Логика | B5: 1) определить клиентские сегменты; 2) задать исходное число потенциальных клиентов; 3) сузить базу по границам рынка, потребности, цифровой готовности и платежеспособности; 4) рассчитать SAM; 5) задать достижимую долю и получить SOM.
A6: Ключевая формула | B6: Объем рынка = количество клиентов × доля соответствия границам × доля потребности × доля цифровой готовности × доля платежеспособности × средний чек × частота покупки.
A7: Применение | B7: Подходит для B2B-услуг, B2C-продуктов, электронных сервисов и платформ, если можно определить базу потенциальных клиентов.
A8: Ограничение | B8: Расчет является оценочным. Все коэффициенты должны подтверждаться источниками: статистикой, Similarweb, Google Trends, Яндекс Вордстат, рекламными кабинетами, конкурентным анализом, опросами или экспертными допущениями.
A10: Порядок работы с файлом
A11: Шаг | B11: Действие | C11: Лист | D11: Результат
A12: 1 | B12: Заполнить исходные параметры бизнес-идеи, географии, валюты и периода расчета. | C12: 01_Параметры | D12: Зафиксированы границы расчета.
A13: 2 | B13: Заполнить клиентские сегменты и коэффициенты сужения. | C13: 02_Сегменты | D13: Получены TAM, SAM и SOM по сегментам.
A14: 3 | B14: Проверить осторожный, базовый и оптимистичный сценарии. | C14: 03_Сценарии | D14: Получен диапазон возможного объема рынка.
A15: 4 | B15: Сопоставить расчет с цифровыми данными конкурентов из Similarweb. | C15: 05_Similarweb | D15: Проверена реалистичность цифрового спроса.
A16: 5 | B16: Посмотреть итоговую панель, выводы и контрольные индикаторы. | C16: 06_Дашборд | D16: Получен итоговый результат для отчета.
A17: 6 | B17: Зафиксировать источники и степень надежности данных. | C17: 07_Источники | D17: Обеспечена воспроизводимость расчета.
A20: Интерпретация итоговых показателей
A21: Показатель | B21: Как читать
A22: TAM | B22: Максимальный потенциальный объем спроса до сужения по реальным ограничениям выбранного рынка.
A23: SAM | B23: Объем рынка в выбранных продуктовых и географических границах с учетом потребности, цифровой готовности и платежеспособности.
A24: SOM | B24: Часть SAM, которую новый бизнес может реалистично привлечь в выбранном периоде.
A25: Расчет через Similarweb | B25: Проверочный ориентир по цифровой активности конкурентов и объему трафика в выбранном сегменте.
A26: Сценарии | B26: Диапазон неопределенности: осторожная, базовая и оптимистичная оценка.

Sheet 01_Параметры
A1: Исходные параметры расчета
A3: Параметр | B3: Значение | C3: Комментарий | D3: Источник / обоснование
A4: Название бизнес-идеи | B4: TableMind: онлайн-сервис независимой проверки (аудита) Excel-моделей | C4: Можно заменить на свою бизнес-идею | D4: Паспорт бизнес-идеи
A5: Компетенция | B5: Проверка таблиц и финансовых моделей | C5: Профессиональная основа бизнеса | D5: Исходная гипотеза
A6: Продуктовые границы | B6: Веб-аудит файла Excel и надстройка: поиск ошибок формул, структуры и логики; тарифы Free, 9 EUR, Pro 19 EUR, Team 29 EUR | C6: Что входит в анализируемый рынок | D6: Методика фиксации границ рынка
A7: Географические границы | B7: Англоязычные страны (США, Великобритания, Канада, Австралия, Ирландия) и ЕС-27; контрольная территория Беларусь и русскоязычный сегмент | C7: Территория первичного расчета | D7: Выбранная территория анализа
A8: Тип рынка | B8: B2B и B2C (профессионалы и малый бизнес), подписка freemium | C8: Основной клиент — организация или предприниматель | D8: Описание модели бизнеса
A9: Валюта | B9: EUR | C9: Курс НБРБ 03.10.2026: 1 EUR = 3,3860 BYN | D9: Допущение
A10: Период расчета | B10: 1 год | C10: Все итоговые показатели приводятся в годовом выражении | D10: Допущение
A11: Дата составления | B11: 46298 | C11: Дата версии расчета | D11: Автоматически / вручную
A12: Ответственный | B12: Р. В. Земляник, гр. 60131 | C12: ФИО или группа
A15: Единицы интерпретации
A16: Единица | B16: Значение
A17: Количество клиентов | B17: Количество организаций, ИП, домохозяйств или пользователей в выбранном сегменте.
A18: Коэффициент сужения | B18: Доля от 0 до 100 %, показывающая, какая часть базы реально относится к выбранному рынку.
A19: Средний чек | B19: Средний платеж за одну покупку или договор.
A20: Частота покупки | B20: Среднее число покупок или оплат в год.
A21: SAM | B21: Доступный объем рынка в выбранных границах.
A22: SOM | B22: Реалистично достижимый объем рынка для нового бизнеса.

Sheet 02_Сегменты
A1: Расчет объема рынка через количество потенциальных клиентов по сегментам
A3: Сегмент клиентов | B3: Тип клиента | C3: Источник количества | D3: Потенциальных клиентов всего | E3: Доля соответствия границам рынка | F3: Клиентов в границах рынка | G3: Доля имеющих потребность | H3: Доля готовых покупать онлайн | I3: Доля платежеспособных | J3: Реально адресуемых клиентов | K3: Средний чек | L3: Покупок в год | M3: SAM: доступный объем рынка | N3: Достижимая доля нового бизнеса | O3: SOM: достижимый объем | P3: Надежность данных | Q3: Комментарий
A4: Финансовые аналитики и FP&A | B4: B2B/B2C | C4: BLS 2025 (США) и масштаб по занятости | D4: 1218525 | E4: 0.7 | F4: =D4*E4 -> 852967.5 | G4: 0.3 | H4: 0.6 | I4: 0.35 | J4: =F4*G4*H4*I4 -> 53736.952 | K4: 120 | L4: 1 | M4: =J4*K4*L4 -> 6448434.3 | N4: 0.0015 | O4: =M4*N4 -> 9672.6514 | P4: Средняя | Q4: Модели строят и проверяют сами; платит чаще работодатель (Pro или Team).
A5: Бухгалтеры и аудиторы | B5: B2B/B2C | C5: BLS 2025 (США) и масштаб по занятости | D5: 4386800 | E5: 0.35 | F5: =D5*E5 -> 1535380 | G5: 0.2 | H5: 0.6 | I5: 0.3 | J5: =F5*G5*H5*I5 -> 55273.68 | K5: 70 | L5: 1 | M5: =J5*K5*L5 -> 3869157.6 | N5: 0.001 | O5: =M5*N5 -> 3869.1576 | P5: Средняя | Q5: В границы входят только работающие со сложными таблицами; часто разовый аудит.
A6: Консультанты по управлению | B6: B2B/B2C | C6: BLS 2025 (США) и масштаб по занятости | D6: 2962025 | E6: 0.4 | F6: =D6*E6 -> 1184810 | G6: 0.3 | H6: 0.7 | I6: 0.4 | J6: =F6*G6*H6*I6 -> 99524.04 | K6: 180 | L6: 1 | M6: =J6*K6*L6 -> 17914327 | N6: 0.0015 | O6: =M6*N6 -> 26871.491 | P6: Низкая | Q6: Проверка чужих моделей клиентов; высокая готовность платить.
A7: МСП с финансовой функцией | B7: B2B/B2C | C7: SBA 2025, UK BPE 2025, ЕК 2025/2026 и допущения | D7: 17415635 | E7: 0.03 | F7: =D7*E7 -> 522469.05 | G7: 0.3 | H7: 0.6 | I7: 0.3 | J7: =F7*G7*H7*I7 -> 28213.329 | K7: 240 | L7: 1 | M7: =J7*K7*L7 -> 6771198.9 | N7: 0.0005 | O7: =M7*N7 -> 3385.5994 | P7: Низкая | Q7: Покупка Team на 2-3 места; основатели и операционные менеджеры.
A8: Резерв | B8: B2B | C8: не используется | D8: 0 | E8: 0 | F8: =D8*E8 -> 0 | G8: 0 | H8: 0 | I8: 0 | J8: =F8*G8*H8*I8 -> 0 | K8: 0 | L8: 0 | M8: =J8*K8*L8 -> 0 | N8: 0 | O8: =M8*N8 -> 0 | P8: Нет данных | Q8: Свободная строка шаблона.
A9: Резерв | B9: B2B | C9: не используется | D9: 0 | E9: 0 | F9: =D9*E9 -> 0 | G9: 0 | H9: 0 | I9: 0 | J9: =F9*G9*H9*I9 -> 0 | K9: 0 | L9: 0 | M9: =J9*K9*L9 -> 0 | N9: 0 | O9: =M9*N9 -> 0 | P9: Нет данных | Q9: Свободная строка шаблона.
A10: Резерв | B10: B2B | C10: не используется | D10: 0 | E10: 0 | F10: =D10*E10 -> 0 | G10: 0 | H10: 0 | I10: 0 | J10: =F10*G10*H10*I10 -> 0 | K10: 0 | L10: 0 | M10: =J10*K10*L10 -> 0 | N10: 0 | O10: =M10*N10 -> 0 | P10: Нет данных | Q10: Свободная строка шаблона.
A12: Итого | D12: =SUM(D4:D10) -> 25982985 | F12: =SUM(F4:F10) -> 4095626.5 | J12: =SUM(J4:J10) -> 236748 | M12: =SUM(M4:M10) -> 35003118 | O12: =SUM(O4:O10) -> 43798.899

Sheet 03_Сценарии
A1: Сценарная оценка объема рынка
A3: Сценарий | B3: Множитель потребности | C3: Множитель онлайн-готовности | D3: Множитель платежеспособности | E3: Множитель среднего чека | F3: Множитель частоты покупки | G3: Достижимая доля | H3: TAM | I3: SAM | J3: SOM | K3: Комментарий
A4: Осторожный | B4: 0.75 | C4: 0.8 | D4: 0.75 | E4: 0.8 | F4: 0.8 | G4: 0.0005 | H4: =SUMPRODUCT('02_Сегменты'!$D$4:$D$10,'02_Сегменты'!$K$4:$K$10,'02_Сегменты'!$L$4:$L$10)*E4*F4 -> 3306378176 | I4: =SUMPRODUCT('02_Сегменты'!$F$4:$F$10,'02_Сегменты'!$G$4:$G$10,'02_Сегменты'!$H$4:$H$10,'02_Сегменты'!$I$4:$I$10,'02_Сегменты'!$K$4:$K$10,'02_Сегменты'!$L$4:$L$10)*B4*C4*D4*E4*F4 -> 10080898 | J4: =I4*G4 -> 5040.449 | K4: Низкие коэффициенты потребности, готовности и платежеспособности; осторожный выход на рынок.
A5: Базовый | B5: 1 | C5: 1 | D5: 1 | E5: 1 | F5: 1 | G5: 0.0013 | H5: =SUMPRODUCT('02_Сегменты'!$D$4:$D$10,'02_Сегменты'!$K$4:$K$10,'02_Сегменты'!$L$4:$L$10)*E5*F5 -> 5166215900 | I5: =SUMPRODUCT('02_Сегменты'!$F$4:$F$10,'02_Сегменты'!$G$4:$G$10,'02_Сегменты'!$H$4:$H$10,'02_Сегменты'!$I$4:$I$10,'02_Сегменты'!$K$4:$K$10,'02_Сегменты'!$L$4:$L$10)*B5*C5*D5*E5*F5 -> 35003118 | J5: =I5*G5 -> 45504.053 | K5: Основной расчет на базе листа сегментов.
A6: Оптимистичный | B6: 1.2 | C6: 1.15 | D6: 1.2 | E6: 1.15 | F6: 1.1 | G6: 0.003 | H6: =SUMPRODUCT('02_Сегменты'!$D$4:$D$10,'02_Сегменты'!$K$4:$K$10,'02_Сегменты'!$L$4:$L$10)*E6*F6 -> 6.5352631e+09 | I6: =SUMPRODUCT('02_Сегменты'!$F$4:$F$10,'02_Сегменты'!$G$4:$G$10,'02_Сегменты'!$H$4:$H$10,'02_Сегменты'!$I$4:$I$10,'02_Сегменты'!$K$4:$K$10,'02_Сегменты'!$L$4:$L$10)*B6*C6*D6*E6*F6 -> 73325932 | J6: =I6*G6 -> 219977.8 | K6: Высокая конверсия в платящих, больше мест в Team, заметная доля рынка.

Sheet 04_Расчет
A1: Итоговые расчетные показатели по методу потенциальных клиентов
A3: Показатель | B3: Формула / источник | C3: Значение | D3: Интерпретация
A4: TAM по базовому подходу | B4: SUMPRODUCT(потенциальные клиенты × средний чек × частота) | C4: =SUMPRODUCT('02_Сегменты'!$D$4:$D$10,'02_Сегменты'!$K$4:$K$10,'02_Сегменты'!$L$4:$L$10) -> 5166215900 | D4: Максимальный ориентир до сужения рынка.
A5: Клиенты в границах рынка | B5: Сумма клиентов после продуктово-географического сужения | C5: ='02_Сегменты'!F12 -> 4095626.5 | D5: Потенциальная база в выбранных границах.
A6: Реально адресуемые клиенты | B6: Сумма после учета потребности, онлайн-готовности и платежеспособности | C6: ='02_Сегменты'!J12 -> 236748 | D6: Практически доступная клиентская база.
A7: SAM | B7: Реально адресуемые клиенты × средний чек × частота | C7: ='02_Сегменты'!M12 -> 35003118 | D7: Доступный объем рынка.
A8: SOM | B8: SAM × достижимая доля | C8: ='02_Сегменты'!O12 -> 43798.899 | D8: Реалистичный объем для нового бизнеса.
A9: Доля SOM в SAM | B9: SOM / SAM | C9: =IFERROR(C8/C7,0) -> 0.0012512857 | D9: Оценка амбициозности выхода на рынок.
A12: Коэффициенты качества расчета
A13: Проверка | B13: Расчет | C13: Значение | D13: Как интерпретировать
A14: Доля реально адресуемых клиентов | B14: реально адресуемые / клиенты в границах | C14: =IFERROR(C6/C5,0) -> 0.057805075 | D14: Если значение слишком высокое, коэффициенты могли быть завышены.
A15: Средний SAM на одного адресуемого клиента | B15: SAM / реально адресуемые клиенты | C15: =IFERROR(C7/C6,0) -> 147.84969 | D15: Показывает среднюю годовую выручку на клиента.
A16: Сравнение SOM и Similarweb-ориентира | B16: SOM / оценочная годовая выручка конкурентов | C16: =IFERROR(C8/'05_Similarweb'!N19,0) -> 0.20811869 | D16: Используется как проверка реалистичности.

Sheet 05_Similarweb
A1: Проверочная оценка рынка через Similarweb и цифровые следы конкурентов
A3: Конкурент / сайт | B3: URL | C3: Роль на рынке | D3: Месячные визиты | E3: Доля выбранной географии | F3: Визиты из выбранной географии | G3: Доля релевантных каналов | H3: Коэффициент коммерческого намерения | I3: Релевантный рыночный трафик | J3: Конверсия в заявку | K3: Конверсия заявки в оплату | L3: Средний чек | M3: Заказов в месяц | N3: Выручка в месяц | O3: Выручка в год
A4: Shortcut | B4: https://www.similarweb.com/website/shortcut.ai/ | C4: частичный: AI-агент для Excel | D4: 154111 | E4: 0.2654 | F4: =D4*E4 -> 40901.059 | G4: 0.35 | H4: 0.85 | I4: =F4*G4*H4 -> 12168.065 | J4: 0.04 | K4: 0.05 | L4: 100.575 | M4: =I4*J4*K4 -> 24.33613 | N4: =M4*L4 -> 2447.6063 | O4: =N4*12 -> 29371.276
A5: PerfectXL | B5: https://www.similarweb.com/website/perfectxl.com/ | C5: прямой: аудит таблиц | D5: 35325 | E5: 0.4395 | F5: =D5*E5 -> 15525.337 | G5: 0.8 | H5: 0.85 | I5: =F5*G5*H5 -> 10557.229 | J5: 0.04 | K5: 0.05 | L5: 100.575 | M5: =I5*J5*K5 -> 21.114459 | N5: =M5*L5 -> 2123.5867 | O5: =N5*12 -> 25483.041
A6: Rows | B6: https://www.similarweb.com/website/rows.com/ | C6: заменитель: AI-таблицы | D6: 241737 | E6: 0.1091 | F6: =D6*E6 -> 26373.507 | G6: 0.15 | H6: 0.85 | I6: =F6*G6*H6 -> 3362.6221 | J6: 0.04 | K6: 0.05 | L6: 100.575 | M6: =I6*J6*K6 -> 6.7252442 | N6: =M6*L6 -> 676.39144 | O6: =N6*12 -> 8116.6972
A7: Numerous.ai | B7: https://www.similarweb.com/website/numerous.ai/ | C7: заменитель: AI-помощник в таблицах | D7: 202178 | E7: 0.1622 | F7: =D7*E7 -> 32793.272 | G7: 0.3 | H7: 0.85 | I7: =F7*G7*H7 -> 8362.2843 | J7: 0.04 | K7: 0.05 | L7: 100.575 | M7: =I7*J7*K7 -> 16.724569 | N7: =M7*L7 -> 1682.0735 | O7: =N7*12 -> 20184.882
A8: Operis | B8: https://www.similarweb.com/website/operis.com/ | C8: прямой: аудит финансовых моделей | D8: 14688 | E8: 0.9598 | F8: =D8*E8 -> 14097.542 | G8: 0.5 | H8: 0.8 | I8: =F8*G8*H8 -> 5639.017 | J8: 0.04 | K8: 0.05 | L8: 100.575 | M8: =I8*J8*K8 -> 11.278034 | N8: =M8*L8 -> 1134.2883 | O8: =N8*12 -> 13611.459
A9: Arixcel | B9: https://www.similarweb.com/website/arixcel.com/ | C9: прямой: аудит таблиц | D9: 17824 | E9: 0.5871 | F9: =D9*E9 -> 10464.47 | G9: 0.8 | H9: 0.8 | I9: =F9*G9*H9 -> 6697.2611 | J9: 0.04 | K9: 0.05 | L9: 100.575 | M9: =I9*J9*K9 -> 13.394522 | N9: =M9*L9 -> 1347.1541 | O9: =N9*12 -> 16165.849
A10: Formula Bot | B10: https://www.similarweb.com/website/formulabot.com/ | C10: заменитель: AI-помощник в таблицах | D10: 292214 | E10: 0.0965 | F10: =D10*E10 -> 28198.651 | G10: 0.3 | H10: 0.8 | I10: =F10*G10*H10 -> 6767.6762 | J10: 0.04 | K10: 0.05 | L10: 100.575 | M10: =I10*J10*K10 -> 13.535352 | N10: =M10*L10 -> 1361.3181 | O10: =N10*12 -> 16335.817
A11: Ajelix | B11: https://www.similarweb.com/website/ajelix.com/ | C11: заменитель: AI-помощник в таблицах | D11: 116617 | E11: 0.1823 | F11: =D11*E11 -> 21259.279 | G11: 0.25 | H11: 0.85 | I11: =F11*G11*H11 -> 4517.5968 | J11: 0.04 | K11: 0.05 | L11: 100.575 | M11: =I11*J11*K11 -> 9.0351936 | N11: =M11*L11 -> 908.7146 | O11: =N11*12 -> 10904.575
A12: Datarails | B12: https://www.similarweb.com/website/datarails.com/ | C12: заменитель: FP&A-платформа для Excel | D12: 222359 | E12: 0.7636 | F12: =D12*E12 -> 169793.33 | G12: 0.15 | H12: 0.9 | I12: =F12*G12*H12 -> 22922.1 | J12: 0.04 | K12: 0.05 | L12: 100.575 | M12: =I12*J12*K12 -> 45.8442 | N12: =M12*L12 -> 4610.7804 | O12: =N12*12 -> 55329.365
A13: Julius AI | B13: https://www.similarweb.com/website/julius.ai/ | C13: заменитель: AI-анализ данных | D13: 701540 | E13: 0.082 | F13: =D13*E13 -> 57526.28 | G13: 0.1 | H13: 0.85 | I13: =F13*G13*H13 -> 4889.7338 | J13: 0.04 | K13: 0.05 | L13: 100.575 | M13: =I13*J13*K13 -> 9.7794676 | N13: =M13*L13 -> 983.56995 | O13: =N13*12 -> 11802.839
A14: Spreadsheet Detective | B14: https://www.similarweb.com/website/spreadsheetdetective.com/ | C14: прямой: аудит таблиц | D14: 1935 | E14: 0.8946 | F14: =D14*E14 -> 1731.051 | G14: 0.8 | H14: 0.6 | I14: =F14*G14*H14 -> 830.90448 | J14: 0.04 | K14: 0.05 | L14: 100.575 | M14: =I14*J14*K14 -> 1.661809 | N14: =M14*L14 -> 167.13644 | O14: =N14*12 -> 2005.6372
A15: CIMCON Software | B15: https://www.similarweb.com/website/cimcon.com/ | C15: частичный: риски пользовательских таблиц | D15: 5522 | E15: 0.4752 | F15: =D15*E15 -> 2624.0544 | G15: 0.3 | H15: 0.6 | I15: =F15*G15*H15 -> 472.32979 | J15: 0.04 | K15: 0.05 | L15: 100.575 | M15: =I15*J15*K15 -> 0.94465958 | N15: =M15*L15 -> 95.009138 | O15: =N15*12 -> 1140.1097
A17: Итого / среднее | D17: =SUM(D4:D15) -> 2006050 | F17: =SUM(F4:F15) -> 421287.84 | I17: =SUM(I4:I15) -> 87186.82 | M17: =SUM(M4:M15) -> 174.37364 | N17: =SUM(N4:N15) -> 17537.629 | O17: =SUM(O4:O15) -> 210451.55
A19: Годовая оценка выручки конкурентов по Similarweb | N19: =O17 -> 210451.55

Sheet 06_Дашборд
A1: Итоговая панель оценки объема рынка через потенциальных клиентов
A3: Показатель | B3: Значение | C3: Интерпретация | G3: Объем по сегментам: SAM и SOM
A4: TAM | B4: ='04_Расчет'!C4 -> 5166215900 | C4: Общий потенциальный рынок до сужения | G4: Сегмент | H4: SAM | I4: SOM
A5: SAM | B5: ='04_Расчет'!C7 -> 35003118 | C5: Доступный рынок в зафиксированных границах | G5: ='02_Сегменты'!A4 -> Финансовые аналитики и FP&A | H5: ='02_Сегменты'!M4 -> 6448434.3 | I5: ='02_Сегменты'!O4 -> 9672.6514
A6: SOM | B6: ='04_Расчет'!C8 -> 43798.899 | C6: Реалистично достижимый объем для нового бизнеса | G6: ='02_Сегменты'!A5 -> Бухгалтеры и аудиторы | H6: ='02_Сегменты'!M5 -> 3869157.6 | I6: ='02_Сегменты'!O5 -> 3869.1576
A7: Адресуемые клиенты | B7: ='04_Расчет'!C6 -> 236748 | C7: Клиенты после учета потребности, онлайн-готовности и платежеспособности | G7: ='02_Сегменты'!A6 -> Консультанты по управлению | H7: ='02_Сегменты'!M6 -> 17914327 | I7: ='02_Сегменты'!O6 -> 26871.491
A8: Similarweb-ориентир | B8: ='05_Similarweb'!N19 -> 210451.55 | C8: Оценочная годовая выручка конкурентов по цифровому трафику | G8: ='02_Сегменты'!A7 -> МСП с финансовой функцией | H8: ='02_Сегменты'!M7 -> 6771198.9 | I8: ='02_Сегменты'!O7 -> 3385.5994
A9: Доля SOM в SAM | B9: ='04_Расчет'!C9 -> 0.0012512857 | C9: Проверка амбициозности выхода на рынок | G9: ='02_Сегменты'!A8 -> Резерв | H9: ='02_Сегменты'!M8 -> 0 | I9: ='02_Сегменты'!O8 -> 0
G10: ='02_Сегменты'!A9 -> Резерв | H10: ='02_Сегменты'!M9 -> 0 | I10: ='02_Сегменты'!O9 -> 0
A12: Сценарный диапазон объема рынка
A13: Сценарий | B13: TAM | C13: SAM | D13: SOM | E13: Вывод
A14: Осторожный | B14: ='03_Сценарии'!H4 -> 3306378176 | C14: ='03_Сценарии'!I4 -> 10080898 | D14: ='03_Сценарии'!J4 -> 5040.449 | E14: Минимальный ориентир при слабой конверсии и низкой достижимой доле.
A15: Базовый | B15: ='03_Сценарии'!H5 -> 5166215900 | C15: ='03_Сценарии'!I5 -> 35003118 | D15: ='03_Сценарии'!J5 -> 45504.053 | E15: Основной расчет.
A16: Оптимистичный | B16: ='03_Сценарии'!H6 -> 6.5352631e+09 | C16: ='03_Сценарии'!I6 -> 73325932 | D16: ='03_Сценарии'!J6 -> 219977.8 | E16: Верхняя граница при благоприятных условиях.
A19: Шаблон итогового вывода
A20: По результатам оценки через количество потенциальных клиентов базовый доступный объем рынка составляет ориентировочно [SAM] EUR в год, а реалистично достижимый объем для нового бизнеса составляет [SOM] EUR в год. Оценка является сценарной и требует проверки через фактические данные о клиентах, конкурентах, рекламных каналах, Similarweb, поисковом спросе и платежеспособности целевых сегментов.

Sheet 07_Источники
A1: Журнал источников данных и допущений
A3: Блок расчета | B3: Показатель | C3: Источник | D3: Ссылка / файл | E3: Дата обращения | F3: Статус данных | G3: Надежность | H3: Комментарий
A4: Количество клиентов | B4: Занятые по профессиям и число предприятий | C4: BLS OOH 2025 (США); SBA Advocacy 2025; European Commission SME Report 2025/2026; UK Business Population Estimates 2025 | D4: см. Материалы_собранные/внешние_данные_2026-10-03.md | E4: 46298 | F4: Факт и допущение (масштаб по занятости 0,45 и 1,30) | G4: Средняя | H4: Заполнено при выполнении ЛР2-3; детали в приложении отчета.
A5: Коэффициент потребности | B5: Доля с потребностью проверять сложные таблицы | C5: Допущение Д-10 на основе ПЗ1 (ошибки в 86-94 % таблиц) и ЛР1 | D5: журнал_допущений.md | E5: 46298 | F5: Экспертное допущение | G5: Низкая | H5: Заполнено при выполнении ЛР2-3; детали в приложении отчета.
A6: Цифровая готовность | B6: Доля покупающих сервис онлайн | C6: Допущение Д-10; Similarweb: каналы поиск и прямые заходы | D6: similarweb_снимок_2026-10-03.csv | E6: 46298 | F6: Оценка | G6: Средняя | H6: Заполнено при выполнении ЛР2-3; детали в приложении отчета.
A7: Платежеспособность | B7: Доля клиентов с бюджетом | C7: Цены конкурентов (PerfectXL от 69 EUR, Numerous 10 USD, Copilot 18 USD) и тарифы ПЗ1 | D7: внешние_данные_2026-10-03.md | E7: 46298 | F7: Оценка | G7: Средняя | H7: Заполнено при выполнении ЛР2-3; детали в приложении отчета.
A8: Средний чек | B8: Выручка первого года на платящего | C8: Структура платящих (допущение Д-09) и тарифы 9/19/29 EUR | D8: inputs.py | E8: 46298 | F8: Расчет по допущению | G8: Средняя | H8: Заполнено при выполнении ЛР2-3; детали в приложении отчета.
A9: Similarweb | B9: Трафик конкурентов | C9: Similarweb Pro (пробный доступ), 06-08.2026 | D9: https://www.similarweb.com/website/ | E9: 46298 | F9: Оценка | G9: Средняя | H9: Заполнено при выполнении ЛР2-3; детали в приложении отчета.

Sheet 08_Справочник
A1: Справочные списки для выпадающих полей
A3: Тип клиента | B3: Статус данных | C3: Надежность | D3: Сценарий
A4: B2B | B4: Факт | C4: Высокая | D4: Осторожный
A5: B2C | B5: Оценка | C5: Средняя | D5: Базовый
A6: Платформа | B6: Экспертное допущение | C6: Низкая | D6: Оптимистичный
A7: Смешанный | B7: Нет данных
