Workbook

Sheet 00_Методика
A1: Методика проверки рынка через платежеспособность
A2: Excel-шаблон для оценки, способен ли выявленный интерес аудитории перейти в платежеспособный спрос
A4: Этап | B4: Что выполняется | C4: Какие данные нужны | D4: Результат
A5: 1. Сегментация | B5: Разделить потенциальных клиентов на группы по типу, размеру, потребности и цифровой доступности. | C5: Сегменты клиентов, численность, доля потребности, доля готовности покупать онлайн. | D5: Расчет платежеспособной клиентской базы.
A6: 2. Ценовой коридор | B6: Собрать минимальные, медианные и максимальные цены конкурентов или аналогичных предложений. | C6: Сайты конкурентов, прайс-листы, коммерческие предложения, маркетплейсы услуг. | D6: Диапазон допустимой цены и ориентир среднего чека.
A7: 3. Экономическая оправданность | B7: Проверить, окупается ли покупка для клиента через дополнительную выручку, экономию или снижение потерь. | C7: Выручка клиента, маржинальность, ожидаемый эффект, стоимость услуги. | D7: Показатель окупаемости и экономический аргумент покупки.
A8: 4. Платежеспособность | B8: Сопоставить бюджет клиента с ежемесячной стоимостью предложения. | C8: Доступный бюджет, цена услуги, регулярность оплаты. | D8: Индекс платежеспособности и статус покупки.
A9: 5. Сценарии | B9: Рассчитать осторожный, базовый и оптимистичный варианты рынка. | C9: Коэффициенты потребности, платежеспособности, частоты покупки и среднего чека. | D9: Диапазон платежеспособного объема рынка.
A10: 6. Проверка цифровыми данными | B10: Использовать Similarweb и другие цифровые источники как косвенную проверку активности рынка. | C10: Посещаемость конкурентов, каналы, география, поисковый трафик. | D10: Проверка того, есть ли цифровая активность вокруг сегмента.

Sheet 01_Параметры
A1: Исходные параметры модели
A2: Заполните базовые сведения о бизнес-идее и единых допущениях расчета
A4: Параметр | B4: Значение | C4: Комментарий
A5: Бизнес-идея | B5: TableMind: онлайн-проверка Excel-моделей | C5: Можно заменить на собственную идею
A6: Географические границы | B6: Англоязычные страны и ЕС-27 | C6: Территория первичной проверки рынка
A7: Валюта расчета | B7: EUR | C7: Можно заменить на RUB, USD, EUR
A8: Период расчета | B8: год | C8: Расчет годового платежеспособного объема рынка
A9: Базовая конверсия интереса в покупку | B9: 0.05 | C9: Доля заинтересованных клиентов, переходящих к покупке
A10: Минимальный индекс платежеспособности | B10: 1 | C10: Бюджет / цена услуги; ниже 1 — покупка затруднена
A11: Целевая маржинальность поставщика | B11: 0.8 | C11: Целевая валовая маржа SaaS (допущение Д-11): цена минус вычисления и LLM
A12: Дата заполнения | B12: 46298 | C12: Дата версии расчета

Sheet 02_Сегменты
A1: Расчет рынка через количество платежеспособных клиентов
A2: Заполните клиентские сегменты, коэффициенты потребности и доступности покупки
A4: Сегмент | B4: Всего потенциальных клиентов | C4: Доля с потребностью | D4: Доля готовых покупать онлайн | E4: Доля платежеспособных | F4: Покупок/контрактов в год | G4: Средний чек | H4: Платежеспособные клиенты | I4: Годовое число покупок | J4: Потенциальный объем рынка | K4: Комментарий | L4: Источник
A5: Финансовые аналитики и FP&A | B5: 852968 | C5: 0.3 | D5: 0.6 | E5: 0.35 | F5: 1 | G5: 120 | H5: =IF(A5="","",B5*C5*D5*E5) -> 53736.984 | I5: =IF(A5="","",H5*F5) -> 53736.984 | J5: =IF(A5="","",I5*G5) -> 6448438.1 | K5: Модели строят и проверяют сами; платит чаще работодатель (Pro или Team). | L5: BLS 2025 (США) и масштаб по занятости
A6: Бухгалтеры и аудиторы | B6: 1535380 | C6: 0.2 | D6: 0.6 | E6: 0.3 | F6: 1 | G6: 70 | H6: =IF(A6="","",B6*C6*D6*E6) -> 55273.68 | I6: =IF(A6="","",H6*F6) -> 55273.68 | J6: =IF(A6="","",I6*G6) -> 3869157.6 | K6: В границы входят только работающие со сложными таблицами; часто разовый аудит. | L6: BLS 2025 (США) и масштаб по занятости
A7: Консультанты по управлению | B7: 1184810 | C7: 0.3 | D7: 0.7 | E7: 0.4 | F7: 1 | G7: 180 | H7: =IF(A7="","",B7*C7*D7*E7) -> 99524.04 | I7: =IF(A7="","",H7*F7) -> 99524.04 | J7: =IF(A7="","",I7*G7) -> 17914327 | K7: Проверка чужих моделей клиентов; высокая готовность платить. | L7: BLS 2025 (США) и масштаб по занятости
A8: МСП с финансовой функцией | B8: 522469 | C8: 0.3 | D8: 0.6 | E8: 0.3 | F8: 1 | G8: 240 | H8: =IF(A8="","",B8*C8*D8*E8) -> 28213.326 | I8: =IF(A8="","",H8*F8) -> 28213.326 | J8: =IF(A8="","",I8*G8) -> 6771198.2 | K8: Покупка Team на 2-3 места; основатели и операционные менеджеры. | L8: SBA 2025, UK BPE 2025, ЕК 2025/2026 и допущения
H9: =IF(A9="","",B9*C9*D9*E9) | I9: =IF(A9="","",H9*F9) | J9: =IF(A9="","",I9*G9)
H10: =IF(A10="","",B10*C10*D10*E10) | I10: =IF(A10="","",H10*F10) | J10: =IF(A10="","",I10*G10)
H11: =IF(A11="","",B11*C11*D11*E11) | I11: =IF(A11="","",H11*F11) | J11: =IF(A11="","",I11*G11)
H12: =IF(A12="","",B12*C12*D12*E12) | I12: =IF(A12="","",H12*F12) | J12: =IF(A12="","",I12*G12)
H13: =IF(A13="","",B13*C13*D13*E13) | I13: =IF(A13="","",H13*F13) | J13: =IF(A13="","",I13*G13)
H14: =IF(A14="","",B14*C14*D14*E14) | I14: =IF(A14="","",H14*F14) | J14: =IF(A14="","",I14*G14)
A16: Итого | H16: =SUM(H5:H14) -> 236748.03 | I16: =SUM(I5:I14) -> 236748.03 | J16: =SUM(J5:J14) -> 35003121

Sheet 03_Ценовой_коридор
A1: Ценовой коридор и конкурентная цена
A2: Сравните цены аналогичных предложений и оцените допустимый средний чек
H3: Индекс цены TableMind к медиане
A4: Услуга / продукт | B4: Минимальная цена | C4: Медианная цена | D4: Максимальная цена | E4: Себестоимость | F4: Валовая маржа | G4: Цена в модели | H4: Индекс доступности цены | I4: Комментарий | J4: Источник
A5: Разовая проверка файла (аналог: месяц дешевого AI-помощника) | B5: 7.1 | C5: 8.88 | D5: 19.17 | E5: 1.5 | F5: =IF(A5="","",(G5-E5)/G5) -> 0.83333333 | G5: 9 | H5: =IF(A5="","",G5/C5) -> 1.0135135 | I5: Прямых разовых аналогов с публичной ценой нет; ориентир - Rows Plus 8 USD, Numerous 10 USD, медиана Pro-класса | J5: rows.com/pricing, numerous.ai/pricing
A6: Персональная подписка уровня Pro (в месяц) | B6: 7.1 | C6: 19.17 | D6: 88.76 | E6: 4 | F6: =IF(A6="","",(G6-E6)/G6) -> 0.78947368 | G6: 19 | H6: =IF(A6="","",G6/C6) -> 0.99113198 | I6: Rows Plus 8 USD; Numerous 10 USD; Copilot Business 18-25,2 USD; PerfectXL от 69 EUR; Shortcut Pro 100 USD | J6: страницы цен, 03.10.2026
A7: Командное место Team (в месяц за место) | B7: 7.1 | C7: 22.37 | D7: 88.76 | E7: 4.5 | F7: =IF(A7="","",(G7-E7)/G7) -> 0.84482759 | G7: 29 | H7: =IF(A7="","",G7/C7) -> 1.2963791 | I7: Rows Plus на пользователя 8 USD; Copilot Business 25,2 USD; Shortcut Teams 100 USD за место | J7: страницы цен, 03.10.2026
A8: Специализированный аудит таблиц (класс PerfectXL) | B8: 69 | C8: 69 | D8: 69 | E8: 4 | F8: =IF(A8="","",(G8-E8)/G8) -> 0.78947368 | G8: 19 | H8: =IF(A8="","",G8/C8) -> 0.27536232 | I8: PerfectXL отдельный инструмент от 69 EUR в месяц; Arixcel 2,75 GBP за пользователя в месяц, Operis OAK 311,66 GBP в год (в коридор не включены) | J8: perfectxl.com/pricing
F9: =IF(A9="","",(G9-E9)/G9) | H9: =IF(A9="","",G9/C9)
F10: =IF(A10="","",(G10-E10)/G10) | G10: =IF(A10="","",C10) | H10: =IF(A10="","",G10/C10)
F11: =IF(A11="","",(G11-E11)/G11) | G11: =IF(A11="","",C11) | H11: =IF(A11="","",G11/C11)
F12: =IF(A12="","",(G12-E12)/G12) | G12: =IF(A12="","",C12) | H12: =IF(A12="","",G12/C12)
A14: Среднее / ориентир | B14: =AVERAGE(B5:B12) -> 22.575 | C14: =AVERAGE(C5:C12) -> 29.855 | D14: =AVERAGE(D5:D12) -> 66.4225 | E14: =AVERAGE(E5:E12) -> 3.5 | F14: =AVERAGE(F5:F12) -> 0.81427707 | G14: =AVERAGE(G5:G12) -> 19 | H14: =AVERAGE(H5:H12) -> 0.89409672

Sheet 04_Экономика_покупки
A1: Экономическая оправданность покупки для клиента
A2: Проверяется, возвращает ли клиент вложения в продукт или услугу
B3: Стоимость месячной работы с таблицами, EUR | C3: Доля времени на проверку и поиск ошибок | D3: Доля экономии времени за счет сервиса | E3: Экономия, EUR/мес.
A4: Сегмент | B4: Средняя месячная выручка клиента | C4: Маржинальность клиента | D4: Ожидаемый рост выручки | E4: Дополнительная валовая прибыль/мес. | F4: Цена услуги/мес. | G4: Окупаемость, мес. | H4: ROI за год | I4: Экономический статус | J4: Комментарий | K4: Источник
A5: Финансовые аналитики и FP&A | B5: 3300 | C5: 0.2 | D5: 0.45 | E5: =IF(A5="","",B5*C5*D5) -> 297 | F5: 19 | G5: =IF(A5="","",IF(E5=0,"",F5/E5)) -> 0.063973064 | H5: =IF(A5="","",((E5-F5)*12)/(F5*12)) -> 14.631579 | I5: =IF(A5="","",IF(H5>=0.5,"экономически оправдано",IF(H5>=0,"требует проверки","экономически слабо"))) -> экономически оправдано | J5: Эффект - экономия времени проверки; не учитывает стоимость пропущенной ошибки (она выше) | K5: Опрос / конкуренты
A6: Бухгалтеры и аудиторы | B6: 2000 | C6: 0.2 | D6: 0.45 | E6: =IF(A6="","",B6*C6*D6) -> 180 | F6: 19 | G6: =IF(A6="","",IF(E6=0,"",F6/E6)) -> 0.10555556 | H6: =IF(A6="","",((E6-F6)*12)/(F6*12)) -> 8.4736842 | I6: =IF(A6="","",IF(H6>=0.5,"экономически оправдано",IF(H6>=0,"требует проверки","экономически слабо"))) -> экономически оправдано | J6: Эффект - экономия времени проверки; не учитывает стоимость пропущенной ошибки (она выше) | K6: Сайты / Similarweb
A7: Консультанты по управлению | B7: 4250 | C7: 0.2 | D7: 0.45 | E7: =IF(A7="","",B7*C7*D7) -> 382.5 | F7: 19 | G7: =IF(A7="","",IF(E7=0,"",F7/E7)) -> 0.049673203 | H7: =IF(A7="","",((E7-F7)*12)/(F7*12)) -> 19.131579 | I7: =IF(A7="","",IF(H7>=0.5,"экономически оправдано",IF(H7>=0,"требует проверки","экономически слабо"))) -> экономически оправдано | J7: Эффект - экономия времени проверки; не учитывает стоимость пропущенной ошибки (она выше) | K7: Опрос / каталоги
A8: МСП с финансовой функцией | B8: 1800 | C8: 0.2 | D8: 0.45 | E8: =IF(A8="","",B8*C8*D8) -> 162 | F8: 58 | G8: =IF(A8="","",IF(E8=0,"",F8/E8)) -> 0.35802469 | H8: =IF(A8="","",((E8-F8)*12)/(F8*12)) -> 1.7931034 | I8: =IF(A8="","",IF(H8>=0.5,"экономически оправдано",IF(H8>=0,"требует проверки","экономически слабо"))) -> экономически оправдано | J8: Эффект - экономия времени проверки; не учитывает стоимость пропущенной ошибки (она выше) | K8: Платформы
E9: =IF(A9="","",B9*C9*D9) | G9: =IF(A9="","",IF(E9=0,"",F9/E9)) | H9: =IF(A9="","",((E9-F9)*12)/(F9*12)) | I9: =IF(A9="","",IF(H9>=0.5,"экономически оправдано",IF(H9>=0,"требует проверки","экономически слабо"))) | K9: Сайты конкурентов
E10: =IF(A10="","",B10*C10*D10) | G10: =IF(A10="","",IF(E10=0,"",F10/E10)) | H10: =IF(A10="","",((E10-F10)*12)/(F10*12)) | I10: =IF(A10="","",IF(H10>=0.5,"экономически оправдано",IF(H10>=0,"требует проверки","экономически слабо")))
E11: =IF(A11="","",B11*C11*D11) | G11: =IF(A11="","",IF(E11=0,"",F11/E11)) | H11: =IF(A11="","",((E11-F11)*12)/(F11*12)) | I11: =IF(A11="","",IF(H11>=0.5,"экономически оправдано",IF(H11>=0,"требует проверки","экономически слабо")))
E12: =IF(A12="","",B12*C12*D12) | G12: =IF(A12="","",IF(E12=0,"",F12/E12)) | H12: =IF(A12="","",((E12-F12)*12)/(F12*12)) | I12: =IF(A12="","",IF(H12>=0.5,"экономически оправдано",IF(H12>=0,"требует проверки","экономически слабо")))
A14: Среднее / сводный показатель | B14: =AVERAGE(B5:B12) -> 2837.5 | C14: =AVERAGE(C5:C12) -> 0.2 | D14: =AVERAGE(D5:D12) -> 0.45 | E14: =AVERAGE(E5:E12) -> 255.375 | F14: =AVERAGE(F5:F12) -> 28.75 | G14: =AVERAGE(G5:G12) -> 0.14430663 | H14: =AVERAGE(H5:H12) -> 11.007486

Sheet 05_Платежеспособность
A1: Проверка платежеспособности клиентских сегментов
A2: Индекс платежеспособности = доступный месячный бюджет клиента / месячная цена предложения
A4: Сегмент | B4: Средний доступный бюджет/мес. | C4: Цена предложения/мес. | D4: Индекс платежеспособности | E4: Статус | F4: Доля клиентов с бюджетом | G4: Платежеспособные клиенты | H4: Годовой чек | I4: Платежеспособный объем | J4: Комментарий
A5: Финансовые аналитики и FP&A | B5: 45 | C5: 19 | D5: =IF(A5="","",B5/C5) -> 2.3684211 | E5: =IF(A5="","",IF(D5>=1.5,"высокая",IF(D5>=1,"достаточная",IF(D5>=0.7,"пограничная","низкая")))) -> высокая | F5: 0.35 | G5: =IF(A5="","",'02_Сегменты'!B5*F5) -> 298538.8 | H5: 120 | I5: =IF(A5="","",G5*H5) -> 35824656 | J5: Платит работодатель; индекс бюджета к Pro.
A6: Бухгалтеры и аудиторы | B6: 25 | C6: 19 | D6: =IF(A6="","",B6/C6) -> 1.3157895 | E6: =IF(A6="","",IF(D6>=1.5,"высокая",IF(D6>=1,"достаточная",IF(D6>=0.7,"пограничная","низкая")))) -> достаточная | F6: 0.3 | G6: =IF(A6="","",'02_Сегменты'!B6*F6) -> 460614 | H6: 70 | I6: =IF(A6="","",G6*H6) -> 32242980 | J6: Часто собственный бюджет или бюджет фирмы; разовый аудит дешевле.
A7: Консультанты по управлению | B7: 80 | C7: 19 | D7: =IF(A7="","",B7/C7) -> 4.2105263 | E7: =IF(A7="","",IF(D7>=1.5,"высокая",IF(D7>=1,"достаточная",IF(D7>=0.7,"пограничная","низкая")))) -> высокая | F7: 0.4 | G7: =IF(A7="","",'02_Сегменты'!B7*F7) -> 473924 | H7: 180 | I7: =IF(A7="","",G7*H7) -> 85306320 | J7: Стоимость включается в проект клиента.
A8: МСП с финансовой функцией | B8: 90 | C8: 58 | D8: =IF(A8="","",B8/C8) -> 1.5517241 | E8: =IF(A8="","",IF(D8>=1.5,"высокая",IF(D8>=1,"достаточная",IF(D8>=0.7,"пограничная","низкая")))) -> высокая | F8: 0.3 | G8: =IF(A8="","",'02_Сегменты'!B8*F8) -> 156740.7 | H8: 240 | I8: =IF(A8="","",G8*H8) -> 37617768 | J8: Team на 2 места по 29 EUR.
D9: =IF(A9="","",B9/C9) | E9: =IF(A9="","",IF(D9>=1.5,"высокая",IF(D9>=1,"достаточная",IF(D9>=0.7,"пограничная","низкая")))) | G9: =IF(A9="","",'02_Сегменты'!B9*F9) | I9: =IF(A9="","",G9*H9)
D10: =IF(A10="","",B10/C10) | E10: =IF(A10="","",IF(D10>=1.5,"высокая",IF(D10>=1,"достаточная",IF(D10>=0.7,"пограничная","низкая")))) | G10: =IF(A10="","",'02_Сегменты'!B10*F10) | I10: =IF(A10="","",G10*H10)
D11: =IF(A11="","",B11/C11) | E11: =IF(A11="","",IF(D11>=1.5,"высокая",IF(D11>=1,"достаточная",IF(D11>=0.7,"пограничная","низкая")))) | G11: =IF(A11="","",'02_Сегменты'!B11*F11) | I11: =IF(A11="","",G11*H11)
D12: =IF(A12="","",B12/C12) | E12: =IF(A12="","",IF(D12>=1.5,"высокая",IF(D12>=1,"достаточная",IF(D12>=0.7,"пограничная","низкая")))) | G12: =IF(A12="","",'02_Сегменты'!B12*F12) | I12: =IF(A12="","",G12*H12)
A14: Итого / среднее | B14: =AVERAGE(B5:B12) -> 60 | C14: =AVERAGE(C5:C12) -> 28.75 | D14: =AVERAGE(D5:D12) -> 2.3616152 | F14: =AVERAGE(F5:F12) -> 0.3375 | G14: =SUM(G5:G12) -> 1389817.5 | H14: =AVERAGE(H5:H12) -> 152.5 | I14: =SUM(I5:I12) -> 190991724

Sheet 06_Сценарии
A1: Сценарная проверка платежеспособного объема рынка
A2: Сценарии позволяют не завышать вывод и показывать диапазон оценки
A4: Параметр | B4: Осторожный | C4: Базовый | D4: Оптимистичный | E4: Комментарий
A5: Коэффициент потребности | B5: 0.75 | C5: 1 | D5: 1.2 | E5: Корректировка доли клиентов с потребностью
A6: Коэффициент платежеспособности | B6: 0.75 | C6: 1 | D6: 1.2 | E6: Корректировка доли платежеспособных клиентов
A7: Коэффициент частоты покупки | B7: 0.8 | C7: 1 | D7: 1.1 | E7: Корректировка числа покупок/контрактов
A8: Коэффициент среднего чека | B8: 0.8 | C8: 1 | D8: 1.15 | E8: Корректировка цены
A9: Достижимая доля нового бизнеса | B9: 0.0005 | C9: 0.0013 | D9: 0.003 | E9: Реалистичная доля рынка для нового игрока
A12: Сегмент | B12: Базовый объем | C12: Осторожный рынок | D12: Базовый рынок | E12: Оптимистичный рынок | F12: Осторожная достижимая выручка | G12: Базовая достижимая выручка | H12: Оптимистичная достижимая выручка
A13: =IF('02_Сегменты'!A5="","",'02_Сегменты'!A5) -> Финансовые аналитики и FP&A | B13: =IF(A13="","",'02_Сегменты'!J5) -> 6448438.1 | C13: =IF(A13="","",B13*$B$5*$B$6*$B$7*$B$8) -> 2321437.7 | D13: =IF(A13="","",B13*$C$5*$C$6*$C$7*$C$8) -> 6448438.1 | E13: =IF(A13="","",B13*$D$5*$D$6*$D$7*$D$8) -> 11746475 | F13: =IF(A13="","",C13*$B$9) -> 1160.7189 | G13: =IF(A13="","",D13*$C$9) -> 8382.9695 | H13: =IF(A13="","",E13*$D$9) -> 35239.424
A14: =IF('02_Сегменты'!A6="","",'02_Сегменты'!A6) -> Бухгалтеры и аудиторы | B14: =IF(A14="","",'02_Сегменты'!J6) -> 3869157.6 | C14: =IF(A14="","",B14*$B$5*$B$6*$B$7*$B$8) -> 1392896.7 | D14: =IF(A14="","",B14*$C$5*$C$6*$C$7*$C$8) -> 3869157.6 | E14: =IF(A14="","",B14*$D$5*$D$6*$D$7*$D$8) -> 7048057.5 | F14: =IF(A14="","",C14*$B$9) -> 696.44837 | G14: =IF(A14="","",D14*$C$9) -> 5029.9049 | H14: =IF(A14="","",E14*$D$9) -> 21144.172
A15: =IF('02_Сегменты'!A7="","",'02_Сегменты'!A7) -> Консультанты по управлению | B15: =IF(A15="","",'02_Сегменты'!J7) -> 17914327 | C15: =IF(A15="","",B15*$B$5*$B$6*$B$7*$B$8) -> 6449157.8 | D15: =IF(A15="","",B15*$C$5*$C$6*$C$7*$C$8) -> 17914327 | E15: =IF(A15="","",B15*$D$5*$D$6*$D$7*$D$8) -> 32632738 | F15: =IF(A15="","",C15*$B$9) -> 3224.5789 | G15: =IF(A15="","",D15*$C$9) -> 23288.625 | H15: =IF(A15="","",E15*$D$9) -> 97898.215
A16: =IF('02_Сегменты'!A8="","",'02_Сегменты'!A8) -> МСП с финансовой функцией | B16: =IF(A16="","",'02_Сегменты'!J8) -> 6771198.2 | C16: =IF(A16="","",B16*$B$5*$B$6*$B$7*$B$8) -> 2437631.4 | D16: =IF(A16="","",B16*$C$5*$C$6*$C$7*$C$8) -> 6771198.2 | E16: =IF(A16="","",B16*$D$5*$D$6*$D$7*$D$8) -> 12334415 | F16: =IF(A16="","",C16*$B$9) -> 1218.8157 | G16: =IF(A16="","",D16*$C$9) -> 8802.5577 | H16: =IF(A16="","",E16*$D$9) -> 37003.244
A17: =IF('02_Сегменты'!A9="","",'02_Сегменты'!A9) | B17: =IF(A17="","",'02_Сегменты'!J9) | C17: =IF(A17="","",B17*$B$5*$B$6*$B$7*$B$8) | D17: =IF(A17="","",B17*$C$5*$C$6*$C$7*$C$8) | E17: =IF(A17="","",B17*$D$5*$D$6*$D$7*$D$8) | F17: =IF(A17="","",C17*$B$9) | G17: =IF(A17="","",D17*$C$9) | H17: =IF(A17="","",E17*$D$9)
A18: =IF('02_Сегменты'!A10="","",'02_Сегменты'!A10) | B18: =IF(A18="","",'02_Сегменты'!J10) | C18: =IF(A18="","",B18*$B$5*$B$6*$B$7*$B$8) | D18: =IF(A18="","",B18*$C$5*$C$6*$C$7*$C$8) | E18: =IF(A18="","",B18*$D$5*$D$6*$D$7*$D$8) | F18: =IF(A18="","",C18*$B$9) | G18: =IF(A18="","",D18*$C$9) | H18: =IF(A18="","",E18*$D$9)
A19: =IF('02_Сегменты'!A11="","",'02_Сегменты'!A11) | B19: =IF(A19="","",'02_Сегменты'!J11) | C19: =IF(A19="","",B19*$B$5*$B$6*$B$7*$B$8) | D19: =IF(A19="","",B19*$C$5*$C$6*$C$7*$C$8) | E19: =IF(A19="","",B19*$D$5*$D$6*$D$7*$D$8) | F19: =IF(A19="","",C19*$B$9) | G19: =IF(A19="","",D19*$C$9) | H19: =IF(A19="","",E19*$D$9)
A20: =IF('02_Сегменты'!A12="","",'02_Сегменты'!A12) | B20: =IF(A20="","",'02_Сегменты'!J12) | C20: =IF(A20="","",B20*$B$5*$B$6*$B$7*$B$8) | D20: =IF(A20="","",B20*$C$5*$C$6*$C$7*$C$8) | E20: =IF(A20="","",B20*$D$5*$D$6*$D$7*$D$8) | F20: =IF(A20="","",C20*$B$9) | G20: =IF(A20="","",D20*$C$9) | H20: =IF(A20="","",E20*$D$9)
A22: Итого | B22: =SUM(B13:B20) -> 35003121 | C22: =SUM(C13:C20) -> 12601124 | D22: =SUM(D13:D20) -> 35003121 | E22: =SUM(E13:E20) -> 63761685 | F22: =SUM(F13:F20) -> 6300.5618 | G22: =SUM(G13:G20) -> 45504.057 | H22: =SUM(H13:H20) -> 191285.06

Sheet 07_Similarweb
A1: Проверка цифровой активности через Similarweb
A2: Используется как косвенная проверка рынка: трафик конкурентов, география, каналы и поисковые запросы
A4: Сайт / конкурент | B4: Месячные посещения | C4: Эффективная доля (география x релевантность x качество) | D4: Релевантный трафик | E4: Доля поискового трафика | F4: Доля прямого трафика | G4: Доля соцсетей | H4: Конверсия визит - платящий | I4: Оценка новых платящих/мес. | J4: Выручка первого года на платящего, EUR | K4: Оценка выручки/мес. (первый год), EUR | L4: Источник / дата
A5: shortcut.ai | B5: 154111 | C5: 0.079 | D5: =IF(A5="","",B5*C5) -> 12174.769 | E5: 0.3174 | F5: 0.5558 | G5: 0.0345 | H5: 0.002 | I5: =IF(A5="","",D5*H5) -> 24.349538 | J5: 100.58 | K5: =IF(A5="","",I5*J5) -> 2449.0765 | L5: Similarweb Pro, 03.10.2026; C = география x релевантность x качество; H = визит - платящий
A6: perfectxl.com | B6: 35325 | C6: 0.2989 | D6: =IF(A6="","",B6*C6) -> 10558.642 | E6: 0.3255 | F6: 0.4043 | G6: 0.0622 | H6: 0.002 | I6: =IF(A6="","",D6*H6) -> 21.117285 | J6: 100.58 | K6: =IF(A6="","",I6*J6) -> 2123.9765 | L6: Similarweb Pro, 03.10.2026; C = география x релевантность x качество; H = визит - платящий
A7: rows.com | B7: 241737 | C7: 0.0139 | D7: =IF(A7="","",B7*C7) -> 3360.1443 | E7: 0.5314 | F7: 0.3416 | G7: 0.0342 | H7: 0.002 | I7: =IF(A7="","",D7*H7) -> 6.7202886 | J7: 100.58 | K7: =IF(A7="","",I7*J7) -> 675.92663 | L7: Similarweb Pro, 03.10.2026; C = география x релевантность x качество; H = визит - платящий
A8: numerous.ai | B8: 202178 | C8: 0.0414 | D8: =IF(A8="","",B8*C8) -> 8370.1692 | E8: 0.5638 | F8: 0.255 | G8: 0.0166 | H8: 0.002 | I8: =IF(A8="","",D8*H8) -> 16.740338 | J8: 100.58 | K8: =IF(A8="","",I8*J8) -> 1683.7432 | L8: Similarweb Pro, 03.10.2026; C = география x релевантность x качество; H = визит - платящий
A9: operis.com | B9: 14688 | C9: 0.3839 | D9: =IF(A9="","",B9*C9) -> 5638.7232 | E9: 0.2938 | F9: 0.2676 | G9: 0.1092 | H9: 0.002 | I9: =IF(A9="","",D9*H9) -> 11.277446 | J9: 100.58 | K9: =IF(A9="","",I9*J9) -> 1134.2856 | L9: Similarweb Pro, 03.10.2026; C = география x релевантность x качество; H = визит - платящий
A10: arixcel.com | B10: 17824 | C10: 0.3757 | D10: =IF(A10="","",B10*C10) -> 6696.4768 | E10: 0.3295 | F10: 0.3864 | G10: 0.0602 | H10: 0.002 | I10: =IF(A10="","",D10*H10) -> 13.392954 | J10: 100.58 | K10: =IF(A10="","",I10*J10) -> 1347.0633 | L10: Similarweb Pro, 03.10.2026; C = география x релевантность x качество; H = визит - платящий
A11: formulabot.com | B11: 292214 | C11: 0.0232 | D11: =IF(A11="","",B11*C11) -> 6779.3648 | E11: 0.577 | F11: 0.2826 | G11: 0.0246 | H11: 0.002 | I11: =IF(A11="","",D11*H11) -> 13.55873 | J11: 100.58 | K11: =IF(A11="","",I11*J11) -> 1363.737 | L11: Similarweb Pro, 03.10.2026; C = география x релевантность x качество; H = визит - платящий
A12: ajelix.com | B12: 116617 | C12: 0.0387 | D12: =IF(A12="","",B12*C12) -> 4513.0779 | E12: 0.5641 | F12: 0.2635 | G12: 0.0174 | H12: 0.002 | I12: =IF(A12="","",D12*H12) -> 9.0261558 | J12: 100.58 | K12: =IF(A12="","",I12*J12) -> 907.85075 | L12: Similarweb Pro, 03.10.2026; C = география x релевантность x качество; H = визит - платящий
A13: datarails.com | B13: 222359 | C13: 0.1031 | D13: =IF(A13="","",B13*C13) -> 22925.213 | E13: 0.121 | F13: 0.592 | G13: 0.0514 | H13: 0.002 | I13: =IF(A13="","",D13*H13) -> 45.850426 | J13: 100.58 | K13: =IF(A13="","",I13*J13) -> 4611.6358 | L13: Similarweb Pro, 03.10.2026; C = география x релевантность x качество; H = визит - платящий
A14: julius.ai | B14: 701540 | C14: 0.007 | D14: =IF(A14="","",B14*C14) -> 4910.78 | E14: 0.4094 | F14: 0.3559 | G14: 0.0201 | H14: 0.002 | I14: =IF(A14="","",D14*H14) -> 9.82156 | J14: 100.58 | K14: =IF(A14="","",I14*J14) -> 987.8525 | L14: Similarweb Pro, 03.10.2026; C = география x релевантность x качество; H = визит - платящий
A15: spreadsheetdetective.com | B15: 1935 | C15: 0.4294 | D15: =IF(A15="","",B15*C15) -> 830.889 | E15: 0.3084 | F15: 0.3897 | G15: 0.0637 | H15: 0.002 | I15: =IF(A15="","",D15*H15) -> 1.661778 | J15: 100.58 | K15: =IF(A15="","",I15*J15) -> 167.14163 | L15: Similarweb Pro, 03.10.2026; C = география x релевантность x качество; H = визит - платящий
A16: cimcon.com | B16: 5522 | C16: 0.0855 | D16: =IF(A16="","",B16*C16) -> 472.131 | E16: 0.3402 | F16: 0.3852 | G16: 0.0614 | H16: 0.002 | I16: =IF(A16="","",D16*H16) -> 0.944262 | J16: 100.58 | K16: =IF(A16="","",I16*J16) -> 94.973872 | L16: Similarweb Pro, 03.10.2026; C = география x релевантность x качество; H = визит - платящий
A18: Итого / среднее | B18: =SUM(B5:B16) -> 2006050 | C18: =AVERAGE(C5:C16) -> 0.15664167 | D18: =SUM(D5:D16) -> 87230.381 | E18: =AVERAGE(E5:E16) -> 0.390125 | F18: =AVERAGE(F5:F16) -> 0.3733 | G18: =AVERAGE(G5:G16) -> 0.046291667 | H18: =AVERAGE(H5:H16) -> 0.002 | I18: =SUM(I5:I16) -> 174.46076 | J18: =AVERAGE(J5:J16) -> 100.58 | K18: =SUM(K5:K16) -> 17547.263

Sheet 08_Итоговая_панель
A1: Итоговая панель проверки платежеспособности
A2: Ключевые показатели, сценарии и вывод для принятия решения
A4: Показатель | B4: Значение | C4: Интерпретация | E4: Сценарий | F4: Рынок | G4: Достижимая выручка | H4: Комментарий
A5: Потенциальный объем по сегментам | B5: ='02_Сегменты'!J16 -> 35003121 | C5: Сумма по всем сегментам с учетом потребности, цифровой доступности и платежеспособности | E5: Осторожный | F5: ='06_Сценарии'!C22 -> 12601124 | G5: ='06_Сценарии'!F22 -> 6300.5618 | H5: Нижняя граница
A6: Платежеспособные клиенты | B6: ='02_Сегменты'!H16 -> 236748.03 | C6: Расчетная база клиентов, способных купить предложение | E6: Базовый | F6: ='06_Сценарии'!D22 -> 35003121 | G6: ='06_Сценарии'!G22 -> 45504.057 | H6: Плановый ориентир
A7: Средний индекс платежеспособности | B7: ='05_Платежеспособность'!D14 -> 2.3616152 | C7: Бюджет клиента / цена предложения | E7: Оптимистичный | F7: ='06_Сценарии'!E22 -> 63761685 | G7: ='06_Сценарии'!H22 -> 191285.06 | H7: Верхняя граница
A8: Средний ROI клиента за год | B8: ='04_Экономика_покупки'!H14 -> 11.007486 | C8: Экономическая оправданность покупки с позиции клиента
A9: Осторожная достижимая выручка | B9: ='06_Сценарии'!F22 -> 6300.5618 | C9: Реалистичный нижний сценарий для нового игрока
A10: Базовая достижимая выручка | B10: ='06_Сценарии'!G22 -> 45504.057 | C10: Основной сценарий для планирования
A11: Оптимистичная достижимая выручка | B11: ='06_Сценарии'!H22 -> 191285.06 | C11: Верхний сценарий при высокой реализации
A12: Оценка выручки конкурентов по Similarweb/мес. | B12: ='07_Similarweb'!K18 -> 17547.263 | C12: Косвенный ориентир цифровой активности рынка
A15: Автоматизированный предварительный вывод
A16: =IF(B7>=1,"Платежеспособность сегментов в среднем достаточная: бюджет клиентов сопоставим с ценой предложения. Рекомендуется переходить к проверке конкурентов, каналов продаж и пилотному запуску.","Платежеспособность сегментов требует дополнительной проверки: цена предложения выше доступного бюджета. Нужно уточнить сегменты, снизить стоимость входного продукта или изменить состав предложения.") -> Платежеспособность сегментов в среднем достаточная: бюджет клиентов сопоставим с ценой предложения. Рекомендуется переходить к проверке конкурентов, каналов продаж и пилотному запуску.

Sheet 09_Источники
A1: Журнал источников данных и допущений
A2: Заполняется для воспроизводимости расчета и проверки ограничений
A4: Источник | B4: Какие данные брать | C4: Как использовать | D4: Ссылка / путь | E4: Дата обращения | F4: Ограничение
A5: BLS, SBA, ЕК, UK BPE (вместо Белстата) | B5: Количество компаний, отрасли, доходы, социально-экономические показатели | C5: Оценка потенциальной клиентской базы и платежеспособности | D5: bls.gov/ooh; advocacy.sba.gov; single-market-economy.ec.europa.eu; gov.uk | E5: 46298 | F5: Официальные данные могут быть укрупненными
A6: Similarweb | B6: Посещаемость конкурентов, каналы, география, поисковый трафик | C6: Проверка цифровой активности и конкурентной среды | D6: https://www.similarweb.com/website/ | E6: 46298 | F6: Оценочные данные, точность ниже для малых сайтов
A7: Google Trends | B7: Динамика относительного интереса | C7: Проверка устойчивости интереса к теме | D7: https://trends.google.com/ | E7: 46298 | F7: Индекс 0–100 не равен абсолютному спросу
A8: Яндекс Вордстат и Google Trends (ЛР1) | B8: Частотность запросов, регионы, динамика | C8: Проверка поискового спроса и коммерческих формулировок | D8: ЛР1, Материалы_собранные | E8: 46298 | F8: Отражает аудиторию Яндекса
A9: Сайты конкурентов | B9: Цены, пакеты услуг, позиционирование, офферы | C9: Определение ценового коридора и коммерческих условий | E9: 46298 | F9: Неполная видимость фактических продаж
A10: Расчет ценовой чувствительности по профилям клиентов | B10: Бюджет, готовность платить, барьеры покупки | C10: Проверка платежеспособности и экономической оправданности | E10: 46298 | F10: Расчет по параметрам сегментов (допущение Д-30), приложение Г отчета
