Workbook

Sheet Панель
A1: Панель оценки тренда, сезонности и циклов спроса
A2: Производится анализ интереса аудитории на основе выгрузок из Google Trends и Яндекс Вордстат.
A3: Блок | B3: Показатель | C3: Значение | D3: Использование
A4: Данные | B4: Количество месяцев | C4: =Оценка_тренда!B3 -> 60 | D4: проверка достаточности ряда
A5: Тренд | B5: Классификация тренда | C5: =Оценка_тренда!B9 -> растущий тренд | D5: основа вывода о росте или снижении интереса
A6: Тренд | B6: Изменение последних 12 мес. к первым 12 мес. | C6: =Оценка_тренда!B7 -> 0.68549771 | D6: оценка силы изменения
A7: Сезонность | B7: Сила сезонности | C7: =Сезонность!B19 -> выраженная сезонность | D7: нужна для планирования месяцев продвижения
A8: Сезонность | B8: Месяц максимума | C8: =Сезонность!B20 -> декабрь | D8: период вероятного повышения интереса
A9: Сезонность | B9: Месяц минимума | C9: =Сезонность!B21 -> июль | D9: период вероятного снижения интереса
A10: Циклы | B10: Текущая фаза | C10: =Деловые_циклы!B6 -> норма | D10: оценка текущего состояния спроса относительно нормы
A11: Циклы | B11: Текущий коэффициент | C11: =Деловые_циклы!B5 -> 1.0051613 | D11: значение выше 1 означает спрос выше трендово-сезонного уровня
A14: Вывод
A15: =Оценка_тренда!B10&" Для ряда характерна "&Сезонность!B19&", максимум интереса приходится на "&Сезонность!B20&", минимум на "&Сезонность!B21&". Текущая фаза спроса - "&Деловые_циклы!B6&"." -> Интерес аудитории растет; бизнес-идея может быть дополнительно проверена на платежеспособный спрос. Для ряда характерна выраженная сезонность, максимум интереса приходится на декабрь, минимум на июль. Текущая фаза спроса - норма.

Sheet Ввод_данных
A1: Ввод данных из Google Trends и Яндекс Вордстат
A2: Google Trends вводится как индекс 0-100. Яндекс Вордстат вводится как абсолютное число запросов по выбранному семантическому кластеру.
A3: Период | B3: Кластер запросов | C3: Google Trends, 0-100 | D3: Яндекс Вордстат, запросов | E3: Регион / рынок | F3: Комментарий
A4: 44470 | B4: проверка и аудит таблиц Excel | C4: 3.8 | D4: 1683 | E4: Google Trends - весь мир, Вордстат - Россия | F4: Google Trends минимум ряда; Вордстат в нижней четверти значений ряда; начало ряда
A5: 44501 | B5: проверка и аудит таблиц Excel | C5: 4.12 | D5: 2298 | E5: Google Trends - весь мир, Вордстат - Россия | F5: Google Trends в нижней четверти значений ряда; Вордстат выше медианы ряда, рост к предыдущему месяцу на 37 %
A6: 44531 | B6: проверка и аудит таблиц Excel | C6: 4.88 | D6: 2523 | E6: Google Trends - весь мир, Вордстат - Россия | F6: Google Trends в нижней четверти значений ряда; Вордстат в верхней четверти значений ряда
A7: 44562 | B7: проверка и аудит таблиц Excel | C7: 6.2 | D7: 1793 | E7: Google Trends - весь мир, Вордстат - Россия | F7: Google Trends в нижней четверти значений ряда; Вордстат в нижней четверти значений ряда, снижение к предыдущему месяцу на 29 %
A8: 44593 | B8: проверка и аудит таблиц Excel | C8: 7.88 | D8: 1909 | E8: Google Trends - весь мир, Вордстат - Россия | F8: Google Trends выше медианы ряда; Вордстат ниже медианы ряда
A9: 44621 | B9: проверка и аудит таблиц Excel | C9: 8.88 | D9: 2207 | E9: Google Trends - весь мир, Вордстат - Россия | F9: Google Trends выше медианы ряда; Вордстат выше медианы ряда
A10: 44652 | B10: проверка и аудит таблиц Excel | C10: 6.38 | D10: 2055 | E10: Google Trends - весь мир, Вордстат - Россия | F10: Google Trends ниже медианы ряда, снижение к предыдущему месяцу на 28 %; Вордстат ниже медианы ряда
A11: 44682 | B11: проверка и аудит таблиц Excel | C11: 5.8 | D11: 1948 | E11: Google Trends - весь мир, Вордстат - Россия | F11: Google Trends в нижней четверти значений ряда; Вордстат ниже медианы ряда
A12: 44713 | B12: проверка и аудит таблиц Excel | C12: 5.12 | D12: 1806 | E12: Google Trends - весь мир, Вордстат - Россия | F12: Google Trends в нижней четверти значений ряда; Вордстат в нижней четверти значений ряда
A13: 44743 | B13: проверка и аудит таблиц Excel | C13: 6.2 | D13: 1175 | E13: Google Trends - весь мир, Вордстат - Россия | F13: Google Trends в нижней четверти значений ряда; Вордстат в нижней четверти значений ряда, снижение к предыдущему месяцу на 35 %
A14: 44774 | B14: проверка и аудит таблиц Excel | C14: 6.88 | D14: 1313 | E14: Google Trends - весь мир, Вордстат - Россия | F14: Google Trends ниже медианы ряда; Вордстат в нижней четверти значений ряда
A15: 44805 | B15: проверка и аудит таблиц Excel | C15: 8.5 | D15: 1627 | E15: Google Trends - весь мир, Вордстат - Россия | F15: Google Trends выше медианы ряда; Вордстат в нижней четверти значений ряда
... A63: 46266 | B63: проверка и аудит таблиц Excel | C63: 50.5 | D63: 1419 | E63: Google Trends - весь мир, Вордстат - Россия | F63: Google Trends в верхней четверти значений ряда; Вордстат в нижней четверти значений ряда, рост к предыдущему месяцу на 51 %; конец ряда, выгрузка от 02.10.2026

Sheet Расчет
A1: Расчет тренда, сезонности и циклических отклонений
A2: Расчет построен по мультипликативной логике. Наблюдаемый интерес = тренд × сезонность × циклическое отклонение × случайные колебания. Для практической оценки используются скользящее среднее, сезонные индексы и коэффициент отклонения от трендово-сезонного уровня.
A3: Период | B3: Месяц № | C3: Месяц | D3: Google Trends | E3: Вордстат | F3: Вордстат норм. 0-100 | G3: Сводный индекс | H3: Скользящее среднее 12 мес. (тренд) | I3: Y/T | J3: Сезонно очищенный индекс | K3: Циклический коэффициент | L3: Фаза цикла | M3: Комментарий | N3: Порядковый №
A4: =IF(Ввод_данных!A4="","",Ввод_данных!A4) -> 44470 | B4: =IF(A4="","",MONTH(A4)) -> 10 | C4: =IF(A4="","",CHOOSE(MONTH(A4),"январь","февраль","март","апрель","май","июнь","июль","август","сентябрь","октябрь","ноябрь","декабрь")) -> октябрь | D4: =IF(Ввод_данных!C4="","",Ввод_данных!C4) -> 3.8 | E4: =IF(Ввод_данных!D4="","",Ввод_данных!D4) -> 1683 | F4: =IF(E4="","",IF(MAX($E$4:$E$63)=0,"",E4/MAX($E$4:$E$63)*100)) -> 46.85412 | G4: =IF(COUNT(D4,F4)=0,"",IF(COUNT(D4,F4)=2,D4*Настройки!$B$3+F4*Настройки!$B$4,IF(D4<>"",D4,F4))) -> 25.32706 | H4: =IF(OR(G4="",COUNT($G$4:G4)<12),"","") | I4: =IF(OR(G4="",H4="",H4=0),"",G4/H4) | J4: =IF(OR(G4="",IFERROR(VLOOKUP(B4,Сезонность!$A$3:$D$14,4,FALSE),0)=0),"",G4/IFERROR(VLOOKUP(B4,Сезонность!$A$3:$D$14,4,FALSE),1)) -> 23.502101 | K4: =IF(OR(G4="",H4="",H4=0,IFERROR(VLOOKUP(B4,Сезонность!$A$3:$D$14,4,FALSE),0)=0),"",G4/(H4*IFERROR(VLOOKUP(B4,Сезонность!$A$3:$D$14,4,FALSE),1))) | L4: =IF(K4="","",IF(K4<Настройки!$B$10,"ниже тренда",IF(K4>Настройки!$B$11,"выше тренда","норма"))) | M4: =IF(G4="","","окно скользящего среднего 12 мес. еще не накоплено, фаза цикла не определяется") -> окно скользящего среднего 12 мес. еще не накоплено, фаза цикла не определяется | N4: =IF(G4="","",COUNT($G$4:G4)) -> 1
A5: =IF(Ввод_данных!A5="","",Ввод_данных!A5) -> 44501 | B5: =IF(A5="","",MONTH(A5)) -> 11 | C5: =IF(A5="","",CHOOSE(MONTH(A5),"январь","февраль","март","апрель","май","июнь","июль","август","сентябрь","октябрь","ноябрь","декабрь")) -> ноябрь | D5: =IF(Ввод_данных!C5="","",Ввод_данных!C5) -> 4.12 | E5: =IF(Ввод_данных!D5="","",Ввод_данных!D5) -> 2298 | F5: =IF(E5="","",IF(MAX($E$4:$E$63)=0,"",E5/MAX($E$4:$E$63)*100)) -> 63.975501 | G5: =IF(COUNT(D5,F5)=0,"",IF(COUNT(D5,F5)=2,D5*Настройки!$B$3+F5*Настройки!$B$4,IF(D5<>"",D5,F5))) -> 34.047751 | H5: =IF(OR(G5="",COUNT($G$4:G5)<12),"","") | I5: =IF(OR(G5="",H5="",H5=0),"",G5/H5) | J5: =IF(OR(G5="",IFERROR(VLOOKUP(B5,Сезонность!$A$3:$D$14,4,FALSE),0)=0),"",G5/IFERROR(VLOOKUP(B5,Сезонность!$A$3:$D$14,4,FALSE),1)) -> 29.215974 | K5: =IF(OR(G5="",H5="",H5=0,IFERROR(VLOOKUP(B5,Сезонность!$A$3:$D$14,4,FALSE),0)=0),"",G5/(H5*IFERROR(VLOOKUP(B5,Сезонность!$A$3:$D$14,4,FALSE),1))) | L5: =IF(K5="","",IF(K5<Настройки!$B$10,"ниже тренда",IF(K5>Настройки!$B$11,"выше тренда","норма"))) | M5: =IF(G5="","","окно скользящего среднего 12 мес. еще не накоплено, фаза цикла не определяется") -> окно скользящего среднего 12 мес. еще не накоплено, фаза цикла не определяется | N5: =IF(G5="","",COUNT($G$4:G5)) -> 2
A6: =IF(Ввод_данных!A6="","",Ввод_данных!A6) -> 44531 | B6: =IF(A6="","",MONTH(A6)) -> 12 | C6: =IF(A6="","",CHOOSE(MONTH(A6),"январь","февраль","март","апрель","май","июнь","июль","август","сентябрь","октябрь","ноябрь","декабрь")) -> декабрь | D6: =IF(Ввод_данных!C6="","",Ввод_данных!C6) -> 4.88 | E6: =IF(Ввод_данных!D6="","",Ввод_данных!D6) -> 2523 | F6: =IF(E6="","",IF(MAX($E$4:$E$63)=0,"",E6/MAX($E$4:$E$63)*100)) -> 70.239421 | G6: =IF(COUNT(D6,F6)=0,"",IF(COUNT(D6,F6)=2,D6*Настройки!$B$3+F6*Настройки!$B$4,IF(D6<>"",D6,F6))) -> 37.55971 | H6: =IF(OR(G6="",COUNT($G$4:G6)<12),"","") | I6: =IF(OR(G6="",H6="",H6=0),"",G6/H6) | J6: =IF(OR(G6="",IFERROR(VLOOKUP(B6,Сезонность!$A$3:$D$14,4,FALSE),0)=0),"",G6/IFERROR(VLOOKUP(B6,Сезонность!$A$3:$D$14,4,FALSE),1)) -> 29.589617 | K6: =IF(OR(G6="",H6="",H6=0,IFERROR(VLOOKUP(B6,Сезонность!$A$3:$D$14,4,FALSE),0)=0),"",G6/(H6*IFERROR(VLOOKUP(B6,Сезонность!$A$3:$D$14,4,FALSE),1))) | L6: =IF(K6="","",IF(K6<Настройки!$B$10,"ниже тренда",IF(K6>Настройки!$B$11,"выше тренда","норма"))) | M6: =IF(G6="","","окно скользящего среднего 12 мес. еще не накоплено, фаза цикла не определяется") -> окно скользящего среднего 12 мес. еще не накоплено, фаза цикла не определяется | N6: =IF(G6="","",COUNT($G$4:G6)) -> 3
A7: =IF(Ввод_данных!A7="","",Ввод_данных!A7) -> 44562 | B7: =IF(A7="","",MONTH(A7)) -> 1 | C7: =IF(A7="","",CHOOSE(MONTH(A7),"январь","февраль","март","апрель","май","июнь","июль","август","сентябрь","октябрь","ноябрь","декабрь")) -> январь | D7: =IF(Ввод_данных!C7="","",Ввод_данных!C7) -> 6.2 | E7: =IF(Ввод_данных!D7="","",Ввод_данных!D7) -> 1793 | F7: =IF(E7="","",IF(MAX($E$4:$E$63)=0,"",E7/MAX($E$4:$E$63)*100)) -> 49.916481 | G7: =IF(COUNT(D7,F7)=0,"",IF(COUNT(D7,F7)=2,D7*Настройки!$B$3+F7*Настройки!$B$4,IF(D7<>"",D7,F7))) -> 28.058241 | H7: =IF(OR(G7="",COUNT($G$4:G7)<12),"","") | I7: =IF(OR(G7="",H7="",H7=0),"",G7/H7) | J7: =IF(OR(G7="",IFERROR(VLOOKUP(B7,Сезонность!$A$3:$D$14,4,FALSE),0)=0),"",G7/IFERROR(VLOOKUP(B7,Сезонность!$A$3:$D$14,4,FALSE),1)) -> 30.945721 | K7: =IF(OR(G7="",H7="",H7=0,IFERROR(VLOOKUP(B7,Сезонность!$A$3:$D$14,4,FALSE),0)=0),"",G7/(H7*IFERROR(VLOOKUP(B7,Сезонность!$A$3:$D$14,4,FALSE),1))) | L7: =IF(K7="","",IF(K7<Настройки!$B$10,"ниже тренда",IF(K7>Настройки!$B$11,"выше тренда","норма"))) | M7: =IF(G7="","","окно скользящего среднего 12 мес. еще не накоплено, фаза цикла не определяется") -> окно скользящего среднего 12 мес. еще не накоплено, фаза цикла не определяется | N7: =IF(G7="","",COUNT($G$4:G7)) -> 4
A8: =IF(Ввод_данных!A8="","",Ввод_данных!A8) -> 44593 | B8: =IF(A8="","",MONTH(A8)) -> 2 | C8: =IF(A8="","",CHOOSE(MONTH(A8),"январь","февраль","март","апрель","май","июнь","июль","август","сентябрь","октябрь","ноябрь","декабрь")) -> февраль | D8: =IF(Ввод_данных!C8="","",Ввод_данных!C8) -> 7.88 | E8: =IF(Ввод_данных!D8="","",Ввод_данных!D8) -> 1909 | F8: =IF(E8="","",IF(MAX($E$4:$E$63)=0,"",E8/MAX($E$4:$E$63)*100)) -> 53.14588 | G8: =IF(COUNT(D8,F8)=0,"",IF(COUNT(D8,F8)=2,D8*Настройки!$B$3+F8*Настройки!$B$4,IF(D8<>"",D8,F8))) -> 30.51294 | H8: =IF(OR(G8="",COUNT($G$4:G8)<12),"","") | I8: =IF(OR(G8="",H8="",H8=0),"",G8/H8) | J8: =IF(OR(G8="",IFERROR(VLOOKUP(B8,Сезонность!$A$3:$D$14,4,FALSE),0)=0),"",G8/IFERROR(VLOOKUP(B8,Сезонность!$A$3:$D$14,4,FALSE),1)) -> 33.450127 | K8: =IF(OR(G8="",H8="",H8=0,IFERROR(VLOOKUP(B8,Сезонность!$A$3:$D$14,4,FALSE),0)=0),"",G8/(H8*IFERROR(VLOOKUP(B8,Сезонность!$A$3:$D$14,4,FALSE),1))) | L8: =IF(K8="","",IF(K8<Настройки!$B$10,"ниже тренда",IF(K8>Настройки!$B$11,"выше тренда","норма"))) | M8: =IF(G8="","","окно скользящего среднего 12 мес. еще не накоплено, фаза цикла не определяется") -> окно скользящего среднего 12 мес. еще не накоплено, фаза цикла не определяется | N8: =IF(G8="","",COUNT($G$4:G8)) -> 5
A9: =IF(Ввод_данных!A9="","",Ввод_данных!A9) -> 44621 | B9: =IF(A9="","",MONTH(A9)) -> 3 | C9: =IF(A9="","",CHOOSE(MONTH(A9),"январь","февраль","март","апрель","май","июнь","июль","август","сентябрь","октябрь","ноябрь","декабрь")) -> март | D9: =IF(Ввод_данных!C9="","",Ввод_данных!C9) -> 8.88 | E9: =IF(Ввод_данных!D9="","",Ввод_данных!D9) -> 2207 | F9: =IF(E9="","",IF(MAX($E$4:$E$63)=0,"",E9/MAX($E$4:$E$63)*100)) -> 61.442094 | G9: =IF(COUNT(D9,F9)=0,"",IF(COUNT(D9,F9)=2,D9*Настройки!$B$3+F9*Настройки!$B$4,IF(D9<>"",D9,F9))) -> 35.161047 | H9: =IF(OR(G9="",COUNT($G$4:G9)<12),"","") | I9: =IF(OR(G9="",H9="",H9=0),"",G9/H9) | J9: =IF(OR(G9="",IFERROR(VLOOKUP(B9,Сезонность!$A$3:$D$14,4,FALSE),0)=0),"",G9/IFERROR(VLOOKUP(B9,Сезонность!$A$3:$D$14,4,FALSE),1)) -> 34.024576 | K9: =IF(OR(G9="",H9="",H9=0,IFERROR(VLOOKUP(B9,Сезонность!$A$3:$D$14,4,FALSE),0)=0),"",G9/(H9*IFERROR(VLOOKUP(B9,Сезонность!$A$3:$D$14,4,FALSE),1))) | L9: =IF(K9="","",IF(K9<Настройки!$B$10,"ниже тренда",IF(K9>Настройки!$B$11,"выше тренда","норма"))) | M9: =IF(G9="","","окно скользящего среднего 12 мес. еще не накоплено, фаза цикла не определяется") -> окно скользящего среднего 12 мес. еще не накоплено, фаза цикла не определяется | N9: =IF(G9="","",COUNT($G$4:G9)) -> 6
A10: =IF(Ввод_данных!A10="","",Ввод_данных!A10) -> 44652 | B10: =IF(A10="","",MONTH(A10)) -> 4 | C10: =IF(A10="","",CHOOSE(MONTH(A10),"январь","февраль","март","апрель","май","июнь","июль","август","сентябрь","октябрь","ноябрь","декабрь")) -> апрель | D10: =IF(Ввод_данных!C10="","",Ввод_данных!C10) -> 6.38 | E10: =IF(Ввод_данных!D10="","",Ввод_данных!D10) -> 2055 | F10: =IF(E10="","",IF(MAX($E$4:$E$63)=0,"",E10/MAX($E$4:$E$63)*100)) -> 57.210468 | G10: =IF(COUNT(D10,F10)=0,"",IF(COUNT(D10,F10)=2,D10*Настройки!$B$3+F10*Настройки!$B$4,IF(D10<>"",D10,F10))) -> 31.795234 | H10: =IF(OR(G10="",COUNT($G$4:G10)<12),"","") | I10: =IF(OR(G10="",H10="",H10=0),"",G10/H10) | J10: =IF(OR(G10="",IFERROR(VLOOKUP(B10,Сезонность!$A$3:$D$14,4,FALSE),0)=0),"",G10/IFERROR(VLOOKUP(B10,Сезонность!$A$3:$D$14,4,FALSE),1)) -> 28.27602 | K10: =IF(OR(G10="",H10="",H10=0,IFERROR(VLOOKUP(B10,Сезонность!$A$3:$D$14,4,FALSE),0)=0),"",G10/(H10*IFERROR(VLOOKUP(B10,Сезонность!$A$3:$D$14,4,FALSE),1))) | L10: =IF(K10="","",IF(K10<Настройки!$B$10,"ниже тренда",IF(K10>Настройки!$B$11,"выше тренда","норма"))) | M10: =IF(G10="","","окно скользящего среднего 12 мес. еще не накоплено, фаза цикла не определяется") -> окно скользящего среднего 12 мес. еще не накоплено, фаза цикла не определяется | N10: =IF(G10="","",COUNT($G$4:G10)) -> 7
A11: =IF(Ввод_данных!A11="","",Ввод_данных!A11) -> 44682 | B11: =IF(A11="","",MONTH(A11)) -> 5 | C11: =IF(A11="","",CHOOSE(MONTH(A11),"январь","февраль","март","апрель","май","июнь","июль","август","сентябрь","октябрь","ноябрь","декабрь")) -> май | D11: =IF(Ввод_данных!C11="","",Ввод_данных!C11) -> 5.8 | E11: =IF(Ввод_данных!D11="","",Ввод_данных!D11) -> 1948 | F11: =IF(E11="","",IF(MAX($E$4:$E$63)=0,"",E11/MAX($E$4:$E$63)*100)) -> 54.231626 | G11: =IF(COUNT(D11,F11)=0,"",IF(COUNT(D11,F11)=2,D11*Настройки!$B$3+F11*Настройки!$B$4,IF(D11<>"",D11,F11))) -> 30.015813 | H11: =IF(OR(G11="",COUNT($G$4:G11)<12),"","") | I11: =IF(OR(G11="",H11="",H11=0),"",G11/H11) | J11: =IF(OR(G11="",IFERROR(VLOOKUP(B11,Сезонность!$A$3:$D$14,4,FALSE),0)=0),"",G11/IFERROR(VLOOKUP(B11,Сезонность!$A$3:$D$14,4,FALSE),1)) -> 27.194683 | K11: =IF(OR(G11="",H11="",H11=0,IFERROR(VLOOKUP(B11,Сезонность!$A$3:$D$14,4,FALSE),0)=0),"",G11/(H11*IFERROR(VLOOKUP(B11,Сезонность!$A$3:$D$14,4,FALSE),1))) | L11: =IF(K11="","",IF(K11<Настройки!$B$10,"ниже тренда",IF(K11>Настройки!$B$11,"выше тренда","норма"))) | M11: =IF(G11="","","окно скользящего среднего 12 мес. еще не накоплено, фаза цикла не определяется") -> окно скользящего среднего 12 мес. еще не накоплено, фаза цикла не определяется | N11: =IF(G11="","",COUNT($G$4:G11)) -> 8
A12: =IF(Ввод_данных!A12="","",Ввод_данных!A12) -> 44713 | B12: =IF(A12="","",MONTH(A12)) -> 6 | C12: =IF(A12="","",CHOOSE(MONTH(A12),"январь","февраль","март","апрель","май","июнь","июль","август","сентябрь","октябрь","ноябрь","декабрь")) -> июнь | D12: =IF(Ввод_данных!C12="","",Ввод_данных!C12) -> 5.12 | E12: =IF(Ввод_данных!D12="","",Ввод_данных!D12) -> 1806 | F12: =IF(E12="","",IF(MAX($E$4:$E$63)=0,"",E12/MAX($E$4:$E$63)*100)) -> 50.278396 | G12: =IF(COUNT(D12,F12)=0,"",IF(COUNT(D12,F12)=2,D12*Настройки!$B$3+F12*Настройки!$B$4,IF(D12<>"",D12,F12))) -> 27.699198 | H12: =IF(OR(G12="",COUNT($G$4:G12)<12),"","") | I12: =IF(OR(G12="",H12="",H12=0),"",G12/H12) | J12: =IF(OR(G12="",IFERROR(VLOOKUP(B12,Сезонность!$A$3:$D$14,4,FALSE),0)=0),"",G12/IFERROR(VLOOKUP(B12,Сезонность!$A$3:$D$14,4,FALSE),1)) -> 26.314795 | K12: =IF(OR(G12="",H12="",H12=0,IFERROR(VLOOKUP(B12,Сезонность!$A$3:$D$14,4,FALSE),0)=0),"",G12/(H12*IFERROR(VLOOKUP(B12,Сезонность!$A$3:$D$14,4,FALSE),1))) | L12: =IF(K12="","",IF(K12<Настройки!$B$10,"ниже тренда",IF(K12>Настройки!$B$11,"выше тренда","норма"))) | M12: =IF(G12="","","окно скользящего среднего 12 мес. еще не накоплено, фаза цикла не определяется") -> окно скользящего среднего 12 мес. еще не накоплено, фаза цикла не определяется | N12: =IF(G12="","",COUNT($G$4:G12)) -> 9
A13: =IF(Ввод_данных!A13="","",Ввод_данных!A13) -> 44743 | B13: =IF(A13="","",MONTH(A13)) -> 7 | C13: =IF(A13="","",CHOOSE(MONTH(A13),"январь","февраль","март","апрель","май","июнь","июль","август","сентябрь","октябрь","ноябрь","декабрь")) -> июль | D13: =IF(Ввод_данных!C13="","",Ввод_данных!C13) -> 6.2 | E13: =IF(Ввод_данных!D13="","",Ввод_данных!D13) -> 1175 | F13: =IF(E13="","",IF(MAX($E$4:$E$63)=0,"",E13/MAX($E$4:$E$63)*100)) -> 32.711581 | G13: =IF(COUNT(D13,F13)=0,"",IF(COUNT(D13,F13)=2,D13*Настройки!$B$3+F13*Настройки!$B$4,IF(D13<>"",D13,F13))) -> 19.455791 | H13: =IF(OR(G13="",COUNT($G$4:G13)<12),"","") | I13: =IF(OR(G13="",H13="",H13=0),"",G13/H13) | J13: =IF(OR(G13="",IFERROR(VLOOKUP(B13,Сезонность!$A$3:$D$14,4,FALSE),0)=0),"",G13/IFERROR(VLOOKUP(B13,Сезонность!$A$3:$D$14,4,FALSE),1)) -> 27.199009 | K13: =IF(OR(G13="",H13="",H13=0,IFERROR(VLOOKUP(B13,Сезонность!$A$3:$D$14,4,FALSE),0)=0),"",G13/(H13*IFERROR(VLOOKUP(B13,Сезонность!$A$3:$D$14,4,FALSE),1))) | L13: =IF(K13="","",IF(K13<Настройки!$B$10,"ниже тренда",IF(K13>Настройки!$B$11,"выше тренда","норма"))) | M13: =IF(G13="","","окно скользящего среднего 12 мес. еще не накоплено, фаза цикла не определяется") -> окно скользящего среднего 12 мес. еще не накоплено, фаза цикла не определяется | N13: =IF(G13="","",COUNT($G$4:G13)) -> 10
A14: =IF(Ввод_данных!A14="","",Ввод_данных!A14) -> 44774 | B14: =IF(A14="","",MONTH(A14)) -> 8 | C14: =IF(A14="","",CHOOSE(MONTH(A14),"январь","февраль","март","апрель","май","июнь","июль","август","сентябрь","октябрь","ноябрь","декабрь")) -> август | D14: =IF(Ввод_данных!C14="","",Ввод_данных!C14) -> 6.88 | E14: =IF(Ввод_данных!D14="","",Ввод_данных!D14) -> 1313 | F14: =IF(E14="","",IF(MAX($E$4:$E$63)=0,"",E14/MAX($E$4:$E$63)*100)) -> 36.553452 | G14: =IF(COUNT(D14,F14)=0,"",IF(COUNT(D14,F14)=2,D14*Настройки!$B$3+F14*Настройки!$B$4,IF(D14<>"",D14,F14))) -> 21.716726 | H14: =IF(OR(G14="",COUNT($G$4:G14)<12),"","") | I14: =IF(OR(G14="",H14="",H14=0),"",G14/H14) | J14: =IF(OR(G14="",IFERROR(VLOOKUP(B14,Сезонность!$A$3:$D$14,4,FALSE),0)=0),"",G14/IFERROR(VLOOKUP(B14,Сезонность!$A$3:$D$14,4,FALSE),1)) -> 29.999309 | K14: =IF(OR(G14="",H14="",H14=0,IFERROR(VLOOKUP(B14,Сезонность!$A$3:$D$14,4,FALSE),0)=0),"",G14/(H14*IFERROR(VLOOKUP(B14,Сезонность!$A$3:$D$14,4,FALSE),1))) | L14: =IF(K14="","",IF(K14<Настройки!$B$10,"ниже тренда",IF(K14>Настройки!$B$11,"выше тренда","норма"))) | M14: =IF(G14="","","окно скользящего среднего 12 мес. еще не накоплено, фаза цикла не определяется") -> окно скользящего среднего 12 мес. еще не накоплено, фаза цикла не определяется | N14: =IF(G14="","",COUNT($G$4:G14)) -> 11
A15: =IF(Ввод_данных!A15="","",Ввод_данных!A15) -> 44805 | B15: =IF(A15="","",MONTH(A15)) -> 9 | C15: =IF(A15="","",CHOOSE(MONTH(A15),"январь","февраль","март","апрель","май","июнь","июль","август","сентябрь","октябрь","ноябрь","декабрь")) -> сентябрь | D15: =IF(Ввод_данных!C15="","",Ввод_данных!C15) -> 8.5 | E15: =IF(Ввод_данных!D15="","",Ввод_данных!D15) -> 1627 | F15: =IF(E15="","",IF(MAX($E$4:$E$63)=0,"",E15/MAX($E$4:$E$63)*100)) -> 45.2951 | G15: =IF(COUNT(D15,F15)=0,"",IF(COUNT(D15,F15)=2,D15*Настройки!$B$3+F15*Настройки!$B$4,IF(D15<>"",D15,F15))) -> 26.89755 | H15: =IF(OR(G15="",COUNT($G$4:G15)<12),"",AVERAGE(G4:G15)) -> 29.020588 | I15: =IF(OR(G15="",H15="",H15=0),"",G15/H15) -> 0.92684372 | J15: =IF(OR(G15="",IFERROR(VLOOKUP(B15,Сезонность!$A$3:$D$14,4,FALSE),0)=0),"",G15/IFERROR(VLOOKUP(B15,Сезонность!$A$3:$D$14,4,FALSE),1)) -> 29.386567 | K15: =IF(OR(G15="",H15="",H15=0,IFERROR(VLOOKUP(B15,Сезонность!$A$3:$D$14,4,FALSE),0)=0),"",G15/(H15*IFERROR(VLOOKUP(B15,Сезонность!$A$3:$D$14,4,FALSE),1))) -> 1.012611 | L15: =IF(K15="","",IF(K15<Настройки!$B$10,"ниже тренда",IF(K15>Настройки!$B$11,"выше тренда","норма"))) -> норма | M15: =IF(L15="","",IF(L15="ниже тренда","возможное ослабление интереса",IF(L15="выше тренда","возможная фаза повышенного интереса","без выраженного отклонения"))) -> без выраженного отклонения | N15: =IF(G15="","",COUNT($G$4:G15)) -> 12
A16: =IF(Ввод_данных!A16="","",Ввод_данных!A16) -> 44835 | B16: =IF(A16="","",MONTH(A16)) -> 10 | C16: =IF(A16="","",CHOOSE(MONTH(A16),"январь","февраль","март","апрель","май","июнь","июль","август","сентябрь","октябрь","ноябрь","декабрь")) -> октябрь | D16: =IF(Ввод_данных!C16="","",Ввод_данных!C16) -> 6.9 | E16: =IF(Ввод_данных!D16="","",Ввод_данных!D16) -> 1868 | F16: =IF(E16="","",IF(MAX($E$4:$E$63)=0,"",E16/MAX($E$4:$E$63)*100)) -> 52.004454 | G16: =IF(COUNT(D16,F16)=0,"",IF(COUNT(D16,F16)=2,D16*Настройки!$B$3+F16*Настройки!$B$4,IF(D16<>"",D16,F16))) -> 29.452227 | H16: =IF(OR(G16="",COUNT($G$4:G16)<12),"",AVERAGE(G5:G16)) -> 29.364352 | I16: =IF(OR(G16="",H16="",H16=0),"",G16/H16) -> 1.0029926 | J16: =IF(OR(G16="",IFERROR(VLOOKUP(B16,Сезонность!$A$3:$D$14,4,FALSE),0)=0),"",G16/IFERROR(VLOOKUP(B16,Сезонность!$A$3:$D$14,4,FALSE),1)) -> 27.330026 | K16: =IF(OR(G16="",H16="",H16=0,IFERROR(VLOOKUP(B16,Сезонность!$A$3:$D$14,4,FALSE),0)=0),"",G16/(H16*IFERROR(VLOOKUP(B16,Сезонность!$A$3:$D$14,4,FALSE),1))) -> 0.93072123 | L16: =IF(K16="","",IF(K16<Настройки!$B$10,"ниже тренда",IF(K16>Настройки!$B$11,"выше тренда","норма"))) -> норма | M16: =IF(L16="","",IF(L16="ниже тренда","возможное ослабление интереса",IF(L16="выше тренда","возможная фаза повышенного интереса","без выраженного отклонения"))) -> без выраженного отклонения | N16: =IF(G16="","",COUNT($G$4:G16)) -> 13
A17: =IF(Ввод_данных!A17="","",Ввод_данных!A17) -> 44866 | B17: =IF(A17="","",MONTH(A17)) -> 11 | C17: =IF(A17="","",CHOOSE(MONTH(A17),"январь","февраль","март","апрель","май","июнь","июль","август","сентябрь","октябрь","ноябрь","декабрь")) -> ноябрь | D17: =IF(Ввод_данных!C17="","",Ввод_данных!C17) -> 5.88 | E17: =IF(Ввод_данных!D17="","",Ввод_данных!D17) -> 2316 | F17: =IF(E17="","",IF(MAX($E$4:$E$63)=0,"",E17/MAX($E$4:$E$63)*100)) -> 64.476615 | G17: =IF(COUNT(D17,F17)=0,"",IF(COUNT(D17,F17)=2,D17*Настройки!$B$3+F17*Настройки!$B$4,IF(D17<>"",D17,F17))) -> 35.178307 | H17: =IF(OR(G17="",COUNT($G$4:G17)<12),"",AVERAGE(G6:G17)) -> 29.458565 | I17: =IF(OR(G17="",H17="",H17=0),"",G17/H17) -> 1.1941623 | J17: =IF(OR(G17="",IFERROR(VLOOKUP(B17,Сезонность!$A$3:$D$14,4,FALSE),0)=0),"",G17/IFERROR(VLOOKUP(B17,Сезонность!$A$3:$D$14,4,FALSE),1)) -> 30.186091 | K17: =IF(OR(G17="",H17="",H17=0,IFERROR(VLOOKUP(B17,Сезонность!$A$3:$D$14,4,FALSE),0)=0),"",G17/(H17*IFERROR(VLOOKUP(B17,Сезонность!$A$3:$D$14,4,FALSE),1))) -> 1.0246966 | L17: =IF(K17="","",IF(K17<Настройки!$B$10,"ниже тренда",IF(K17>Настройки!$B$11,"выше тренда","норма"))) -> норма | M17: =IF(L17="","",IF(L17="ниже тренда","возможное ослабление интереса",IF(L17="выше тренда","возможная фаза повышенного интереса","без выраженного отклонения"))) -> без выраженного отклонения | N17: =IF(G17="","",COUNT($G$4:G17)) -> 14
A18: =IF(Ввод_данных!A18="","",Ввод_данных!A18) -> 44896 | B18: =IF(A18="","",MONTH(A18)) -> 12 | C18: =IF(A18="","",CHOOSE(MONTH(A18),"январь","февраль","март","апрель","май","июнь","июль","август","сентябрь","октябрь","ноябрь","декабрь")) -> декабрь | D18: =IF(Ввод_данных!C18="","",Ввод_данных!C18) -> 6.38 | E18: =IF(Ввод_данных!D18="","",Ввод_данных!D18) -> 2704 | F18: =IF(E18="","",IF(MAX($E$4:$E$63)=0,"",E18/MAX($E$4:$E$63)*100)) -> 75.278396 | G18: =IF(COUNT(D18,F18)=0,"",IF(COUNT(D18,F18)=2,D18*Настройки!$B$3+F18*Настройки!$B$4,IF(D18<>"",D18,F18))) -> 40.829198 | H18: =IF(OR(G18="",COUNT($G$4:G18)<12),"",AVERAGE(G7:G18)) -> 29.731023 | I18: =IF(OR(G18="",H18="",H18=0),"",G18/H18) -> 1.373286 | J18: =IF(OR(G18="",IFERROR(VLOOKUP(B18,Сезонность!$A$3:$D$14,4,FALSE),0)=0),"",G18/IFERROR(VLOOKUP(B18,Сезонность!$A$3:$D$14,4,FALSE),1)) -> 32.165327 | K18: =IF(OR(G18="",H18="",H18=0,IFERROR(VLOOKUP(B18,Сезонность!$A$3:$D$14,4,FALSE),0)=0),"",G18/(H18*IFERROR(VLOOKUP(B18,Сезонность!$A$3:$D$14,4,FALSE),1))) -> 1.0818776 | L18: =IF(K18="","",IF(K18<Настройки!$B$10,"ниже тренда",IF(K18>Настройки!$B$11,"выше тренда","норма"))) -> норма | M18: =IF(L18="","",IF(L18="ниже тренда","возможное ослабление интереса",IF(L18="выше тренда","возможная фаза повышенного интереса","без выраженного отклонения"))) -> без выраженного отклонения | N18: =IF(G18="","",COUNT($G$4:G18)) -> 15
A19: =IF(Ввод_данных!A19="","",Ввод_данных!A19) -> 44927 | B19: =IF(A19="","",MONTH(A19)) -> 1 | C19: =IF(A19="","",CHOOSE(MONTH(A19),"январь","февраль","март","апрель","май","июнь","июль","август","сентябрь","октябрь","ноябрь","декабрь")) -> январь | D19: =IF(Ввод_данных!C19="","",Ввод_данных!C19) -> 7.5 | E19: =IF(Ввод_данных!D19="","",Ввод_данных!D19) -> 1979 | F19: =IF(E19="","",IF(MAX($E$4:$E$63)=0,"",E19/MAX($E$4:$E$63)*100)) -> 55.094655 | G19: =IF(COUNT(D19,F19)=0,"",IF(COUNT(D19,F19)=2,D19*Настройки!$B$3+F19*Настройки!$B$4,IF(D19<>"",D19,F19))) -> 31.297327 | H19: =IF(OR(G19="",COUNT($G$4:G19)<12),"",AVERAGE(G8:G19)) -> 30.000947 | I19: =IF(OR(G19="",H19="",H19=0),"",G19/H19) -> 1.0432113 | J19: =IF(OR(G19="",IFERROR(VLOOKUP(B19,Сезонность!$A$3:$D$14,4,FALSE),0)=0),"",G19/IFERROR(VLOOKUP(B19,Сезонность!$A$3:$D$14,4,FALSE),1)) -> 34.518144 | K19: =IF(OR(G19="",H19="",H19=0,IFERROR(VLOOKUP(B19,Сезонность!$A$3:$D$14,4,FALSE),0)=0),"",G19/(H19*IFERROR(VLOOKUP(B19,Сезонность!$A$3:$D$14,4,FALSE),1))) -> 1.1505685 | L19: =IF(K19="","",IF(K19<Настройки!$B$10,"ниже тренда",IF(K19>Настройки!$B$11,"выше тренда","норма"))) -> выше тренда | M19: =IF(L19="","",IF(L19="ниже тренда","возможное ослабление интереса",IF(L19="выше тренда","возможная фаза повышенного интереса","без выраженного отклонения"))) -> возможная фаза повышенного интереса | N19: =IF(G19="","",COUNT($G$4:G19)) -> 16
A20: =IF(Ввод_данных!A20="","",Ввод_данных!A20) -> 44958 | B20: =IF(A20="","",MONTH(A20)) -> 2 | C20: =IF(A20="","",CHOOSE(MONTH(A20),"январь","февраль","март","апрель","май","июнь","июль","август","сентябрь","октябрь","ноябрь","декабрь")) -> февраль | D20: =IF(Ввод_данных!C20="","",Ввод_данных!C20) -> 5.12 | E20: =IF(Ввод_данных!D20="","",Ввод_данных!D20) -> 1815 | F20: =IF(E20="","",IF(MAX($E$4:$E$63)=0,"",E20/MAX($E$4:$E$63)*100)) -> 50.528953 | G20: =IF(COUNT(D20,F20)=0,"",IF(COUNT(D20,F20)=2,D20*Настройки!$B$3+F20*Настройки!$B$4,IF(D20<>"",D20,F20))) -> 27.824477 | H20: =IF(OR(G20="",COUNT($G$4:G20)<12),"",AVERAGE(G9:G20)) -> 29.776908 | I20: =IF(OR(G20="",H20="",H20=0),"",G20/H20) -> 0.93443136 | J20: =IF(OR(G20="",IFERROR(VLOOKUP(B20,Сезонность!$A$3:$D$14,4,FALSE),0)=0),"",G20/IFERROR(VLOOKUP(B20,Сезонность!$A$3:$D$14,4,FALSE),1)) -> 30.502871 | K20: =IF(OR(G20="",H20="",H20=0,IFERROR(VLOOKUP(B20,Сезонность!$A$3:$D$14,4,FALSE),0)=0),"",G20/(H20*IFERROR(VLOOKUP(B20,Сезонность!$A$3:$D$14,4,FALSE),1))) -> 1.0243801 | L20: =IF(K20="","",IF(K20<Настройки!$B$10,"ниже тренда",IF(K20>Настройки!$B$11,"выше тренда","норма"))) -> норма | M20: =IF(L20="","",IF(L20="ниже тренда","возможное ослабление интереса",IF(L20="выше тренда","возможная фаза повышенного интереса","без выраженного отклонения"))) -> без выраженного отклонения | N20: =IF(G20="","",COUNT($G$4:G20)) -> 17
A21: =IF(Ввод_данных!A21="","",Ввод_данных!A21) -> 44986 | B21: =IF(A21="","",MONTH(A21)) -> 3 | C21: =IF(A21="","",CHOOSE(MONTH(A21),"январь","февраль","март","апрель","май","июнь","июль","август","сентябрь","октябрь","ноябрь","декабрь")) -> март | D21: =IF(Ввод_данных!C21="","",Ввод_данных!C21) -> 6.75 | E21: =IF(Ввод_данных!D21="","",Ввод_данных!D21) -> 2218 | F21: =IF(E21="","",IF(MAX($E$4:$E$63)=0,"",E21/MAX($E$4:$E$63)*100)) -> 61.74833 | G21: =IF(COUNT(D21,F21)=0,"",IF(COUNT(D21,F21)=2,D21*Настройки!$B$3+F21*Настройки!$B$4,IF(D21<>"",D21,F21))) -> 34.249165 | H21: =IF(OR(G21="",COUNT($G$4:G21)<12),"",AVERAGE(G10:G21)) -> 29.700918 | I21: =IF(OR(G21="",H21="",H21=0),"",G21/H21) -> 1.1531349 | J21: =IF(OR(G21="",IFERROR(VLOOKUP(B21,Сезонность!$A$3:$D$14,4,FALSE),0)=0),"",G21/IFERROR(VLOOKUP(B21,Сезонность!$A$3:$D$14,4,FALSE),1)) -> 33.142168 | K21: =IF(OR(G21="",H21="",H21=0,IFERROR(VLOOKUP(B21,Сезонность!$A$3:$D$14,4,FALSE),0)=0),"",G21/(H21*IFERROR(VLOOKUP(B21,Сезонность!$A$3:$D$14,4,FALSE),1))) -> 1.1158634 | L21: =IF(K21="","",IF(K21<Настройки!$B$10,"ниже тренда",IF(K21>Настройки!$B$11,"выше тренда","норма"))) -> выше тренда | M21: =IF(L21="","",IF(L21="ниже тренда","возможное ослабление интереса",IF(L21="выше тренда","возможная фаза повышенного интереса","без выраженного отклонения"))) -> возможная фаза повышенного интереса | N21: =IF(G21="","",COUNT($G$4:G21)) -> 18
A22: =IF(Ввод_данных!A22="","",Ввод_данных!A22) -> 45017 | B22: =IF(A22="","",MONTH(A22)) -> 4 | C22: =IF(A22="","",CHOOSE(MONTH(A22),"январь","февраль","март","апрель","май","июнь","июль","август","сентябрь","октябрь","ноябрь","декабрь")) -> апрель | D22: =IF(Ввод_данных!C22="","",Ввод_данных!C22) -> 7.6 | E22: =IF(Ввод_данных!D22="","",Ввод_данных!D22) -> 2146 | F22: =IF(E22="","",IF(MAX($E$4:$E$63)=0,"",E22/MAX($E$4:$E$63)*100)) -> 59.743875 | G22: =IF(COUNT(D22,F22)=0,"",IF(COUNT(D22,F22)=2,D22*Настройки!$B$3+F22*Настройки!$B$4,IF(D22<>"",D22,F22))) -> 33.671938 | H22: =IF(OR(G22="",COUNT($G$4:G22)<12),"",AVERAGE(G11:G22)) -> 29.85731 | I22: =IF(OR(G22="",H22="",H22=0),"",G22/H22) -> 1.1277619 | J22: =IF(OR(G22="",IFERROR(VLOOKUP(B22,Сезонность!$A$3:$D$14,4,FALSE),0)=0),"",G22/IFERROR(VLOOKUP(B22,Сезонность!$A$3:$D$14,4,FALSE),1)) -> 29.945004 | K22: =IF(OR(G22="",H22="",H22=0,IFERROR(VLOOKUP(B22,Сезонность!$A$3:$D$14,4,FALSE),0)=0),"",G22/(H22*IFERROR(VLOOKUP(B22,Сезонность!$A$3:$D$14,4,FALSE),1))) -> 1.0029371 | L22: =IF(K22="","",IF(K22<Настройки!$B$10,"ниже тренда",IF(K22>Настройки!$B$11,"выше тренда","норма"))) -> норма | M22: =IF(L22="","",IF(L22="ниже тренда","возможное ослабление интереса",IF(L22="выше тренда","возможная фаза повышенного интереса","без выраженного отклонения"))) -> без выраженного отклонения | N22: =IF(G22="","",COUNT($G$4:G22)) -> 19
A23: =IF(Ввод_данных!A23="","",Ввод_данных!A23) -> 45047 | B23: =IF(A23="","",MONTH(A23)) -> 5 | C23: =IF(A23="","",CHOOSE(MONTH(A23),"январь","февраль","март","апрель","май","июнь","июль","август","сентябрь","октябрь","ноябрь","декабрь")) -> май | D23: =IF(Ввод_данных!C23="","",Ввод_данных!C23) -> 6.25 | E23: =IF(Ввод_данных!D23="","",Ввод_данных!D23) -> 2267 | F23: =IF(E23="","",IF(MAX($E$4:$E$63)=0,"",E23/MAX($E$4:$E$63)*100)) -> 63.112472 | G23: =IF(COUNT(D23,F23)=0,"",IF(COUNT(D23,F23)=2,D23*Настройки!$B$3+F23*Настройки!$B$4,IF(D23<>"",D23,F23))) -> 34.681236 | H23: =IF(OR(G23="",COUNT($G$4:G23)<12),"",AVERAGE(G12:G23)) -> 30.246095 | I23: =IF(OR(G23="",H23="",H23=0),"",G23/H23) -> 1.1466352 | J23: =IF(OR(G23="",IFERROR(VLOOKUP(B23,Сезонность!$A$3:$D$14,4,FALSE),0)=0),"",G23/IFERROR(VLOOKUP(B23,Сезонность!$A$3:$D$14,4,FALSE),1)) -> 31.421612 | K23: =IF(OR(G23="",H23="",H23=0,IFERROR(VLOOKUP(B23,Сезонность!$A$3:$D$14,4,FALSE),0)=0),"",G23/(H23*IFERROR(VLOOKUP(B23,Сезонность!$A$3:$D$14,4,FALSE),1))) -> 1.0388651 | L23: =IF(K23="","",IF(K23<Настройки!$B$10,"ниже тренда",IF(K23>Настройки!$B$11,"выше тренда","норма"))) -> норма | M23: =IF(L23="","",IF(L23="ниже тренда","возможное ослабление интереса",IF(L23="выше тренда","возможная фаза повышенного интереса","без выраженного отклонения"))) -> без выраженного отклонения | N23: =IF(G23="","",COUNT($G$4:G23)) -> 20
A24: =IF(Ввод_данных!A24="","",Ввод_данных!A24) -> 45078 | B24: =IF(A24="","",MONTH(A24)) -> 6 | C24: =IF(A24="","",CHOOSE(MONTH(A24),"январь","февраль","март","апрель","май","июнь","июль","август","сентябрь","октябрь","ноябрь","декабрь")) -> июнь | D24: =IF(Ввод_данных!C24="","",Ввод_данных!C24) -> 7.25 | E24: =IF(Ввод_данных!D24="","",Ввод_данных!D24) -> 1932 | F24: =IF(E24="","",IF(MAX($E$4:$E$63)=0,"",E24/MAX($E$4:$E$63)*100)) -> 53.786192 | G24: =IF(COUNT(D24,F24)=0,"",IF(COUNT(D24,F24)=2,D24*Настройки!$B$3+F24*Настройки!$B$4,IF(D24<>"",D24,F24))) -> 30.518096 | H24: =IF(OR(G24="",COUNT($G$4:G24)<12),"",AVERAGE(G13:G24)) -> 30.481003 | I24: =IF(OR(G24="",H24="",H24=0),"",G24/H24) -> 1.0012169 | J24: =IF(OR(G24="",IFERROR(VLOOKUP(B24,Сезонность!$A$3:$D$14,4,FALSE),0)=0),"",G24/IFERROR(VLOOKUP(B24,Сезонность!$A$3:$D$14,4,FALSE),1)) -> 28.992804 | K24: =IF(OR(G24="",H24="",H24=0,IFERROR(VLOOKUP(B24,Сезонность!$A$3:$D$14,4,FALSE),0)=0),"",G24/(H24*IFERROR(VLOOKUP(B24,Сезонность!$A$3:$D$14,4,FALSE),1))) -> 0.95117618 | L24: =IF(K24="","",IF(K24<Настройки!$B$10,"ниже тренда",IF(K24>Настройки!$B$11,"выше тренда","норма"))) -> норма | M24: =IF(L24="","",IF(L24="ниже тренда","возможное ослабление интереса",IF(L24="выше тренда","возможная фаза повышенного интереса","без выраженного отклонения"))) -> без выраженного отклонения | N24: =IF(G24="","",COUNT($G$4:G24)) -> 21
A25: =IF(Ввод_данных!A25="","",Ввод_данных!A25) -> 45108 | B25: =IF(A25="","",MONTH(A25)) -> 7 | C25: =IF(A25="","",CHOOSE(MONTH(A25),"январь","февраль","март","апрель","май","июнь","июль","август","сентябрь","октябрь","ноябрь","декабрь")) -> июль | D25: =IF(Ввод_данных!C25="","",Ввод_данных!C25) -> 5.8 | E25: =IF(Ввод_данных!D25="","",Ввод_данных!D25) -> 1795 | F25: =IF(E25="","",IF(MAX($E$4:$E$63)=0,"",E25/MAX($E$4:$E$63)*100)) -> 49.97216 | G25: =IF(COUNT(D25,F25)=0,"",IF(COUNT(D25,F25)=2,D25*Настройки!$B$3+F25*Настройки!$B$4,IF(D25<>"",D25,F25))) -> 27.88608 | H25: =IF(OR(G25="",COUNT($G$4:G25)<12),"",AVERAGE(G14:G25)) -> 31.183527 | I25: =IF(OR(G25="",H25="",H25=0),"",G25/H25) -> 0.89425676 | J25: =IF(OR(G25="",IFERROR(VLOOKUP(B25,Сезонность!$A$3:$D$14,4,FALSE),0)=0),"",G25/IFERROR(VLOOKUP(B25,Сезонность!$A$3:$D$14,4,FALSE),1)) -> 38.984473 | K25: =IF(OR(G25="",H25="",H25=0,IFERROR(VLOOKUP(B25,Сезонность!$A$3:$D$14,4,FALSE),0)=0),"",G25/(H25*IFERROR(VLOOKUP(B25,Сезонность!$A$3:$D$14,4,FALSE),1))) -> 1.2501624 | L25: =IF(K25="","",IF(K25<Настройки!$B$10,"ниже тренда",IF(K25>Настройки!$B$11,"выше тренда","норма"))) -> выше тренда | M25: =IF(L25="","",IF(L25="ниже тренда","возможное ослабление интереса",IF(L25="выше тренда","возможная фаза повышенного интереса","без выраженного отклонения"))) -> возможная фаза повышенного интереса | N25: =IF(G25="","",COUNT($G$4:G25)) -> 22
A26: =IF(Ввод_данных!A26="","",Ввод_данных!A26) -> 45139 | B26: =IF(A26="","",MONTH(A26)) -> 8 | C26: =IF(A26="","",CHOOSE(MONTH(A26),"январь","февраль","март","апрель","май","июнь","июль","август","сентябрь","октябрь","ноябрь","декабрь")) -> август | D26: =IF(Ввод_данных!C26="","",Ввод_данных!C26) -> 5.88 | E26: =IF(Ввод_данных!D26="","",Ввод_данных!D26) -> 1936 | F26: =IF(E26="","",IF(MAX($E$4:$E$63)=0,"",E26/MAX($E$4:$E$63)*100)) -> 53.89755 | G26: =IF(COUNT(D26,F26)=0,"",IF(COUNT(D26,F26)=2,D26*Настройки!$B$3+F26*Настройки!$B$4,IF(D26<>"",D26,F26))) -> 29.888775 | H26: =IF(OR(G26="",COUNT($G$4:G26)<12),"",AVERAGE(G15:G26)) -> 31.864531 | I26: =IF(OR(G26="",H26="",H26=0),"",G26/H26) -> 0.93799512 | J26: =IF(OR(G26="",IFERROR(VLOOKUP(B26,Сезонность!$A$3:$D$14,4,FALSE),0)=0),"",G26/IFERROR(VLOOKUP(B26,Сезонность!$A$3:$D$14,4,FALSE),1)) -> 41.288111 | K26: =IF(OR(G26="",H26="",H26=0,IFERROR(VLOOKUP(B26,Сезонность!$A$3:$D$14,4,FALSE),0)=0),"",G26/(H26*IFERROR(VLOOKUP(B26,Сезонность!$A$3:$D$14,4,FALSE),1))) -> 1.2957388 | L26: =IF(K26="","",IF(K26<Настройки!$B$10,"ниже тренда",IF(K26>Настройки!$B$11,"выше тренда","норма"))) -> выше тренда | M26: =IF(L26="","",IF(L26="ниже тренда","возможное ослабление интереса",IF(L26="выше тренда","возможная фаза повышенного интереса","без выраженного отклонения"))) -> возможная фаза повышенного интереса | N26: =IF(G26="","",COUNT($G$4:G26)) -> 23
... A63: =IF(Ввод_данных!A63="","",Ввод_данных!A63) -> 46266 | B63: =IF(A63="","",MONTH(A63)) -> 9 | C63: =IF(A63="","",CHOOSE(MONTH(A63),"январь","февраль","март","апрель","май","июнь","июль","август","сентябрь","октябрь","ноябрь","декабрь")) -> сентябрь | D63: =IF(Ввод_данных!C63="","",Ввод_данных!C63) -> 50.5 | E63: =IF(Ввод_данных!D63="","",Ввод_данных!D63) -> 1419 | F63: =IF(E63="","",IF(MAX($E$4:$E$63)=0,"",E63/MAX($E$4:$E$63)*100)) -> 39.504454 | G63: =IF(COUNT(D63,F63)=0,"",IF(COUNT(D63,F63)=2,D63*Настройки!$B$3+F63*Настройки!$B$4,IF(D63<>"",D63,F63))) -> 45.002227 | H63: =IF(OR(G63="",COUNT($G$4:G63)<12),"",AVERAGE(G52:G63)) -> 48.914135 | I63: =IF(OR(G63="",H63="",H63=0),"",G63/H63) -> 0.920025 | J63: =IF(OR(G63="",IFERROR(VLOOKUP(B63,Сезонность!$A$3:$D$14,4,FALSE),0)=0),"",G63/IFERROR(VLOOKUP(B63,Сезонность!$A$3:$D$14,4,FALSE),1)) -> 49.166595 | K63: =IF(OR(G63="",H63="",H63=0,IFERROR(VLOOKUP(B63,Сезонность!$A$3:$D$14,4,FALSE),0)=0),"",G63/(H63*IFERROR(VLOOKUP(B63,Сезонность!$A$3:$D$14,4,FALSE),1))) -> 1.0051613 | L63: =IF(K63="","",IF(K63<Настройки!$B$10,"ниже тренда",IF(K63>Настройки!$B$11,"выше тренда","норма"))) -> норма | M63: =IF(L63="","",IF(L63="ниже тренда","возможное ослабление интереса",IF(L63="выше тренда","возможная фаза повышенного интереса","без выраженного отклонения"))) -> без выраженного отклонения | N63: =IF(G63="","",COUNT($G$4:G63)) -> 60

Sheet Сезонность
A1: Расчет сезонных индексов по месяцам
A2: Месяц № | B2: Месяц | C2: Средний Y/T | D2: Сезонный индекс | E2: Отклонение от среднего | F2: Интерпретация
A3: 1 | B3: январь | C3: =IFERROR(SUMIFS(Расчет!$I$4:$I$63,Расчет!$B$4:$B$63,A3)/COUNTIFS(Расчет!$B$4:$B$63,A3,Расчет!$I$4:$I$63,">0"),"") -> 0.96526708 | D3: =IF(C3="","",C3/AVERAGE($C$3:$C$14)) -> 0.90669208 | E3: =IF(D3="","",D3-1) -> -0.093307919 | F3: =IF(D3="","",IF(D3>1.1,"сезонный максимум",IF(D3<0.9,"сезонный минимум","средний сезонный уровень"))) -> средний сезонный уровень
A4: 2 | B4: февраль | C4: =IFERROR(SUMIFS(Расчет!$I$4:$I$63,Расчет!$B$4:$B$63,A4)/COUNTIFS(Расчет!$B$4:$B$63,A4,Расчет!$I$4:$I$63,">0"),"") -> 0.97112236 | D4: =IF(C4="","",C4/AVERAGE($C$3:$C$14)) -> 0.91219205 | E4: =IF(D4="","",D4-1) -> -0.087807945 | F4: =IF(D4="","",IF(D4>1.1,"сезонный максимум",IF(D4<0.9,"сезонный минимум","средний сезонный уровень"))) -> средний сезонный уровень
A5: 3 | B5: март | C5: =IFERROR(SUMIFS(Расчет!$I$4:$I$63,Расчет!$B$4:$B$63,A5)/COUNTIFS(Расчет!$B$4:$B$63,A5,Расчет!$I$4:$I$63,">0"),"") -> 1.1001623 | D5: =IF(C5="","",C5/AVERAGE($C$3:$C$14)) -> 1.0334015 | E5: =IF(D5="","",D5-1) -> 0.033401464 | F5: =IF(D5="","",IF(D5>1.1,"сезонный максимум",IF(D5<0.9,"сезонный минимум","средний сезонный уровень"))) -> средний сезонный уровень
A6: 4 | B6: апрель | C6: =IFERROR(SUMIFS(Расчет!$I$4:$I$63,Расчет!$B$4:$B$63,A6)/COUNTIFS(Расчет!$B$4:$B$63,A6,Расчет!$I$4:$I$63,">0"),"") -> 1.1971027 | D6: =IF(C6="","",C6/AVERAGE($C$3:$C$14)) -> 1.1244593 | E6: =IF(D6="","",D6-1) -> 0.12445929 | F6: =IF(D6="","",IF(D6>1.1,"сезонный максимум",IF(D6<0.9,"сезонный минимум","средний сезонный уровень"))) -> сезонный максимум
A7: 5 | B7: май | C7: =IFERROR(SUMIFS(Расчет!$I$4:$I$63,Расчет!$B$4:$B$63,A7)/COUNTIFS(Расчет!$B$4:$B$63,A7,Расчет!$I$4:$I$63,">0"),"") -> 1.175043 | D7: =IF(C7="","",C7/AVERAGE($C$3:$C$14)) -> 1.1037383 | E7: =IF(D7="","",D7-1) -> 0.10373828 | F7: =IF(D7="","",IF(D7>1.1,"сезонный максимум",IF(D7<0.9,"сезонный минимум","средний сезонный уровень"))) -> сезонный максимум
A8: 6 | B8: июнь | C8: =IFERROR(SUMIFS(Расчет!$I$4:$I$63,Расчет!$B$4:$B$63,A8)/COUNTIFS(Расчет!$B$4:$B$63,A8,Расчет!$I$4:$I$63,">0"),"") -> 1.120611 | D8: =IF(C8="","",C8/AVERAGE($C$3:$C$14)) -> 1.0526093 | E8: =IF(D8="","",D8-1) -> 0.052609322 | F8: =IF(D8="","",IF(D8>1.1,"сезонный максимум",IF(D8<0.9,"сезонный минимум","средний сезонный уровень"))) -> средний сезонный уровень
A9: 7 | B9: июль | C9: =IFERROR(SUMIFS(Расчет!$I$4:$I$63,Расчет!$B$4:$B$63,A9)/COUNTIFS(Расчет!$B$4:$B$63,A9,Расчет!$I$4:$I$63,">0"),"") -> 0.76152378 | D9: =IF(C9="","",C9/AVERAGE($C$3:$C$14)) -> 0.71531248 | E9: =IF(D9="","",D9-1) -> -0.28468752 | F9: =IF(D9="","",IF(D9>1.1,"сезонный максимум",IF(D9<0.9,"сезонный минимум","средний сезонный уровень"))) -> сезонный минимум
A10: 8 | B10: август | C10: =IFERROR(SUMIFS(Расчет!$I$4:$I$63,Расчет!$B$4:$B$63,A10)/COUNTIFS(Расчет!$B$4:$B$63,A10,Расчет!$I$4:$I$63,">0"),"") -> 0.77067412 | D10: =IF(C10="","",C10/AVERAGE($C$3:$C$14)) -> 0.72390755 | E10: =IF(D10="","",D10-1) -> -0.27609245 | F10: =IF(D10="","",IF(D10>1.1,"сезонный максимум",IF(D10<0.9,"сезонный минимум","средний сезонный уровень"))) -> сезонный минимум
A11: 9 | B11: сентябрь | C11: =IFERROR(SUMIFS(Расчет!$I$4:$I$63,Расчет!$B$4:$B$63,A11)/COUNTIFS(Расчет!$B$4:$B$63,A11,Расчет!$I$4:$I$63,">0"),"") -> 0.97443201 | D11: =IF(C11="","",C11/AVERAGE($C$3:$C$14)) -> 0.91530087 | E11: =IF(D11="","",D11-1) -> -0.084699134 | F11: =IF(D11="","",IF(D11>1.1,"сезонный максимум",IF(D11<0.9,"сезонный минимум","средний сезонный уровень"))) -> средний сезонный уровень
A12: 10 | B12: октябрь | C12: =IFERROR(SUMIFS(Расчет!$I$4:$I$63,Расчет!$B$4:$B$63,A12)/COUNTIFS(Расчет!$B$4:$B$63,A12,Расчет!$I$4:$I$63,">0"),"") -> 1.1472703 | D12: =IF(C12="","",C12/AVERAGE($C$3:$C$14)) -> 1.0776509 | E12: =IF(D12="","",D12-1) -> 0.0776509 | F12: =IF(D12="","",IF(D12>1.1,"сезонный максимум",IF(D12<0.9,"сезонный минимум","средний сезонный уровень"))) -> средний сезонный уровень
A13: 11 | B13: ноябрь | C13: =IFERROR(SUMIFS(Расчет!$I$4:$I$63,Расчет!$B$4:$B$63,A13)/COUNTIFS(Расчет!$B$4:$B$63,A13,Расчет!$I$4:$I$63,">0"),"") -> 1.2406684 | D13: =IF(C13="","",C13/AVERAGE($C$3:$C$14)) -> 1.1653813 | E13: =IF(D13="","",D13-1) -> 0.16538133 | F13: =IF(D13="","",IF(D13>1.1,"сезонный максимум",IF(D13<0.9,"сезонный минимум","средний сезонный уровень"))) -> сезонный максимум
A14: 12 | B14: декабрь | C14: =IFERROR(SUMIFS(Расчет!$I$4:$I$63,Расчет!$B$4:$B$63,A14)/COUNTIFS(Расчет!$B$4:$B$63,A14,Расчет!$I$4:$I$63,">0"),"") -> 1.3513584 | D14: =IF(C14="","",C14/AVERAGE($C$3:$C$14)) -> 1.2693544 | E14: =IF(D14="","",D14-1) -> 0.26935438 | F14: =IF(D14="","",IF(D14>1.1,"сезонный максимум",IF(D14<0.9,"сезонный минимум","средний сезонный уровень"))) -> сезонный максимум
A15: Показатель | B15: Значение
A16: Максимальный сезонный индекс | B16: =MAX($D$3:$D$14) -> 1.2693544
A17: Минимальный сезонный индекс | B17: =MIN($D$3:$D$14) -> 0.71531248
A18: Амплитуда сезонности | B18: =B16-B17 -> 0.55404191
A19: Оценка силы сезонности | B19: =IF(B18>=Настройки!$B$6,"выраженная сезонность",IF(B18>=Настройки!$B$7,"умеренная сезонность","слабая сезонность")) -> выраженная сезонность
A20: Месяц максимума | B20: =IFERROR(INDEX($B$3:$B$14,MATCH(B16,$D$3:$D$14,0)),"") -> декабрь
A21: Месяц минимума | B21: =IFERROR(INDEX($B$3:$B$14,MATCH(B17,$D$3:$D$14,0)),"") -> июль

Sheet Оценка_тренда
A1: Оценка устойчивой динамики интереса
A2: Показатель | B2: Формула / значение | C2: Интерпретация | D2: Комментарий
A3: Количество наблюдений | B3: =COUNT(Расчет!$G$4:$G$63) -> 60 | C3: минимально желательно не менее 24 месяцев | D3: чем длиннее ряд, тем надежнее оценка
A4: Средний индекс за первые 12 месяцев | B4: =IF(B3<12,"",SUMIFS(Расчет!$G$4:$G$63,Расчет!$N$4:$N$63,">=1",Расчет!$N$4:$N$63,"<=12")/COUNTIFS(Расчет!$N$4:$N$63,">=1",Расчет!$N$4:$N$63,"<=12")) -> 29.020588 | C4: исходный уровень интереса | D4: используется для сравнения с последним годом
A5: Средний индекс за последние 12 месяцев | B5: =IF(B3<12,"",SUMIFS(Расчет!$G$4:$G$63,Расчет!$N$4:$N$63,">="&B3-11,Расчет!$N$4:$N$63,"<="&B3)/COUNTIFS(Расчет!$N$4:$N$63,">="&B3-11,Расчет!$N$4:$N$63,"<="&B3)) -> 48.914135 | C5: текущий уровень интереса | D5: сравнивается с первым годом
A6: Абсолютное изменение | B6: =IF(OR(B4="",B5=""),"",B5-B4) -> 19.893547 | C6: последние 12 месяцев минус первые 12 месяцев | D6: положительное значение означает рост
A7: Относительное изменение | B7: =IF(OR(B4="",B5=""),"",B6/B4) -> 0.68549771 | C7: темп изменения среднего уровня | D7: ключевой показатель тренда
A8: Наклон линейного тренда | B8: =IFERROR(SLOPE(Расчет!$G$4:$G$63,Расчет!$N$4:$N$63),"") -> 0.35072853 | C8: среднее изменение за месяц | D8: дополнительная оценка направления
A9: Классификация тренда | B9: =IF(B7="","",IF(B7>=Настройки!$B$9,"растущий тренд",IF(B7<=Настройки!$B$8,"снижающийся тренд","стабильный тренд"))) -> растущий тренд | C9: растущий / стабильный / снижающийся | D9: по порогам на листе «Настройки»
A10: Управленческий вывод | B10: =IF(B9="","Недостаточно данных",IF(B9="растущий тренд","Интерес аудитории растет; бизнес-идея может быть дополнительно проверена на платежеспособный спрос.",IF(B9="снижающийся тренд","Интерес аудитории снижается; требуется осторожная проверка ниши, сегмента и каналов продвижения.","Интерес аудитории относительно стабилен; целесообразно изучить структуру спроса, конкурентов и целевые сегменты."))) -> Интерес аудитории растет; бизнес-идея может быть дополнительно проверена на платежеспособный спрос. | C10: готовая формулировка для отчета | D10: используется в обосновании бизнес-идеи

Sheet Деловые_циклы
A1: Оценка циклических отклонений и фаз спроса
A2: В таблице оценивается поисковый цикл спроса, то есть периоды, когда интерес находится выше или ниже трендово-сезонного уровня.
A3: Показатель | B3: Значение
A4: Последний период | B4: =IFERROR(INDEX(Расчет!$A$4:$A$63,Оценка_тренда!$B$3),"") -> 46266
A5: Текущий циклический коэффициент | B5: =IFERROR(INDEX(Расчет!$K$4:$K$63,Оценка_тренда!$B$3),"") -> 1.0051613
A6: Текущая фаза | B6: =IFERROR(INDEX(Расчет!$L$4:$L$63,Оценка_тренда!$B$3),"") -> норма
A7: Минимальный коэффициент | B7: =MIN(Расчет!$K$4:$K$63) -> 0.87820576
A8: Максимальный коэффициент | B8: =MAX(Расчет!$K$4:$K$63) -> 1.2957388
A9: Амплитуда циклических колебаний | B9: =B8-B7 -> 0.41753308
A10: Период | B10: Сводный индекс | C10: Тренд | D10: Сезонный индекс | E10: Сезонно очищенный индекс | F10: Циклический коэффициент | G10: Фаза | H10: Практическое значение
A11: =Расчет!A4 -> 44470 | B11: =Расчет!G4 -> 25.32706 | C11: =Расчет!H4 | D11: =IFERROR(VLOOKUP(Расчет!B4,Сезонность!$A$3:$D$14,4,FALSE),"") -> 1.0776509 | E11: =Расчет!J4 -> 23.502101 | F11: =Расчет!K4 | G11: =Расчет!L4 | H11: =IF(B11="","","окно 12 мес. не накоплено, период входит в расчет сезонности после 12-го месяца") -> окно 12 мес. не накоплено, период входит в расчет сезонности после 12-го месяца
A12: =Расчет!A5 -> 44501 | B12: =Расчет!G5 -> 34.047751 | C12: =Расчет!H5 | D12: =IFERROR(VLOOKUP(Расчет!B5,Сезонность!$A$3:$D$14,4,FALSE),"") -> 1.1653813 | E12: =Расчет!J5 -> 29.215974 | F12: =Расчет!K5 | G12: =Расчет!L5 | H12: =IF(B12="","","окно 12 мес. не накоплено, период входит в расчет сезонности после 12-го месяца") -> окно 12 мес. не накоплено, период входит в расчет сезонности после 12-го месяца
A13: =Расчет!A6 -> 44531 | B13: =Расчет!G6 -> 37.55971 | C13: =Расчет!H6 | D13: =IFERROR(VLOOKUP(Расчет!B6,Сезонность!$A$3:$D$14,4,FALSE),"") -> 1.2693544 | E13: =Расчет!J6 -> 29.589617 | F13: =Расчет!K6 | G13: =Расчет!L6 | H13: =IF(B13="","","окно 12 мес. не накоплено, период входит в расчет сезонности после 12-го месяца") -> окно 12 мес. не накоплено, период входит в расчет сезонности после 12-го месяца
A14: =Расчет!A7 -> 44562 | B14: =Расчет!G7 -> 28.058241 | C14: =Расчет!H7 | D14: =IFERROR(VLOOKUP(Расчет!B7,Сезонность!$A$3:$D$14,4,FALSE),"") -> 0.90669208 | E14: =Расчет!J7 -> 30.945721 | F14: =Расчет!K7 | G14: =Расчет!L7 | H14: =IF(B14="","","окно 12 мес. не накоплено, период входит в расчет сезонности после 12-го месяца") -> окно 12 мес. не накоплено, период входит в расчет сезонности после 12-го месяца
A15: =Расчет!A8 -> 44593 | B15: =Расчет!G8 -> 30.51294 | C15: =Расчет!H8 | D15: =IFERROR(VLOOKUP(Расчет!B8,Сезонность!$A$3:$D$14,4,FALSE),"") -> 0.91219205 | E15: =Расчет!J8 -> 33.450127 | F15: =Расчет!K8 | G15: =Расчет!L8 | H15: =IF(B15="","","окно 12 мес. не накоплено, период входит в расчет сезонности после 12-го месяца") -> окно 12 мес. не накоплено, период входит в расчет сезонности после 12-го месяца
A16: =Расчет!A9 -> 44621 | B16: =Расчет!G9 -> 35.161047 | C16: =Расчет!H9 | D16: =IFERROR(VLOOKUP(Расчет!B9,Сезонность!$A$3:$D$14,4,FALSE),"") -> 1.0334015 | E16: =Расчет!J9 -> 34.024576 | F16: =Расчет!K9 | G16: =Расчет!L9 | H16: =IF(B16="","","окно 12 мес. не накоплено, период входит в расчет сезонности после 12-го месяца") -> окно 12 мес. не накоплено, период входит в расчет сезонности после 12-го месяца
A17: =Расчет!A10 -> 44652 | B17: =Расчет!G10 -> 31.795234 | C17: =Расчет!H10 | D17: =IFERROR(VLOOKUP(Расчет!B10,Сезонность!$A$3:$D$14,4,FALSE),"") -> 1.1244593 | E17: =Расчет!J10 -> 28.27602 | F17: =Расчет!K10 | G17: =Расчет!L10 | H17: =IF(B17="","","окно 12 мес. не накоплено, период входит в расчет сезонности после 12-го месяца") -> окно 12 мес. не накоплено, период входит в расчет сезонности после 12-го месяца
A18: =Расчет!A11 -> 44682 | B18: =Расчет!G11 -> 30.015813 | C18: =Расчет!H11 | D18: =IFERROR(VLOOKUP(Расчет!B11,Сезонность!$A$3:$D$14,4,FALSE),"") -> 1.1037383 | E18: =Расчет!J11 -> 27.194683 | F18: =Расчет!K11 | G18: =Расчет!L11 | H18: =IF(B18="","","окно 12 мес. не накоплено, период входит в расчет сезонности после 12-го месяца") -> окно 12 мес. не накоплено, период входит в расчет сезонности после 12-го месяца
A19: =Расчет!A12 -> 44713 | B19: =Расчет!G12 -> 27.699198 | C19: =Расчет!H12 | D19: =IFERROR(VLOOKUP(Расчет!B12,Сезонность!$A$3:$D$14,4,FALSE),"") -> 1.0526093 | E19: =Расчет!J12 -> 26.314795 | F19: =Расчет!K12 | G19: =Расчет!L12 | H19: =IF(B19="","","окно 12 мес. не накоплено, период входит в расчет сезонности после 12-го месяца") -> окно 12 мес. не накоплено, период входит в расчет сезонности после 12-го месяца
A20: =Расчет!A13 -> 44743 | B20: =Расчет!G13 -> 19.455791 | C20: =Расчет!H13 | D20: =IFERROR(VLOOKUP(Расчет!B13,Сезонность!$A$3:$D$14,4,FALSE),"") -> 0.71531248 | E20: =Расчет!J13 -> 27.199009 | F20: =Расчет!K13 | G20: =Расчет!L13 | H20: =IF(B20="","","окно 12 мес. не накоплено, период входит в расчет сезонности после 12-го месяца") -> окно 12 мес. не накоплено, период входит в расчет сезонности после 12-го месяца
A21: =Расчет!A14 -> 44774 | B21: =Расчет!G14 -> 21.716726 | C21: =Расчет!H14 | D21: =IFERROR(VLOOKUP(Расчет!B14,Сезонность!$A$3:$D$14,4,FALSE),"") -> 0.72390755 | E21: =Расчет!J14 -> 29.999309 | F21: =Расчет!K14 | G21: =Расчет!L14 | H21: =IF(B21="","","окно 12 мес. не накоплено, период входит в расчет сезонности после 12-го месяца") -> окно 12 мес. не накоплено, период входит в расчет сезонности после 12-го месяца
A22: =Расчет!A15 -> 44805 | B22: =Расчет!G15 -> 26.89755 | C22: =Расчет!H15 -> 29.020588 | D22: =IFERROR(VLOOKUP(Расчет!B15,Сезонность!$A$3:$D$14,4,FALSE),"") -> 0.91530087 | E22: =Расчет!J15 -> 29.386567 | F22: =Расчет!K15 -> 1.012611 | G22: =Расчет!L15 -> норма | H22: =IF(G22="","",IF(G22="ниже тренда","период осторожного планирования продаж и бюджета",IF(G22="выше тренда","период активизации продвижения и продаж","обычный режим анализа спроса"))) -> обычный режим анализа спроса
A23: =Расчет!A16 -> 44835 | B23: =Расчет!G16 -> 29.452227 | C23: =Расчет!H16 -> 29.364352 | D23: =IFERROR(VLOOKUP(Расчет!B16,Сезонность!$A$3:$D$14,4,FALSE),"") -> 1.0776509 | E23: =Расчет!J16 -> 27.330026 | F23: =Расчет!K16 -> 0.93072123 | G23: =Расчет!L16 -> норма | H23: =IF(G23="","",IF(G23="ниже тренда","период осторожного планирования продаж и бюджета",IF(G23="выше тренда","период активизации продвижения и продаж","обычный режим анализа спроса"))) -> обычный режим анализа спроса
A24: =Расчет!A17 -> 44866 | B24: =Расчет!G17 -> 35.178307 | C24: =Расчет!H17 -> 29.458565 | D24: =IFERROR(VLOOKUP(Расчет!B17,Сезонность!$A$3:$D$14,4,FALSE),"") -> 1.1653813 | E24: =Расчет!J17 -> 30.186091 | F24: =Расчет!K17 -> 1.0246966 | G24: =Расчет!L17 -> норма | H24: =IF(G24="","",IF(G24="ниже тренда","период осторожного планирования продаж и бюджета",IF(G24="выше тренда","период активизации продвижения и продаж","обычный режим анализа спроса"))) -> обычный режим анализа спроса
A25: =Расчет!A18 -> 44896 | B25: =Расчет!G18 -> 40.829198 | C25: =Расчет!H18 -> 29.731023 | D25: =IFERROR(VLOOKUP(Расчет!B18,Сезонность!$A$3:$D$14,4,FALSE),"") -> 1.2693544 | E25: =Расчет!J18 -> 32.165327 | F25: =Расчет!K18 -> 1.0818776 | G25: =Расчет!L18 -> норма | H25: =IF(G25="","",IF(G25="ниже тренда","период осторожного планирования продаж и бюджета",IF(G25="выше тренда","период активизации продвижения и продаж","обычный режим анализа спроса"))) -> обычный режим анализа спроса
A26: =Расчет!A19 -> 44927 | B26: =Расчет!G19 -> 31.297327 | C26: =Расчет!H19 -> 30.000947 | D26: =IFERROR(VLOOKUP(Расчет!B19,Сезонность!$A$3:$D$14,4,FALSE),"") -> 0.90669208 | E26: =Расчет!J19 -> 34.518144 | F26: =Расчет!K19 -> 1.1505685 | G26: =Расчет!L19 -> выше тренда | H26: =IF(G26="","",IF(G26="ниже тренда","период осторожного планирования продаж и бюджета",IF(G26="выше тренда","период активизации продвижения и продаж","обычный режим анализа спроса"))) -> период активизации продвижения и продаж
A27: =Расчет!A20 -> 44958 | B27: =Расчет!G20 -> 27.824477 | C27: =Расчет!H20 -> 29.776908 | D27: =IFERROR(VLOOKUP(Расчет!B20,Сезонность!$A$3:$D$14,4,FALSE),"") -> 0.91219205 | E27: =Расчет!J20 -> 30.502871 | F27: =Расчет!K20 -> 1.0243801 | G27: =Расчет!L20 -> норма | H27: =IF(G27="","",IF(G27="ниже тренда","период осторожного планирования продаж и бюджета",IF(G27="выше тренда","период активизации продвижения и продаж","обычный режим анализа спроса"))) -> обычный режим анализа спроса
A28: =Расчет!A21 -> 44986 | B28: =Расчет!G21 -> 34.249165 | C28: =Расчет!H21 -> 29.700918 | D28: =IFERROR(VLOOKUP(Расчет!B21,Сезонность!$A$3:$D$14,4,FALSE),"") -> 1.0334015 | E28: =Расчет!J21 -> 33.142168 | F28: =Расчет!K21 -> 1.1158634 | G28: =Расчет!L21 -> выше тренда | H28: =IF(G28="","",IF(G28="ниже тренда","период осторожного планирования продаж и бюджета",IF(G28="выше тренда","период активизации продвижения и продаж","обычный режим анализа спроса"))) -> период активизации продвижения и продаж
A29: =Расчет!A22 -> 45017 | B29: =Расчет!G22 -> 33.671938 | C29: =Расчет!H22 -> 29.85731 | D29: =IFERROR(VLOOKUP(Расчет!B22,Сезонность!$A$3:$D$14,4,FALSE),"") -> 1.1244593 | E29: =Расчет!J22 -> 29.945004 | F29: =Расчет!K22 -> 1.0029371 | G29: =Расчет!L22 -> норма | H29: =IF(G29="","",IF(G29="ниже тренда","период осторожного планирования продаж и бюджета",IF(G29="выше тренда","период активизации продвижения и продаж","обычный режим анализа спроса"))) -> обычный режим анализа спроса
A30: =Расчет!A23 -> 45047 | B30: =Расчет!G23 -> 34.681236 | C30: =Расчет!H23 -> 30.246095 | D30: =IFERROR(VLOOKUP(Расчет!B23,Сезонность!$A$3:$D$14,4,FALSE),"") -> 1.1037383 | E30: =Расчет!J23 -> 31.421612 | F30: =Расчет!K23 -> 1.0388651 | G30: =Расчет!L23 -> норма | H30: =IF(G30="","",IF(G30="ниже тренда","период осторожного планирования продаж и бюджета",IF(G30="выше тренда","период активизации продвижения и продаж","обычный режим анализа спроса"))) -> обычный режим анализа спроса
A31: =Расчет!A24 -> 45078 | B31: =Расчет!G24 -> 30.518096 | C31: =Расчет!H24 -> 30.481003 | D31: =IFERROR(VLOOKUP(Расчет!B24,Сезонность!$A$3:$D$14,4,FALSE),"") -> 1.0526093 | E31: =Расчет!J24 -> 28.992804 | F31: =Расчет!K24 -> 0.95117618 | G31: =Расчет!L24 -> норма | H31: =IF(G31="","",IF(G31="ниже тренда","период осторожного планирования продаж и бюджета",IF(G31="выше тренда","период активизации продвижения и продаж","обычный режим анализа спроса"))) -> обычный режим анализа спроса
A32: =Расчет!A25 -> 45108 | B32: =Расчет!G25 -> 27.88608 | C32: =Расчет!H25 -> 31.183527 | D32: =IFERROR(VLOOKUP(Расчет!B25,Сезонность!$A$3:$D$14,4,FALSE),"") -> 0.71531248 | E32: =Расчет!J25 -> 38.984473 | F32: =Расчет!K25 -> 1.2501624 | G32: =Расчет!L25 -> выше тренда | H32: =IF(G32="","",IF(G32="ниже тренда","период осторожного планирования продаж и бюджета",IF(G32="выше тренда","период активизации продвижения и продаж","обычный режим анализа спроса"))) -> период активизации продвижения и продаж
A33: =Расчет!A26 -> 45139 | B33: =Расчет!G26 -> 29.888775 | C33: =Расчет!H26 -> 31.864531 | D33: =IFERROR(VLOOKUP(Расчет!B26,Сезонность!$A$3:$D$14,4,FALSE),"") -> 0.72390755 | E33: =Расчет!J26 -> 41.288111 | F33: =Расчет!K26 -> 1.2957388 | G33: =Расчет!L26 -> выше тренда | H33: =IF(G33="","",IF(G33="ниже тренда","период осторожного планирования продаж и бюджета",IF(G33="выше тренда","период активизации продвижения и продаж","обычный режим анализа спроса"))) -> период активизации продвижения и продаж
... A70: =Расчет!A63 -> 46266 | B70: =Расчет!G63 -> 45.002227 | C70: =Расчет!H63 -> 48.914135 | D70: =IFERROR(VLOOKUP(Расчет!B63,Сезонность!$A$3:$D$14,4,FALSE),"") -> 0.91530087 | E70: =Расчет!J63 -> 49.166595 | F70: =Расчет!K63 -> 1.0051613 | G70: =Расчет!L63 -> норма | H70: =IF(G70="","",IF(G70="ниже тренда","период осторожного планирования продаж и бюджета",IF(G70="выше тренда","период активизации продвижения и продаж","обычный режим анализа спроса"))) -> обычный режим анализа спроса

Sheet Журнал_выгрузки
A1: Журнал выгрузки исходных данных
A2: Дата выгрузки | B2: Источник | C2: Запрос / кластер | D2: Регион | E2: Период | F2: Формат файла | G2: Имя файла | H2: Примечание
A3: 46297 | B3: Google Trends | C3: среднее индексов запросов excel audit и spreadsheet audit | D3: весь мир | E3: 2021-10 - 2026-09 (5 лет, недели -> месяцы) | F3: текст (сжатый, base62) | G3: S_excel_audit_5y.txt; S_spreadsheet_audit_5y.txt | H3: веб-поиск, все категории; недели усреднены по месяцам; неполная последняя неделя исключена
A4: 46297 | B4: Яндекс Вордстат | C4: проверка формул excel; ошибки в формулах excel; аудит excel; проверить excel на ошибки | D4: Россия (код 225) | E4: 2021-10 - 2026-09 (месяцы) | F4: CSV/JSON | G4: YW_динамика_месяцы_2018-01_2026-09.csv | H4: вкладка «Динамика», все устройства; значения запросов кластера суммированы

Sheet Методика_и_источники
A1: Методика использования файла и источники
A2: Раздел | B2: Содержание | C2: Практическое действие | D2: Результат | E2: Ограничение | F2: Источник
A3: 1. Сбор данных | B3: Выгрузить данные из Google Trends и Яндекс Вордстат за одинаковый период и одну территорию. | C3: Зафиксировать регион, период, запросы, категорию и тип поиска. | D3: Сопоставимый временной ряд. | E3: Разные источники отражают разные аудитории. | F3: https://support.google.com/trends/answer/4365538?hl=en
A4: 2. Нормирование | B4: Google Trends уже представлен как индекс 0–100; Вордстат нормируется относительно максимума в выбранном ряду. | C4: Ввести фактические значения на лист «Ввод_данных». | D4: Сводный индекс интереса. | E4: Нормирование не превращает поисковый интерес в размер рынка. | F4: https://support.google.com/trends/answer/4365533?hl=en
A5: 3. Тренд | B5: Тренд оценивается через средние значения и скользящее среднее за 12 месяцев. | C5: Смотреть лист «Оценка_тренда». | D5: Рост, стабильность или снижение интереса. | E5: Короткие ряды менее надежны. | F5: https://otexts.com/fpp3/moving-averages.html
A6: 4. Сезонность | B6: Сезонный индекс показывает, в какие месяцы интерес выше или ниже среднего трендового уровня. | C6: Смотреть лист «Сезонность». | D6: Месяцы максимального и минимального спроса. | E6: Сезонность корректнее оценивать по данным за 2–3 года и более. | F6: https://otexts.com/fpp3/classical-decomposition.html
A7: 5. Циклы спроса | B7: Циклический коэффициент показывает отклонение от тренда с учетом сезонности. | C7: Смотреть лист «Деловые_циклы». | D7: Периоды выше или ниже нормального уровня спроса. | E7: Это поисковый цикл спроса, а не прямое измерение макроэкономического делового цикла. | F7: https://otexts.com/fpp3/tspatterns.html
A8: 6. Яндекс Вордстат | B8: Вордстат показывает статистику поисковых запросов к Яндексу, динамику популярности и региональные различия. | C8: Использовать одинаковые запросы и географические настройки. | D8: Оценка интереса аудитории Яндекса. | E8: Не отражает весь интернет-рынок. | F8: https://wordstat.yandex.ru/

Sheet Настройки
A1: Настройки модели оценки тренда, сезонности и циклов
A2: Параметр | B2: Значение | C2: Назначение | D2: Рекомендация
A3: Вес Google Trends | B3: 0.5 | C3: Доля индекса Google Trends в сводном индексе | D3: 0,40–0,60
A4: Вес Яндекс Вордстат | B4: 0.5 | C4: Доля нормированного показателя Вордстат в сводном индексе | D4: 0,40–0,60
A5: Окно скользящего среднего, мес. | B5: 12 | C5: Период сглаживания для оценки тренда | D5: 12 месяцев
A6: Порог сильной сезонности | B6: 0.3 | C6: Амплитуда сезонных индексов, при которой сезонность считается выраженной | D6: 0,25–0,35
A7: Порог слабой сезонности | B7: 0.15 | C7: Амплитуда сезонных индексов для умеренной сезонности | D7: 0,10–0,20
A8: Порог снижения тренда | B8: -0.15 | C8: Граница для классификации снижающегося тренда | D8: -15%
A9: Порог роста тренда | B9: 0.15 | C9: Граница для классификации растущего тренда | D9: +15%
A10: Нижний порог цикла | B10: 0.9 | C10: Ниже этого значения спрос считается ниже трендового уровня | D10: 0,90
A11: Верхний порог цикла | B11: 1.1 | C11: Выше этого значения спрос считается выше трендового уровня | D11: 1,10
