Workbook

Sheet 00_Инструкция
A1: Сборка бизнес-модели по Канвас
A2: Назначение файла
A3: Книга переводит результаты анализа конкурентов, отзывов, уровней конкуренции, цифрового товара, ценностного предложения и монетизации в связанную бизнес-модель по шаблону Канвас. Исходные данные выделены голубым, расчетные поля - светлым фоном.
A4: Этап | B4: Содержание | C4: Лист | D4: Что получится | E4: Контроль качества
A5: 1 | B5: Внести выводы из всех предыдущих видов анализа | C5: 01_Данные_анализа | D5: Единый банк фактов и доказательств | E5: Каждый вывод должен иметь источник, блок Канвас и оценку достоверности
A6: 2 | B6: 9 блоков Канвас | C6: 02_Канвас | D6: Черновик бизнес-модели | E6: По каждому блоку должны быть формулировка, доказательства, оценка полноты и риска
A7: 3 | B7: Детализировать сегменты, проблемы и ценность | C7: 03_Сегменты; 04_Ценность_товар | D7: Связка «клиент - проблема - ценность - цифровой товар» | E7: Не должно быть ценности без подтвержденной проблемы
A8: 4 | B8: Описать каналы, отношения и монетизацию | C8: 05_Каналы_отношения; 06_Монетизация | D8: Механизм привлечения, продажи, удержания и получения дохода | E8: Единица монетизации должна быть связана с воспринимаемой ценностью
A9: 5 | B9: Собрать операционную и затратную часть | C9: 07_Операционная_основа; 08_Затраты | D9: Основания выполнения обещания ценности | E9: Ключевые ресурсы и действия должны поддерживать ценностное предложение
A10: 6 | B10: Проверить связность бизнес-модели | C10: 09_Проверка_связности | D10: Карта слабых мест бизнес-модели | E10: Разрывы переводятся в задачи проверки или доработки
A11: 7 | B11: Сформировать итоговый паспорт | C11: 10_Паспорт; 11_Дашборд | D11: Итоговое описание бизнес-модели и сводные показатели | E11: Паспорт используется для презентации и управленческого обсуждения

Sheet 01_Данные_анализа
A1: Единый банк выводов из всех видов анализа
A2: ID | B2: Источник анализа | C2: Объект анализа | D2: Компания / товар | E2: Ссылка или место фиксации | F2: Факт / наблюдение | G2: Вывод для бизнес-модели | H2: Блок Канвас | I2: Достоверность 1-5 | J2: Актуальность 1-5 | K2: Приоритет 1-5 | L2: Индекс доказательности | M2: Статус использования | N2: Комментарий
A3: 1 | B3: Отчет ЛР1 | C3: запросы о таблицах Excel | D3: Вордстат | E3: ЛР1, раздел 2.4 | F3: Структура намерений 4 578 запросов - проблемные 36,6 %, AI 45,3 %, проверка 8,6 %, услуги 2,3 % | G3: Спрос проблемный, прямого запроса на аудит мало | H3: Клиентские сегменты | I3: 4 | J3: 5 | K3: 4 | L3: =IF(COUNTA(B3:K3)=0,"",ROUND(AVERAGE(I3:K3),2)) -> 4.33 | M3: использовано | N3: SRC-001
A4: 2 | B4: Отчет ЛР2-3 | C4: рынок | D4: Расчеты | E4: ЛР2-3, раздел 2.10 | F4: SAM 35 млн у.е. в год; индекс платежеспособности сегментов 2,4 | G4: Платежеспособность достаточная | H4: Потоки доходов | I4: 4 | J4: 5 | K4: 4 | L4: =IF(COUNTA(B4:K4)=0,"",ROUND(AVERAGE(I4:K4),2)) -> 4.33 | M4: использовано | N4: SRC-002
A5: 3 | B5: Отчет ЛР4 | C5: 12 сайтов | D5: Similarweb | E5: ЛР4, раздел 2.2 | F5: Заменители дают 73 % релевантного трафика; CR3 52 % | G5: Критичная сила - заменители | H5: Каналы | I5: 4 | J5: 5 | K5: 4 | L5: =IF(COUNTA(B5:K5)=0,"",ROUND(AVERAGE(I5:K5),2)) -> 4.33 | M5: использовано | N5: SRC-003
A6: 4 | B6: Отзывы | C6: PerfectXL | D6: G2 | E6: https://www.g2.com/search?query=perfectxl | F6: 0 отзывов на G2 и Trustpilot | G6: У прямых конкурентов нет публичных отзывов | H6: Отношения с клиентами | I6: 5 | J6: 5 | K6: 4 | L6: =IF(COUNTA(B6:K6)=0,"",ROUND(AVERAGE(I6:K6),2)) -> 4.67 | M6: использовано | N6: SRC-004
A7: 5 | B7: Отзывы | C7: Datarails | D7: G2 | E7: https://www.g2.com/search?query=datarails | F7: 386 отзывов, 4,6 | G7: Платформы сильнее в доверии | H7: Отношения с клиентами | I7: 5 | J7: 5 | K7: 4 | L7: =IF(COUNTA(B7:K7)=0,"",ROUND(AVERAGE(I7:K7),2)) -> 4.67 | M7: использовано | N7: SRC-005
A8: 6 | B8: Страница цен | C8: PerfectXL | D8: perfectxl.com | E8: https://www.perfectxl.com/pricing/ | F8: Отдельный инструмент от 69 у.е. в месяц; пакеты без цен | G8: Цена специализированных аналогов выше Pro 19 у.е. | H8: Потоки доходов | I8: 5 | J8: 5 | K8: 4 | L8: =IF(COUNTA(B8:K8)=0,"",ROUND(AVERAGE(I8:K8),2)) -> 4.67 | M8: использовано | N8: SRC-006
A9: 7 | B9: Страница цен | C9: Shortcut | D9: shortcut.ai | E9: https://www.shortcut.ai/pricing | F9: Free, Pro 89 у.е., Teams 284 у.е. + 89 у.е. за место | G9: Лестница тарифов с бесплатным входом | H9: Потоки доходов | I9: 5 | J9: 5 | K9: 4 | L9: =IF(COUNTA(B9:K9)=0,"",ROUND(AVERAGE(I9:K9),2)) -> 4.67 | M9: использовано | N9: SRC-007
A10: 8 | B10: Главная страница | C10: Shortcut | D10: shortcut.ai | E10: https://www.shortcut.ai/ | F10: SOC 2 Type II, нулевое хранение данных | G10: Безопасность - обязательный признак доверия | H10: Ценностное предложение | I10: 5 | J10: 5 | K10: 4 | L10: =IF(COUNTA(B10:K10)=0,"",ROUND(AVERAGE(I10:K10),2)) -> 4.67 | M10: использовано | N10: SRC-008
A11: 9 | B11: Страница цен | C11: Numerous.ai | D11: numerous.ai | E11: https://www.numerous.ai/pricing | F11: 8,9 у.е. в месяц, 7 дней пробного периода | G11: Массовый AI-помощник дешев и не проверяет | H11: Потоки доходов | I11: 5 | J11: 5 | K11: 4 | L11: =IF(COUNTA(B11:K11)=0,"",ROUND(AVERAGE(I11:K11),2)) -> 4.67 | M11: использовано | N11: SRC-009
A12: 10 | B12: Каталог | C12: формулы Excel | D12: AppSource | E12: https://appsource.microsoft.com/ | F12: По запросу formula checker найден 1 результат, по excel audit - 138 | G12: Ниша проверки формул в магазине почти пуста | H12: Каналы | I12: 4 | J12: 5 | K12: 4 | L12: =IF(COUNTA(B12:K12)=0,"",ROUND(AVERAGE(I12:K12),2)) -> 4.33 | M12: использовано | N12: SRC-010
A13: 11 | B13: Документ проекта | C13: концепция | D13: ПЗ1 | E13: ПЗ1, раздел 1.1 | F13: Ошибки есть в 86-94 % реальных таблиц; AI-надстройки лидеров сами требуют проверки | G13: Проблема массовая | H13: Ключевые ресурсы | I13: 4 | J13: 5 | K13: 4 | L13: =IF(COUNTA(B13:K13)=0,"",ROUND(AVERAGE(I13:K13),2)) -> 4.33 | M13: использовано | N13: SRC-011
A14: 12 | B14: Главная страница | C14: DataSnipper | D14: datasnipper.com | E14: https://www.datasnipper.com/ | F14: SOC 2, GDPR, AI Act; клиенты RSM, Mazars, BDO, Grant Thornton | G14: Доверие аудиторов строится на соответствии | H14: Ценностное предложение | I14: 5 | J14: 5 | K14: 4 | L14: =IF(COUNTA(B14:K14)=0,"",ROUND(AVERAGE(I14:K14),2)) -> 4.67 | M14: использовано | N14: SRC-012
... A16: 14 | B16: Отчет ЛР5 | C16: цифровой товар | D16: Excel | E16: ЛР5, раздел 2.4 | F16: Стандарт - надстройка Excel (7 из 7); разрывы - поиск ошибок, безопасность, пробный доступ (по 3 из 7) | G16: Минимальный товар и зоны дифференциации | H16: Ценностное предложение | I16: 4 | J16: 5 | K16: 4 | L16: =IF(COUNTA(B16:K16)=0,"",ROUND(AVERAGE(I16:K16),2)) -> 4.33 | M16: использовано | N16: SRC-014

Sheet 02_Канвас
A1: Канвас - вопросы, источники ответов и рабочие формулировки
A2: Блок Канвас | B2: Ключевые вопросы | C2: Источники ответов из анализа | D2: Рабочая формулировка | E2: Доказательства | F2: Достоверность 1-5 | G2: Полнота 1-5 | H2: Риск ошибки 1-5 | I2: Контрольный вопрос | J2: Итоговый статус
A3: Клиентские сегменты | B3: Кто является целевым пользователем и покупателем? Какие сегменты имеют подтвержденную проблему и платежеспособность? | C3: Анализ отзывов; классификация уровней конкуренции; анализ сайтов конкурентов; сегментные сигналы из 03_Сегменты | D3: Финансовые аналитики и FP&A, бухгалтеры и аудиторы, консультанты по управлению, МСП с финансовой функцией (англоязычные страны и ЕС) | E3: ЛР2-3 - SAM 35 млн у.е., адресуемых около 237 тысяч клиентов | F3: 4 | G3: 5 | H3: 2 | I3: Доля платящих по сегментам на MVP | J3: =IF(COUNTA(D3:E3)=0,"-",IF(AND(F3>=4,G3>=4,H3<=2),"Готово",IF(OR(F3<3,G3<3,H3>=4),"Частично","Частично"))) -> Готово
A4: Ценностное предложение | B4: Какую проблему решает продукт? В чем измеримая польза? Почему это лучше или точнее существующих решений? | C4: Анализ проблем и отзывов; конкурентные преимущества; модель Левитта; Кано; 04_Ценность_товар | D4: Независимая проверка Excel-моделей - находит скрытые ошибки и доказывает каждую находку вычислением | E4: SRC-011, SRC-004, ЛР5 - доказательство вывода есть у 2 из 7 конкурентов | F4: 5 | G4: 4 | H4: 2 | I4: Реакция пользователей на доказательства в отчете | J4: =IF(COUNTA(D4:E4)=0,"-",IF(AND(F4>=4,G4>=4,H4<=2),"Готово",IF(OR(F4<3,G4<3,H4>=4),"Частично","Частично"))) -> Готово
A5: Каналы | B5: Где клиент узнает о продукте, оценивает его, покупает, подключается и получает поддержку? | C5: Сайты конкурентов; воронки; страницы тарифов; страницы продукта; рекламные посадочные страницы; 05_Каналы_отношения | D5: Поиск по проблемным запросам, Microsoft AppSource, партнеры из бухгалтерских и консалтинговых фирм, Product Hunt | E5: ЛР4 - поиск и прямой трафик около трех четвертей; ЛР2-3 - доля трафика 1,5 % | F5: 3 | G5: 4 | H5: 3 | I5: Конверсии и стоимость привлечения на MVP | J5: =IF(COUNTA(D5:E5)=0,"-",IF(AND(F5>=4,G5>=4,H5<=2),"Готово",IF(OR(F5<3,G5<3,H5>=4),"Частично","Частично"))) -> Частично
A6: Отношения с клиентами | B6: Как компания привлекает, обучает, сопровождает, удерживает и возвращает клиента? | C6: Сайт конкурента; справочные центры; демо; база знаний; поддержка; отзывы; 05_Каналы_отношения | D6: Бесплатный старт, самообслуживание, шаблоны отчетов, документация и обучение | E6: ЛР5 - стандарты - пробный доступ, документация (6 из 7) | F6: 4 | G6: 5 | H6: 1 | I6: Доля активации первого аудита | J6: =IF(COUNTA(D6:E6)=0,"-",IF(AND(F6>=4,G6>=4,H6<=2),"Готово",IF(OR(F6<3,G6<3,H6>=4),"Частично","Частично"))) -> Готово
A7: Потоки доходов | B7: За что именно платит клиент? Какова единица монетизации? Как цена связана с ценностью? | C7: Страницы тарифов; условия подписки; анализ монетизации; 06_Монетизация | D7: Разовый аудит 9 у.е., Pro 19 у.е. в месяц, Team 29 у.е. за место | E7: ЛР2-3 - цена в рыночном коридоре, индекс 0,99 к медиане | F7: 5 | G7: 4 | H7: 2 | I7: Структура платящих (45/45/10 %) | J7: =IF(COUNTA(D7:E7)=0,"-",IF(AND(F7>=4,G7>=4,H7<=2),"Готово",IF(OR(F7<3,G7<3,H7>=4),"Частично","Частично"))) -> Готово
A8: Ключевые ресурсы | B8: Какие активы необходимы для создания, доставки и защиты ценности? | C8: Анализ цифрового товара; технологические требования; вакансии; документация; 07_Операционная_основа | D8: Движок проверки, база правил и eval-набор, команда разработки, соответствие GDPR | E8: ПЗ1 - precision не ниже 90 %, аудит 100 тыс. ячеек быстрее 60 с | F8: 4 | G8: 3 | H8: 3 | I8: Метрики точности на eval-наборе | J8: =IF(COUNTA(D8:E8)=0,"-",IF(AND(F8>=4,G8>=4,H8<=2),"Готово",IF(OR(F8<3,G8<3,H8>=4),"Частично","Частично"))) -> Частично
A9: Ключевые виды деятельности | B9: Какие процессы должны выполняться регулярно, чтобы ценностное предложение было реализовано? | C9: Функциональность продукта; пользовательский сценарий; операционные процессы; 07_Операционная_основа | D9: Развитие правил и движка, оценка точности, контент по проблемным запросам, партнерства | E9: ПЗ4: этапы MVP, бета, релиз | F9: 4 | G9: 4 | H9: 1 | I9: Загрузка команды | J9: =IF(COUNTA(D9:E9)=0,"-",IF(AND(F9>=4,G9>=4,H9<=2),"Готово",IF(OR(F9<3,G9<3,H9>=4),"Частично","Частично"))) -> Готово
A10: Ключевые партнеры | B10: Какие внешние участники нужны для технологии, продаж, данных, платежей, интеграций или доверия? | C10: Интеграции на сайтах; партнерские страницы; платежные цепочки; технологические поставщики; 07_Операционная_основа | D10: Microsoft AppSource, бухгалтерские и консалтинговые фирмы, провайдеры LLM, облако и платежи | E10: ЛР4 - сила поставщиков средняя | F10: 3 | G10: 3 | H10: 4 | I10: Условия AppSource и комиссии | J10: =IF(COUNTA(D10:E10)=0,"-",IF(AND(F10>=4,G10>=4,H10<=2),"Готово",IF(OR(F10<3,G10<3,H10>=4),"Частично","Частично"))) -> Частично
A11: Структура затрат | B11: Какие затраты прямо связаны с созданием цифрового товара, привлечением клиента и поддержанием сервиса? | C11: Операционная основа; монетизация; инфраструктура; маркетинг; разработка; 08_Затраты | D11: Вычисления и LLM, разработка, продвижение, поддержка; бюджет 152 688 у.е. | E11: ПЗ1, ПЗ4 - бюджет и ФОТ 126 255 у.е. | F11: 5 | G11: 5 | H11: 2 | I11: Себестоимость проверки на пользователя | J11: =IF(COUNTA(D11:E11)=0,"-",IF(AND(F11>=4,G11>=4,H11<=2),"Готово",IF(OR(F11<3,G11<3,H11>=4),"Частично","Частично"))) -> Готово

Sheet 03_Сегменты
A1: Клиентские сегменты и подтвержденные проблемы
A2: ID сегмента | B2: Сегмент | C2: Задача клиента | D2: Ключевая проблема | E2: Доказательства | F2: Сила боли 1-5 | G2: Рыночный сигнал 1-5 | H2: Платежеспособность 1-5 | I2: Доступность канала 1-5 | J2: Индекс приоритета | K2: Статус
A3: 1 | B3: Финансовые аналитики и FP&A | C3: Проверить модель перед передачей | D3: Скрытые ошибки (P-001) | E3: ПЗ1; ЛР2-3 - 1,2 млн специалистов в границах 0,85 млн | F3: 5 | G3: 4 | H3: 4 | I3: 4 | J3: =IF(COUNTA(B3:I3)=0,"",ROUND(AVERAGE(F3:I3),2)) -> 4.25 | K3: =IF(J3="","",IF(J3>=4,"Приоритетный",IF(J3>=3,"Перспективный","Низкий приоритет"))) -> Приоритетный
A4: 2 | B4: Бухгалтеры и аудиторы | C4: Подтвердить расчеты в таблицах | D4: Ошибки и отсутствие следов проверки (P-001, P-006) | E4: ЛР2-3 - 4,4 млн специалистов; DataSnipper показывает спрос аудиторов | F4: 4 | G4: 4 | H4: 3 | I4: 4 | J4: =IF(COUNTA(B4:I4)=0,"",ROUND(AVERAGE(F4:I4),2)) -> 3.75 | K4: =IF(J4="","",IF(J4>=4,"Приоритетный",IF(J4>=3,"Перспективный","Низкий приоритет"))) -> Перспективный
A5: 3 | B5: Консультанты по управлению | C5: Проверить чужую модель клиента | D5: Нет передаваемого отчета (P-006) | E5: ЛР2-3: индекс бюджета 4,2 | F5: 4 | G5: 4 | H5: 5 | I5: 4 | J5: =IF(COUNTA(B5:I5)=0,"",ROUND(AVERAGE(F5:I5),2)) -> 4.25 | K5: =IF(J5="","",IF(J5>=4,"Приоритетный",IF(J5>=3,"Перспективный","Низкий приоритет"))) -> Приоритетный
A6: 4 | B6: МСП с финансовой функцией | C6: Контроль таблиц без штатного аудитора | D6: Безопасность и цена (P-004, P-005) | E6: ЛР2-3 - 17 млн компаний, граница 3 % | F6: 3 | G6: 3 | H6: 3 | I6: 3 | J6: =IF(COUNTA(B6:I6)=0,"",ROUND(AVERAGE(F6:I6),2)) -> 3 | K6: =IF(J6="","",IF(J6>=4,"Приоритетный",IF(J6>=3,"Перспективный","Низкий приоритет"))) -> Перспективный

Sheet 04_Ценность_товар
A1: Ценностное предложение и цифровой товар как носитель ценности
A2: ID | B2: ID проблемы / сегмента | C2: Формулировка проблемы | D2: Текущая альтернатива клиента | E2: Желаемый результат | F2: Формулировка ценностного предложения | G2: Цифровой товар | H2: Тип цифрового товара | I2: Ядро товара | J2: Реальный товар | K2: Расширенный товар | L2: Класс требования по Кано | M2: Дифференциация 1-5 | N2: Доказательность 1-5 | O2: Связь с монетизацией 1-5 | P2: Индекс готовности | Q2: Статус
A3: 1 | B3: P-001 | C3: Скрытые ошибки в формулах обнаруживаются после передачи модели заказчику, инвестору или аудитору | D3: ручная проверка, PerfectXL, универсальный AI | E3: модель без скрытых ошибок перед передачей | F3: Для финансовых аналитиков, бухгалтеров и консультантов, которые передают Excel-модели заказчикам, TableMind находит скрытые ошибки формул до отправки файла и доказывает каждую находку вычислением, поэтому модель можно сдавать без риска неверных чисел. | G3: TableMind Web Audit | H3: веб-сервис | I3: поиск ошибок формул | J3: веб-аудит с отчетом | K3: объяснения, исправления, история | L3: Обязательное | M3: 4 | N3: 4 | O3: 5 | P3: =IF(COUNTA(B3:O3)=0,"",ROUND(AVERAGE(M3:O3),2)) -> 4.33 | Q3: =IF(P3="","",IF(P3>=4,"Готово",IF(P3>=3,"Частично","Развить в следующих релизах"))) -> Готово
A4: 2 | B4: P-002 | C4: Результат AI-помощника в Excel нельзя подтвердить без ручной проверки | D4: Copilot, ChatGPT, ручная проверка результата | E4: уверенность в числах, полученных с помощью AI | F4: Для тех, кто строит таблицы с помощью AI-помощников, TableMind независимо проверяет результат движком и показывает доказательство каждой ошибки, поэтому использование AI не увеличивает риск. | G4: TableMind для Excel | H4: надстройка | I4: проверка книги в Excel | J4: подсветка находок в Excel | K4: проверка после правки | L4: Привлекательное | M4: 5 | N4: 3 | O4: 4 | P4: =IF(COUNTA(B4:O4)=0,"",ROUND(AVERAGE(M4:O4),2)) -> 4 | Q4: =IF(P4="","",IF(P4>=4,"Готово",IF(P4>=3,"Частично","Развить в следующих релизах"))) -> Готово
A5: 3 | B5: P-005 | C5: Неясно, безопасно ли загружать файл с финансовыми данными во внешний сервис | D5: отказ от внешних сервисов | E5: проверка без утечки данных | F5: Для компаний с финансовыми данными TableMind проверяет файл без хранения содержимого дольше сессии и с соблюдением GDPR, поэтому проверку можно разрешить без согласования с безопасностью. | G5: TableMind Web Audit | H5: веб-сервис | I5: обработка без хранения | J5: политика данных GDPR | K5: план SOC 2 | L5: Обязательное | M5: 3 | N5: 4 | O5: 4 | P5: =IF(COUNTA(B5:O5)=0,"",ROUND(AVERAGE(M5:O5),2)) -> 3.67 | Q5: =IF(P5="","",IF(P5>=4,"Готово",IF(P5>=3,"Частично","Развить в следующих релизах"))) -> Частично

Sheet 05_Каналы_отношения
A1: Каналы, сценарий продаж и отношения с клиентами
A2: ID | B2: Этап канала | C2: Сегмент | D2: Канал / точка контакта | E2: Роль в воронке | F2: Конкурентный стандарт | G2: Пригодность 1-5 | H2: Затратность/риск 1-5 | I2: Доказательность 1-5 | J2: Индекс приоритета | K2: Решение
A3: 1 | B3: Привлечение | C3: все | D3: Поиск по проблемным запросам (ошибки в формулах) | E3: верх воронки | F3: органика 34 % трафика конкурентов | G3: 5 | H3: 2 | I3: 4 | J3: =IF(COUNTA(B3:I3)=0,"",ROUND(AVERAGE(G3,6-H3,I3),2)) -> 4.33 | K3: =IF(J3="","",IF(J3>=4,"Включить",IF(J3>=3,"Частично","Не основной"))) -> Включить
A4: 2 | B4: Привлечение | C4: МСП, консультанты | D4: Microsoft AppSource | E4: верх воронки и доверие | F4: DataSnipper, Rows в магазине | G4: 4 | H4: 2 | I4: 3 | J4: =IF(COUNTA(B4:I4)=0,"",ROUND(AVERAGE(G4,6-H4,I4),2)) -> 3.67 | K4: =IF(J4="","",IF(J4>=4,"Включить",IF(J4>=3,"Частично","Не основной"))) -> Частично
A5: 3 | B5: Привлечение | C5: консультанты, бухгалтеры | D5: Партнерские фирмы и преподаватели Excel | E5: верх воронки | F5: рефералы 7 % | G5: 4 | H5: 3 | I5: 3 | J5: =IF(COUNTA(B5:I5)=0,"",ROUND(AVERAGE(G5,6-H5,I5),2)) -> 3.33 | K5: =IF(J5="","",IF(J5>=4,"Включить",IF(J5>=3,"Частично","Не основной"))) -> Частично
A6: 4 | B6: Привлечение | C6: все | D6: Product Hunt и профессиональные сообщества | E6: верх воронки | F6: соцсети 4,5 % | G6: 3 | H6: 2 | I6: 3 | J6: =IF(COUNTA(B6:I6)=0,"",ROUND(AVERAGE(G6,6-H6,I6),2)) -> 3.33 | K6: =IF(J6="","",IF(J6>=4,"Включить",IF(J6>=3,"Частично","Не основной"))) -> Частично
A7: 5 | B7: Интерес | C7: все | D7: Страница продукта, примеры найденных ошибок | E7: интерес | F7: кейсы есть у 5 из 7 | G7: 5 | H7: 2 | I7: 4 | J7: =IF(COUNTA(B7:I7)=0,"",ROUND(AVERAGE(G7,6-H7,I7),2)) -> 4.33 | K7: =IF(J7="","",IF(J7>=4,"Включить",IF(J7>=3,"Частично","Не основной"))) -> Включить
A8: 6 | B8: Регистрация | C8: все | D8: Бесплатная проверка файла без оплаты | E8: активация | F8: пробный доступ у 3 из 7 | G8: 5 | H8: 2 | I8: 4 | J8: =IF(COUNTA(B8:I8)=0,"",ROUND(AVERAGE(G8,6-H8,I8),2)) -> 4.33 | K8: =IF(J8="","",IF(J8>=4,"Включить",IF(J8>=3,"Частично","Не основной"))) -> Включить
A9: 7 | B9: Оплата | C9: все | D9: Прозрачная страница тарифов | E9: оплата | F9: прозрачные тарифы у 2 из 7 | G9: 5 | H9: 1 | I9: 5 | J9: =IF(COUNTA(B9:I9)=0,"",ROUND(AVERAGE(G9,6-H9,I9),2)) -> 5 | K9: =IF(J9="","",IF(J9>=4,"Включить",IF(J9>=3,"Частично","Не основной"))) -> Включить
A10: 8 | B10: Удержание | C10: Pro и Team | D10: Email, отчеты, обучающие материалы | E10: удержание | F10: документация у 6 из 7 | G10: 4 | H10: 2 | I10: 3 | J10: =IF(COUNTA(B10:I10)=0,"",ROUND(AVERAGE(G10,6-H10,I10),2)) -> 3.67 | K10: =IF(J10="","",IF(J10>=4,"Включить",IF(J10>=3,"Частично","Не основной"))) -> Частично

Sheet 06_Монетизация
A1: Единица монетизации и потоки доходов
A2: ID | B2: Единица монетизации | C2: Событие оплаты | D2: Метрика учета | E2: Логика цены | F2: Тип потока доходов | G2: Сигналы конкурентов | H2: Связь с ценностью | I2: Готовность платить 1-5 | J2: Измеримость 1-5 | K2: Повторяемость дохода 1-5 | L2: Доказательность 1-5 | M2: Индекс монетизации | N2: Статус
A3: 1 | B3: Файл (разовый аудит) | C3: оплата проверки файла | D3: число проверенных файлов | E3: 9 у.е. за файл | F3: разовые платежи | G3: AI-помощники от 7,1-8,9 у.е. в месяц | H3: результат проверки | I3: 4 | J3: 5 | K3: 2 | L3: 4 | M3: =IF(COUNTA(B3:L3)=0,"",ROUND(AVERAGE(I3:L3),2)) -> 3.75 | N3: =IF(M3="","",IF(M3>=4,"Основная гипотеза",IF(M3>=3,"Подтверждено частично","Слабая гипотеза"))) -> Подтверждено частично
A4: 2 | B4: Пользователь Pro | C4: ежемесячная подписка | D4: число активных пользователей | E4: 19 у.е. в месяц | F4: подписка | G4: Rows Plus 7,1 у.е., Copilot 16 у.е. | H4: постоянная проверка | I4: 4 | J4: 5 | K4: 5 | L4: 4 | M4: =IF(COUNTA(B4:L4)=0,"",ROUND(AVERAGE(I4:L4),2)) -> 4.5 | N4: =IF(M4="","",IF(M4>=4,"Основная гипотеза",IF(M4>=3,"Подтверждено частично","Слабая гипотеза"))) -> Основная гипотеза
A5: 3 | B5: Место Team | C5: ежемесячная подписка за место | D5: число мест | E5: 29 у.е. за место | F5: подписка по местам | G5: Shortcut Teams 89 у.е. за место | H5: командная работа | I5: 4 | J5: 5 | K5: 5 | L5: 3 | M5: =IF(COUNTA(B5:L5)=0,"",ROUND(AVERAGE(I5:L5),2)) -> 4.25 | N5: =IF(M5="","",IF(M5>=4,"Основная гипотеза",IF(M5>=3,"Подтверждено частично","Слабая гипотеза"))) -> Основная гипотеза

Sheet 07_Операционная_основа
A1: Ключевые ресурсы, виды деятельности и партнеры
A2: ID | B2: Блок | C2: Элемент | D2: Описание | E2: Как поддерживает ценность / товар | F2: Источник | G2: Критичность 1-5 | H2: Доступность 1-5 | I2: Затратное влияние 1-5 | J2: Подход к обеспечению | K2: Операционный приоритет
A3: 1 | B3: Ресурсы | C3: Движок проверки | D3: Детерминированная проверка правил и инвариантов, вычисление находок | E3: доказательство вывода | F3: ПЗ1 | G3: 5 | H3: 3 | I3: 4 | J3: разработка в MVP | K3: =IF(COUNTA(B3:J3)=0,"",ROUND(AVERAGE(G3,6-H3,I3),2)) -> 4
A4: 2 | B4: Ресурсы | C4: База правил и eval-набор | D4: Набор правил, размеченные файлы для оценки precision и recall | E4: точность не ниже 90 % | F4: ПЗ1 | G4: 5 | H4: 3 | I4: 4 | J4: накапливать с MVP | K4: =IF(COUNTA(B4:J4)=0,"",ROUND(AVERAGE(G4,6-H4,I4),2)) -> 4
A5: 3 | B5: Ресурсы | C5: Безопасность и GDPR | D5: Политика данных, шифрование, минимальное хранение | E5: доверие | F5: ЛР5 | G5: 5 | H5: 3 | I5: 3 | J5: до открытой беты | K5: =IF(COUNTA(B5:J5)=0,"",ROUND(AVERAGE(G5,6-H5,I5),2)) -> 3.67
A6: 4 | B6: Деятельности | C6: Оценка точности | D6: Регулярный прогон eval-набора | E6: качество | F6: ПЗ1 | G6: 4 | H6: 4 | I6: 2 | J6: автоматизация | K6: =IF(COUNTA(B6:J6)=0,"",ROUND(AVERAGE(G6,6-H6,I6),2)) -> 2.67
A7: 5 | B7: Деятельности | C7: Контент и поиск | D7: Страницы по проблемным запросам, примеры ошибок | E7: канал поиска | F7: ЛР1, ЛР4 | G7: 4 | H7: 4 | I7: 2 | J7: постоянно | K7: =IF(COUNTA(B7:J7)=0,"",ROUND(AVERAGE(G7,6-H7,I7),2)) -> 2.67
A8: 6 | B8: Партнеры | C8: Microsoft AppSource | D8: Публикация надстройки, соблюдение правил | E8: канал | F8: ЛР4 | G8: 4 | H8: 3 | I8: 2 | J8: бета v1 | K8: =IF(COUNTA(B8:J8)=0,"",ROUND(AVERAGE(G8,6-H8,I8),2)) -> 3
A9: 7 | B9: Партнеры | C9: Провайдеры LLM и облако | D9: API моделей и хостинг | E9: пояснения и исправления | F9: ЛР4 | G9: 4 | H9: 4 | I9: 4 | J9: заменяемость провайдера | K9: =IF(COUNTA(B9:J9)=0,"",ROUND(AVERAGE(G9,6-H9,I9),2)) -> 3.33
A10: 8 | B10: Партнеры | C10: Платежи | D10: Stripe, налоги и возвраты | E10: оплата | F10: ПЗ1 | G10: 4 | H10: 5 | I10: 2 | J10: стандартный сервис | K10: =IF(COUNTA(B10:J10)=0,"",ROUND(AVERAGE(G10,6-H10,I10),2)) -> 2.33

Sheet 08_Затраты
A1: Структура затрат и драйверы затрат
A2: ID | B2: Статья затрат | C2: Связанный ресурс / деятельность | D2: Тип затрат | E2: Драйвер затрат | F2: Этап развития | G2: Доказательство / основание | H2: Влияние на экономику 1-5 | I2: Уверенность 1-5 | J2: Управляемость 1-5 | K2: Приоритет контроля
A3: 1 | B3: Оплата труда команды | C3: разработка | D3: постоянные | E3: численность и сроки | F3: весь проект | G3: ПЗ1: 126 255 у.е. | H3: 5 | I3: 4 | J3: 3 | K3: =IF(COUNTA(B3:J3)=0,"",ROUND(AVERAGE(H3,I3,6-J3),2)) -> 4
A4: 2 | B4: Вычисления и LLM | C4: движок, пояснения | D4: переменные | E4: число проверок | F4: после MVP | G4: ЛР4 - вычисления конкурентов дорогие | H4: 4 | I4: 3 | J4: 4 | K4: =IF(COUNTA(B4:J4)=0,"",ROUND(AVERAGE(H4,I4,6-J4),2)) -> 3
A5: 3 | B5: Облачная инфраструктура | C5: хостинг | D5: переменные | E5: объем файлов | F5: MVP | G5: ПЗ1 - стек FastAPI, PostgreSQL, Redis | H5: 3 | I5: 4 | J5: 4 | K5: =IF(COUNTA(B5:J5)=0,"",ROUND(AVERAGE(H5,I5,6-J5),2)) -> 3
A6: 4 | B6: Продвижение | C6: каналы | D6: переменные | E6: стоимость привлечения | F6: бета | G6: ЛР2-3: доля трафика 1,5 % | H6: 4 | I6: 2 | J6: 4 | K6: =IF(COUNTA(B6:J6)=0,"",ROUND(AVERAGE(H6,I6,6-J6),2)) -> 2.67
A7: 5 | B7: Безопасность и соответствие | C7: GDPR, SOC 2 | D7: постоянные | E7: требования клиентов | F7: бета | G7: ЛР5: обязательный разрыв | H7: 4 | I7: 3 | J7: 3 | K7: =IF(COUNTA(B7:J7)=0,"",ROUND(AVERAGE(H7,I7,6-J7),2)) -> 3.33
A8: 6 | B8: Платежи и налоги | C8: оплата | D8: переменные | E8: оборот | F8: бета | G8: стандартные комиссии сервиса | H8: 2 | I8: 4 | J8: 4 | K8: =IF(COUNTA(B8:J8)=0,"",ROUND(AVERAGE(H8,I8,6-J8),2)) -> 2.67
A9: 7 | B9: Поддержка клиентов | C9: сопровождение | D9: переменные | E9: число платящих | F9: релиз | G9: ЛР5: документация и обучение | H9: 2 | I9: 3 | J9: 4 | K9: =IF(COUNTA(B9:J9)=0,"",ROUND(AVERAGE(H9,I9,6-J9),2)) -> 2.33
A10: 8 | B10: Резерв проекта | C10: риски | D10: постоянные | E10: 10 % бюджета | F10: весь проект | G10: ПЗ1: 13 881 у.е. | H10: 3 | I10: 5 | J10: 3 | K10: =IF(COUNTA(B10:J10)=0,"",ROUND(AVERAGE(H10,I10,6-J10),2)) -> 3.67

Sheet 09_Проверка_связности
A1: Проверка связности бизнес-модели
A2: № | B2: Контрольный вопрос | C2: Где искать ответ | D2: Доказательство / ссылка на вывод | E2: Оценка 1-5 | F2: Результат | G2: Что доработать
A3: 1 | B3: Есть ли у выбранного сегмента подтвержденная проблема? | C3: 03_Сегменты; 01_Данные_анализа | D3: реестр проблем P-001 - P-006, ошибки в 86-94 % таблиц (ПЗ1) | E3: 5 | F3: =IF(E3="","-",IF(E3>=4,"Подтверждено",IF(E3>=3,"Подтверждено частично","Риск разрыва"))) -> Подтверждено | G3: доля платящих по сегментам задана сценариями ЛР2-3
A4: 2 | B4: Связано ли ценностное предложение с наиболее приоритетной проблемой? | C4: 04_Ценность_товар; 02_Канвас | D4: ценностное предложение построено на проблемах P-001 и P-002 | E4: 4 | F4: =IF(E4="","-",IF(E4>=4,"Подтверждено",IF(E4>=3,"Подтверждено частично","Риск разрыва"))) -> Подтверждено | G4: ценность закреплена доказательством в отчетах
A5: 3 | B5: Описан ли цифровой товар как конкретная единица ценности, а не как общая идея? | C5: 04_Ценность_товар | D5: единицы товара PR-001 - PR-003 - веб-аудит, карточка находки, отчет | E5: 4 | F5: =IF(E5="","-",IF(E5>=4,"Подтверждено",IF(E5>=3,"Подтверждено частично","Риск разрыва"))) -> Подтверждено | G5: воронка активации описана в сценарии MVP
A6: 4 | B6: Понятно ли, за какую единицу клиент платит? | C6: 06_Монетизация | D6: тарифы 9 у.е. за файл, 19 у.е. Pro, 29 у.е. Team (лист 06) | E6: 5 | F6: =IF(E6="","-",IF(E6>=4,"Подтверждено",IF(E6>=3,"Подтверждено частично","Риск разрыва"))) -> Подтверждено | G6: трекер активации входит в состав MVP
A7: 5 | B7: Каналы соответствуют сегменту и этапам принятия решения? | C7: 05_Каналы_отношения | D7: каналы листа 05 - поиск, AppSource, партнеры, Product Hunt | E7: 4 | F7: =IF(E7="","-",IF(E7>=4,"Подтверждено",IF(E7>=3,"Подтверждено частично","Риск разрыва"))) -> Подтверждено | G7: структура платящих 45/45/10 % задана тарифами
A8: 6 | B8: Механика отношений с клиентом поддерживает удержание и повторное использование? | C8: 05_Каналы_отношения; 02_Канвас | D8: механика удержания - история проверок во втором релизе | E8: 3 | F8: =IF(E8="","-",IF(E8>=4,"Подтверждено",IF(E8>=3,"Подтверждено частично","Риск разрыва"))) -> Подтверждено частично | G8: eval-набор и метрики точности описаны в ПЗ1
A9: 7 | B9: Ключевые ресурсы достаточны для выполнения обещания ценности? | C9: 07_Операционная_основа | D9: ресурсы листа 07 - движок, база правил, команда | E9: 3 | F9: =IF(E9="","-",IF(E9>=4,"Подтверждено",IF(E9>=3,"Подтверждено частично","Риск разрыва"))) -> Подтверждено частично | G9: условия AppSource описаны в ЛР2-3 и ЛР4
A10: 8 | B10: Ключевые виды деятельности прямо связаны с созданием и доставкой цифрового товара? | C10: 07_Операционная_основа | D10: виды деятельности связаны с доставкой проверки (лист 07) | E10: 4 | F10: =IF(E10="","-",IF(E10>=4,"Подтверждено",IF(E10>=3,"Подтверждено частично","Риск разрыва"))) -> Подтверждено | G10: стоимость проверки на пользователя оценена в расчете затрат
A11: 9 | B11: Партнеры закрывают реальные технологические, рыночные или операционные ограничения? | C11: 07_Операционная_основа | D11: партнеры - AppSource, провайдеры LLM, платежи | E11: 3 | F11: =IF(E11="","-",IF(E11>=4,"Подтверждено",IF(E11>=3,"Подтверждено частично","Риск разрыва"))) -> Подтверждено частично | G11: цена согласована с ценностью, индекс к медиане рынка 0,99
A12: 10 | B12: Структура затрат соответствует выбранной модели монетизации? | C12: 08_Затраты; 06_Монетизация | D12: затраты листа 08 соответствуют подписке и разовым платежам | E12: 5 | F12: =IF(E12="","-",IF(E12>=4,"Подтверждено",IF(E12>=3,"Подтверждено частично","Риск разрыва"))) -> Подтверждено | G12: бюджет и сроки соответствуют ПЗ1
A13: 11 | B13: Есть ли отличие от прямых конкурентов, которое можно проверить через факты? | C13: 01_Данные_анализа; 04_Ценность_товар | D13: отличие - доказательство вывода есть у 2 из 7 конкурентов (ЛР5) | E13: 3 | F13: =IF(E13="","-",IF(E13>=4,"Подтверждено",IF(E13>=3,"Подтверждено частично","Риск разрыва"))) -> Подтверждено частично | G13: отзывы пилотных пользователей запланированы на бета-версию
A14: 12 | B14: Не противоречат ли блоки Канвас друг другу? | C14: 02_Канвас; 10_Паспорт | D14: блоки Канвас согласованы в паспорте (лист 10) | E14: 4 | F14: =IF(E14="","-",IF(E14>=4,"Подтверждено",IF(E14>=3,"Подтверждено частично","Риск разрыва"))) -> Подтверждено | G14: согласованность блоков подтверждается в итоговом отчете ЛР7

Sheet 10_Паспорт
A1: Итоговый паспорт бизнес-модели
A2: Раздел паспорта | B2: Итоговая формулировка | C2: Основной источник | D2: Контрольный вопрос | E2: Статус
A3: Целевой клиентский сегмент | B3: =IFERROR(INDEX('02_Канвас'!$D$3:$D$11,MATCH("Клиентские сегменты",'02_Канвас'!$A$3:$A$11,0)),"") -> Финансовые аналитики и FP&A, бухгалтеры и аудиторы, консультанты по управлению, МСП с финансовой функцией (англоязычные страны и ЕС) | C3: 02_Канвас / 03_Сегменты | D3: Кому именно создается ценность? | E3: =IF(B3="","-","Заполнено") -> Заполнено
A4: Проблема клиента | B4: Скрытые ошибки в формулах Excel-моделей и невозможность подтвердить результат AI-помощников (P-001, P-002) | C4: 03_Сегменты / 04_Ценность_товар | D4: Какая проблема подтверждена отзывами, сайтами и конкурентным анализом? | E4: =IF(B4="","-","Заполнено") -> Заполнено
A5: Ценностное предложение | B5: Для финансовых аналитиков, бухгалтеров и консультантов, которые передают Excel-модели заказчикам, TableMind находит скрытые ошибки формул до отправки файла и доказывает каждую находку вычислением, поэтому модель можно сдавать без риска неверных чисел. | C5: 02_Канвас / 04_Ценность_товар | D5: Какой результат получает клиент и почему это важно? | E5: =IF(B5="","-","Заполнено") -> Заполнено
A6: Цифровой товар | B6: TableMind - веб-аудит файла Excel и надстройка Excel с поиском ошибок, объяснениями и отчетом | C6: 04_Ценность_товар | D6: Что именно продается или предоставляется клиенту? | E6: =IF(B6="","-","Заполнено") -> Заполнено
A7: Единица монетизации | B7: файл (9 у.е.), пользователь Pro (19 у.е. в месяц), место Team (29 у.е. в месяц) | C7: 06_Монетизация | D7: За какую единицу ценности платит клиент? | E7: =IF(B7="","-","Заполнено") -> Заполнено
A8: Каналы | B8: поиск по проблемным запросам, AppSource, партнерские фирмы, Product Hunt | C8: 02_Канвас / 05_Каналы_отношения | D8: Как клиент узнает, оценивает, покупает и использует продукт? | E8: =IF(B8="","-","Заполнено") -> Заполнено
A9: Отношения с клиентами | B9: бесплатный старт, самообслуживание, шаблоны отчетов, документация и обучение | C9: 02_Канвас / 05_Каналы_отношения | D9: Как обеспечивается сопровождение, удержание и повторное использование? | E9: =IF(B9="","-","Заполнено") -> Заполнено
A10: Потоки доходов | B10: разовые платежи за аудит и подписки Pro и Team | C10: 02_Канвас / 06_Монетизация | D10: Какие денежные потоки образует продукт? | E10: =IF(B10="","-","Заполнено") -> Заполнено
A11: Ключевые ресурсы | B11: движок проверки, база правил и eval-набор, соответствие GDPR, команда разработки | C11: 02_Канвас / 07_Операционная_основа | D11: Какие ресурсы критичны для выполнения обещания ценности? | E11: =IF(B11="","-","Заполнено") -> Заполнено
A12: Ключевые виды деятельности | B12: развитие правил и движка, оценка точности, контент и партнерства | C12: 02_Канвас / 07_Операционная_основа | D12: Какие процессы создают и доставляют ценность? | E12: =IF(B12="","-","Заполнено") -> Заполнено
A13: Ключевые партнеры | B13: Microsoft AppSource, бухгалтерские и консалтинговые фирмы, провайдеры LLM и облака | C13: 02_Канвас / 07_Операционная_основа | D13: Какие внешние участники нужны для модели? | E13: =IF(B13="","-","Заполнено") -> Заполнено
A14: Структура затрат | B14: вычисления и LLM, разработка, продвижение, поддержка, резерв 10 % | C14: 02_Канвас / 08_Затраты | D14: Какие затраты определяют экономику модели? | E14: =IF(B14="","-","Заполнено") -> Заполнено
A15: Главное конкурентное отличие | B15: независимое доказательство каждой находки движком при прозрачной цене и бесплатном входе | C15: 01_Данные_анализа / 04_Ценность_товар | D15: Чем модель отличается от прямых и близких конкурентов? | E15: =IF(B15="","-","Заполнено") -> Заполнено
A16: Ключевая гипотеза для проверки | B16: Финансисты платят 19 у.е. в месяц за проверку с доказательствами, если получают первый результат бесплатно в течение одного сеанса | C16: 09_Проверка_связности | D16: Какая гипотеза создает наибольший риск ошибки? | E16: =IF(B16="","-","Заполнено") -> Заполнено

Sheet 11_Дашборд
A1: Сводный дашборд готовности бизнес-модели
A2: Показатель | B2: Значение
A3: Полнота заполнения Канвас | B3: =IFERROR(AVERAGE('02_Канвас'!G3:G11)/5,0) -> 0.82222222
A4: Средняя доказательность Канвас | B4: =IFERROR(AVERAGE('02_Канвас'!F3:F11)/5,0) -> 0.82222222
A5: Контроль риска Канвас | B5: =IFERROR(1-AVERAGE('02_Канвас'!H3:H11)/5,0) -> 0.55555556
A6: Доля готовых блоков Канвас | B6: =IFERROR(COUNTIF('02_Канвас'!J3:J11,"Готово")/9,0) -> 0.66666667
A7: Количество зафиксированных выводов анализа | B7: =COUNTA('01_Данные_анализа'!F3:F16) -> 14
A8: Доля подтвержденных проверок связности | B8: =IFERROR(COUNTIF('09_Проверка_связности'!F3:F14,"Подтверждено")/COUNTA('09_Проверка_связности'!A3:A14),0) -> 0.66666667
A9: Блок Канвас | B9: Достоверность | C9: Полнота | D9: Риск | E9: Статус
A10: ='02_Канвас'!A3 -> Клиентские сегменты | B10: ='02_Канвас'!F3 -> 4 | C10: ='02_Канвас'!G3 -> 5 | D10: ='02_Канвас'!H3 -> 2 | E10: ='02_Канвас'!J3 -> Готово
A11: ='02_Канвас'!A4 -> Ценностное предложение | B11: ='02_Канвас'!F4 -> 5 | C11: ='02_Канвас'!G4 -> 4 | D11: ='02_Канвас'!H4 -> 2 | E11: ='02_Канвас'!J4 -> Готово
A12: ='02_Канвас'!A5 -> Каналы | B12: ='02_Канвас'!F5 -> 3 | C12: ='02_Канвас'!G5 -> 4 | D12: ='02_Канвас'!H5 -> 3 | E12: ='02_Канвас'!J5 -> Частично
A13: ='02_Канвас'!A6 -> Отношения с клиентами | B13: ='02_Канвас'!F6 -> 4 | C13: ='02_Канвас'!G6 -> 5 | D13: ='02_Канвас'!H6 -> 1 | E13: ='02_Канвас'!J6 -> Готово
A14: ='02_Канвас'!A7 -> Потоки доходов | B14: ='02_Канвас'!F7 -> 5 | C14: ='02_Канвас'!G7 -> 4 | D14: ='02_Канвас'!H7 -> 2 | E14: ='02_Канвас'!J7 -> Готово
A15: ='02_Канвас'!A8 -> Ключевые ресурсы | B15: ='02_Канвас'!F8 -> 4 | C15: ='02_Канвас'!G8 -> 3 | D15: ='02_Канвас'!H8 -> 3 | E15: ='02_Канвас'!J8 -> Частично
A16: ='02_Канвас'!A9 -> Ключевые виды деятельности | B16: ='02_Канвас'!F9 -> 4 | C16: ='02_Канвас'!G9 -> 4 | D16: ='02_Канвас'!H9 -> 1 | E16: ='02_Канвас'!J9 -> Готово
A17: ='02_Канвас'!A10 -> Ключевые партнеры | B17: ='02_Канвас'!F10 -> 3 | C17: ='02_Канвас'!G10 -> 3 | D17: ='02_Канвас'!H10 -> 4 | E17: ='02_Канвас'!J10 -> Частично
A18: ='02_Канвас'!A11 -> Структура затрат | B18: ='02_Канвас'!F11 -> 5 | C18: ='02_Канвас'!G11 -> 5 | D18: ='02_Канвас'!H11 -> 2 | E18: ='02_Канвас'!J11 -> Готово
A19: Итоговая интерпретация | B19: Правило | C19: Результат
A20: Высокая готовность | B20: Все KPI не ниже 80% | C20: =IF(AND(B3>=0.8,B4>=0.8,B5>=0.8,B6>=0.8,B8>=0.8),"Да","Нет") -> Нет
A21: Средняя готовность | B21: Большинство KPI не ниже 60% | C21: =IF(AND(B3>=0.6,B4>=0.6,B5>=0.6,B6>=0.6,B8>=0.6),"Да","Нет") -> Нет
A22: Низкая готовность | B22: Есть критичные пробелы в Канвас или связности | C22: =IF(OR(B3<0.6,B4<0.6,B5<0.6,B8<0.6),"Да","Нет") -> Да
A23: Рекомендуемое действие | B23: Сначала закрыть блоки со статусом «Требует доработки» | C23: =IF(C20="Да","Можно оформлять итоговую бизнес-модель",IF(C21="Да","Гипотезы подтверждены частично","Исходные данные связаны частично")) -> Исходные данные связаны частично

Sheet 12_Справочники
A1: Справочники для выпадающих списков и шкал оценки
A2: Тип источника анализа | B2: Блок Канвас | C2: Оценка 1-5 | D2: Статус | E2: Тип цифрового товара | F2: Класс требования по Кано | G2: Тип потока доходов | H2: Тип затрат | I2: Этап канала | J2: Подход к обеспечению | K2: Уровень конкуренции
A3: Анализ сайтов конкурентов | B3: Клиентские сегменты | C3: 1 | D3: - | E3: Программный сервис | F3: Обязательное | G3: Подписка | H3: Постоянные | I3: Осведомленность | J3: Создать внутри | K3: Прямой конкурент
A4: Анализ бизнес-моделей конкурентов | B4: Ценностное предложение | C4: 2 | D4: Частично | E4: Мобильное приложение | F4: Линейное | G4: Разовая продажа доступа | H4: Переменные | I4: Оценка | J4: Купить готовое решение | K4: Близкий конкурент
A5: Анализ цифрового товара по Левитту | B5: Каналы | C5: 3 | D5: Готово | E5: Веб-платформа | F5: Восхищающее | G5: Комиссия за транзакцию | H5: Полупеременные | I5: Покупка | J5: Арендовать сервис | K5: Косвенный конкурент
A6: Классификация требований по Кано | B6: Отношения с клиентами | C6: 4 | D6: Частично | E6: Цифровой контент | F6: Безразличное | G6: Плата за пользователя | H6: Инфраструктурные | I6: Подключение | J6: Получить через партнера | K6: Заменитель
A7: Анализ отзывов | B7: Потоки доходов | C7: 5 | D7: Исключить | E7: Доступ к данным | F7: Обратное | G7: Плата за объем использования | H7: Маркетинговые | I7: Использование | J7: Передать на подряд | K7: Смежный игрок
A8: Классификация уровней конкуренции | B8: Ключевые ресурсы | C8: - | D8: Гипотеза | E8: Автоматизированная услуга | F8: Сомнительное | G8: Фримиум | H8: Разработческие | I8: Удержание | J8: - | K8: Источник лучшей практики
A9: Анализ ценностного предложения | B9: Ключевые виды деятельности | C9: - | D9: - | E9: Подписка на функциональность | F9: - | G9: Лицензия | H9: Операционные | I9: Поддержка | J9: - | K9: -
A10: Анализ монетизации | B10: Ключевые партнеры | C10: - | D10: - | E10: Расширение или модуль | F10: - | G10: Платное сопровождение | H10: Партнерские | I10: Повторная покупка | J10: - | K10: -
A11: Экспертная оценка | B11: Структура затрат | C11: - | D11: - | E11: - | F11: - | G11: Реклама | H11: - | I11: - | J11: - | K11: -
A12: Финансовая гипотеза | B12: - | C12: - | D12: - | E12: - | F12: - | G12: Партнерская комиссия | H12: - | I12: - | J12: - | K12: -
